[
  {
    "id": "x_2048947772053946746",
    "platform": "X",
    "username": "@sanrio_oshikatu",
    "content": "＼⚠️本日4/28(火)入荷📣🆕／ 「サンリオキャラクターズ なかよしペアスイング」 ガチャガチャ入荷したよ🥹💖 今日大型店舗へ入荷始まってるようなので明日以降取扱店舗増えていきそう🙆‍♀️ これで今月のバンダイさんの新作ガチャ入荷はラスト✨ 5月はどんなの出るか楽しみだね🥹🩷… https://t.co/WQkvrducpb pic.twitter.com/06ZgBGqkFh — サンリオ推し活部🌈 (@sanrio_oshikatu) April 28, 2026",
    "url": "https://x.com/sanrio_oshikatu/status/2048947772053946746",
    "postedAt": "2026-04-28T14:28:00.304117+00:00",
    "matchedKeyword": "サンリオ ガチャ 新作"
  },
  {
    "id": "x_2048974172047749325",
    "platform": "X",
    "username": "@SM_seal_room",
    "content": "ボンボンドロップシール祭り こめいちさんも来たー！！ ⤵⤵ https://t.co/GILMQq2hQw 【PR】 サンリオキャラクターズ もじ この後キャンセル分来る可能性大あり 購入ルール確認お忘れなく！ サンリオボンドロ ミニチュアチャーム 新作ガチャ サンリオキャラクター大賞2026 しまむら イオン シル活 pic.twitter.com/M8bpTL48sI — シャインマスカット｜シール情報局 (@SM_seal_room) April 28, 2026",
    "url": "https://x.com/SM_seal_room/status/2048974172047749325",
    "postedAt": "2026-04-28T14:28:00.304117+00:00",
    "matchedKeyword": "サンリオ ガチャ 新作"
  },
  {
    "id": "x_2048760893358645450",
    "platform": "X",
    "username": "@T87W2nB8G783953",
    "content": "7月再販予定だから早めに見ておきたい！ リプ欄見てね❤️ 🔻A-TOYS 楽天市場店 https://t.co/W8tJ7DH7Ht ボンボンドロップシール ボンドロ 再入荷 抽選 入荷情報 しまむら ドンキ イオン 新宿 池袋 コンビニ ヨドバシ サンリオ ガチャ ガシャポン カプセルトイ 新作 予約 再販 全4種セット — 美香の推しセレクト (@T87W2nB8G783953) April 27, 2026",
    "url": "https://x.com/T87W2nB8G783953/status/2048760893358645450",
    "postedAt": "2026-04-28T14:28:00.304117+00:00",
    "matchedKeyword": "サンリオ ガチャ 新作"
  },
  {
    "id": "x_2048749968832565339",
    "platform": "X",
    "username": "@DailyPicks12065",
    "content": "7月再販予定で今から話題🥹 売り切れ前に見ておきたい 🔻A-TOYS 楽天市場店 https://t.co/RlXbZyuTEt ボンボンドロップシール ボンドロ 再入荷 抽選 入荷情報 しまむら ドンキ イオン 新宿 池袋 コンビニ ヨドバシ サンリオ ガチャ ガシャポン カプセルトイ 新作 予約 再販 全4種セット — さくら | Daily Picks (@DailyPicks12065) April 27, 2026",
    "url": "https://x.com/DailyPicks12065/status/2048749968832565339",
    "postedAt": "2026-04-28T14:28:00.304117+00:00",
    "matchedKeyword": "サンリオ ガチャ 新作"
  },
  {
    "id": "x_2048749869159141565",
    "platform": "X",
    "username": "@BeautyS52760",
    "content": "ドロップ風チャームでバッグにも付けたい🥰 🔻A-TOYS 楽天市場店 https://t.co/qm35DJVSzC ボンボンドロップシール ボンドロ 再入荷 抽選 入荷情報 しまむら ドンキ イオン 新宿 池袋 コンビニ ヨドバシ サンリオ ガチャ ガシャポン カプセルトイ 新作 予約 再販 全4種セット — Rina’s Beauty Roo (@BeautyS52760) April 27, 2026",
    "url": "https://x.com/BeautyS52760/status/2048749869159141565",
    "postedAt": "2026-04-28T14:28:00.304117+00:00",
    "matchedKeyword": "サンリオ ガチャ 新作"
  },
  {
    "id": "x_2048749733729227259",
    "platform": "X",
    "username": "@fit_aya38729",
    "content": "7月再販予定だから今が狙い目！ リプ欄見てね❤️ 🔻A-TOYS 楽天市場店 https://t.co/uAjBil0zXq ボンボンドロップシール ボンドロ 再入荷 抽選 入荷情報 しまむら ドンキ イオン 新宿 池袋 コンビニ ヨドバシ サンリオ ガチャ ガシャポン カプセルトイ 新作 予約 再販 全4種セット — Aya Fit Life (@fit_aya38729) April 27, 2026",
    "url": "https://x.com/fit_aya38729/status/2048749733729227259",
    "postedAt": "2026-04-28T14:28:00.304117+00:00",
    "matchedKeyword": "サンリオ ガチャ 新作"
  },
  {
    "id": "x_2048744113164706113",
    "platform": "X",
    "username": "@finds_love18706",
    "content": "7月再販予定だから今のうちに要チェック！ リプ欄見てね❤️ 🔻A-TOYS 楽天市場店 https://t.co/zJSWecQ5G3 ボンボンドロップシール ボンドロ 再入荷 抽選 入荷情報 しまむら ドンキ イオン 新宿 池袋 コンビニ ヨドバシ サンリオ ガチャ ガシャポン カプセルトイ 新作 予約 再販 全4種セット — みゆき | Lovely Finds (@finds_love18706) April 27, 2026",
    "url": "https://x.com/finds_love18706/status/2048744113164706113",
    "postedAt": "2026-04-28T14:28:00.304117+00:00",
    "matchedKeyword": "サンリオ ガチャ 新作"
  },
  {
    "id": "x_2048738110109061407",
    "platform": "X",
    "username": "@trend_diar67661",
    "content": "キティちゃん×ミミィちゃんの双子感が可愛すぎる💗 🔻A-TOYS 楽天市場店 https://t.co/1QG64n0Ogm ボンボンドロップシール ボンドロ 再入荷 抽選 入荷情報 しまむら ドンキ イオン 新宿 池袋 コンビニ ヨドバシ サンリオ ガチャ ガシャポン カプセルトイ 新作 予約 再販 全4種セット — あやの | Trend Diary (@trend_diar67661) April 27, 2026",
    "url": "https://x.com/trend_diar67661/status/2048738110109061407",
    "postedAt": "2026-04-28T14:28:00.304117+00:00",
    "matchedKeyword": "サンリオ ガチャ 新作"
  },
  {
    "id": "x_2048685581950148881",
    "platform": "X",
    "username": "@SM_seal_room",
    "content": "きゅるるんシール定価祭り！ ▶ https://t.co/OPuqyMRPID 【PR】 喫茶アラモードも👍 ↓ ひとつ＆ふたつ前と同ショップ これも うるちゅるポップシール も プチドロ も サンリオボンドロ ミニチュアチャーム みたいに 新作ガチャ作ってほしい！！ しまむら イオン ロフト 西松屋 バースデイ シル活 pic.twitter.com/ZWNdYDKwig — シャインマスカット｜シール情報局 (@SM_seal_room) April 27, 2026",
    "url": "https://x.com/SM_seal_room/status/2048685581950148881",
    "postedAt": "2026-04-28T14:28:00.304117+00:00",
    "matchedKeyword": "サンリオ ガチャ 新作"
  },
  {
    "id": "x_2048664555648413731",
    "platform": "X",
    "username": "@SM_seal_room",
    "content": "ポチッちゃおさん シール祭り来てます⤵⤵ https://t.co/qnoR4zvRGg 【PR】 モンチッチ おぱんちゅうさぎ ほっぺちゃん サンリオ 日焼けキティまみれ etc 推しキャラいる人は要チェックです👍 しかし 新作ガチャ サンリオボンドロ ミニチュアチャーム も たまごっちカスタムキーリング も厳しすぎる😨 — シャインマスカット｜シール情報局 (@SM_seal_room) April 27, 2026",
    "url": "https://x.com/SM_seal_room/status/2048664555648413731",
    "postedAt": "2026-04-28T14:28:00.304117+00:00",
    "matchedKeyword": "サンリオ ガチャ 新作"
  },
  {
    "id": "x_2048635718852059166",
    "platform": "X",
    "username": "@hiyori14300",
    "content": "[PR] 【6月予約】サンリオキャラクターズ ミニえんぴつけずり 全5種 コンプリートセット ガチャ 楽天で買える🌟 🔻ホビー雑貨のチャチャ https://t.co/ca01FGVXUd ハローキティ、コロコロクリリン、マロンクリーム、タキシードサム、けろけろけろっぴ🥰 ガチャガチャ カプセルトイ 入荷 新作 — ひより🤍🤍 (@hiyori14300) April 27, 2026",
    "url": "https://x.com/hiyori14300/status/2048635718852059166",
    "postedAt": "2026-04-28T14:28:00.304117+00:00",
    "matchedKeyword": "サンリオ ガチャ 新作"
  },
  {
    "id": "x_2048622632254484492",
    "platform": "X",
    "username": "@sgtenmonkan1",
    "content": "✨新作ガチャ入荷✨ お問い合わせありました ・サンリオ BONBON DROP ミニチュアチャーム 入荷いたしました！ 数に限りがありますのでゲットしたい方はお早めに！ #サープラ天文館あそびタウン pic.twitter.com/G3w2F02EdG — サープラ天文館あそびタウン (@sgtenmonkan1) April 27, 2026",
    "url": "https://x.com/sgtenmonkan1/status/2048622632254484492",
    "postedAt": "2026-04-28T14:28:00.304117+00:00",
    "matchedKeyword": "サンリオ ガチャ 新作"
  },
  {
    "id": "x_2048551801990054107",
    "platform": "X",
    "username": "@SM_seal_room",
    "content": "新作！定価！ クーリア ボンドロシェイカーキット ▶ https://t.co/DQVkeyqb8Z 【PR】 ボンボンドロップシール → めじるしチャーム GW 前 雨の月曜日 朝から びしょ濡れ 😢 もこれ買えたぜ👍 新作ガチャ サンリオボンドロ ミニチュアチャーム セブンイレブン ちいかわボンドロ も欲しい🤤 Amazon 8:56 — シャインマスカット｜シール情報局 (@SM_seal_room) April 26, 2026",
    "url": "https://x.com/SM_seal_room/status/2048551801990054107",
    "postedAt": "2026-04-28T14:28:00.304117+00:00",
    "matchedKeyword": "サンリオ ガチャ 新作"
  },
  {
    "id": "x_2048373172723212351",
    "platform": "X",
    "username": "@SM_seal_room",
    "content": "急ぎ―！！ プチドロ＋シール帳セット ▶ https://t.co/h7VbHfiuvF 【PR】 今日は、みずいろドロップ💧 カミオジャパン 西松屋 しまむら セブンイレブン ちいかｗあボンドロ ローソン サンリオ ファミマ クーリア イオン アプリ ミニチュアチャーム 新作ガチャ シールバインダー サンスター文具 シル活 — シャインマスカット｜シール情報局 (@SM_seal_room) April 26, 2026",
    "url": "https://x.com/SM_seal_room/status/2048373172723212351",
    "postedAt": "2026-04-28T14:28:00.304117+00:00",
    "matchedKeyword": "サンリオ ガチャ 新作"
  },
  {
    "id": "x_2048358937066688830",
    "platform": "X",
    "username": "@EBI___EBI__",
    "content": "久々のガチャの横動画投稿しましたっ(`・ω・´) 【🌈SNSで話題沸騰🌈の４月下旬発売｜新作サンリオガチャ】 BONBONDROPミニチュアチャーム｜１回300円 ～思い（？）を語りながら開封しましたっ🫡～ #ガチャガチャ https://t.co/N8m1Qu1b73 — EBI🍤 (@EBI___EBI__) April 26, 2026",
    "url": "https://x.com/EBI___EBI__/status/2048358937066688830",
    "postedAt": "2026-04-28T14:28:00.304117+00:00",
    "matchedKeyword": "サンリオ ガチャ 新作"
  },
  {
    "id": "x_2048335178582667654",
    "platform": "X",
    "username": "@SM_seal_room",
    "content": "サンリオボンドロ入り 大人気福袋再入荷来てるよー！ ▶ https://t.co/6GltqTYVk0 【PR】 サンリオキャラクター大賞2026 サンリオキャラクターズ ボンボンドロップシール ミニチュアチャーム めじるしアクセサリー 新作ガチャ しまむら バースデイ イオン アプリ ローソン シル活 pic.twitter.com/Dz0ncymzXP — シャインマスカット｜シール情報局 (@SM_seal_room) April 26, 2026",
    "url": "https://x.com/SM_seal_room/status/2048335178582667654",
    "postedAt": "2026-04-28T14:28:00.304117+00:00",
    "matchedKeyword": "サンリオ ガチャ 新作"
  },
  {
    "id": "x_2048324719452262564",
    "platform": "X",
    "username": "@hiyori14300",
    "content": "[PR] 【7月再販予定】 サンリオキャラクターズ なかよしドロップチャーム 【全4種セット】 楽天で買える✨ 🔻A-TOYS 楽天市場店 https://t.co/Q9gSfoWZsv ハローキティ×ハローミミィも、マイメロディ×クロミも、並ぶだけで気分上がる💗 ガチャガチャ ガチャ ガシャポン カプセルトイ 入荷 新作 — ひより🤍🤍 (@hiyori14300) April 26, 2026",
    "url": "https://x.com/hiyori14300/status/2048324719452262564",
    "postedAt": "2026-04-28T14:28:00.304117+00:00",
    "matchedKeyword": "サンリオ ガチャ 新作"
  },
  {
    "id": "x_2048322306783752687",
    "platform": "X",
    "username": "@SM_seal_room",
    "content": "送料無料715円！ ラメきらクリスタルシール ▶ https://t.co/aoqTPgaoug 【PR】 今 メロクロ 買えます👍 サンスター文具 12柄 昨日は ディズニー ちいかわ 再販あり サンリオキャラクターズ サンリオキャラクター大賞2026 マック ハッピーセット しまむら バースデイ 西松屋 新作ガチャ イオン シル活 pic.twitter.com/qnEAwW4yC7 — シャインマスカット｜シール情報局 (@SM_seal_room) April 26, 2026",
    "url": "https://x.com/SM_seal_room/status/2048322306783752687",
    "postedAt": "2026-04-28T14:28:00.304117+00:00",
    "matchedKeyword": "サンリオ ガチャ 新作"
  },
  {
    "id": "x_2048280920189284513",
    "platform": "X",
    "username": "@Play_Gacha",
    "content": "🌸4月ガチャ サンリオキャラクターズ新作まとめ🌸 ₊˚✧꒰🗨️紹介しているアイテムはこちら ꒱✧˚₊ ＼ぷっくり立体的でかわいいラバーマスコット第2弾！🍎／ ◒サンリオキャラクターズ メルヘン工房おなまえホルダーミニチュアラバーマスコット2 ＼ぷっくり立体的なラバーマスコット第1弾！♥／… pic.twitter.com/RfSNTYyzhX — タカラトミーアーツ ガチャ公式 (@Play_Gacha) April 26, 2026",
    "url": "https://x.com/Play_Gacha/status/2048280920189284513",
    "postedAt": "2026-04-28T14:28:00.304117+00:00",
    "matchedKeyword": "サンリオ ガチャ 新作"
  },
  {
    "id": "x_2048210956006863056",
    "platform": "X",
    "username": "@SM_seal_room",
    "content": "うるちゅるポップシール祭り ▶ https://t.co/hKZ8XMPrw0 【PR】 シブヤ文房具さんで本日も開催中🙌 今 シナモロール、この後ほか来る可能性大 サンリオキャラクターズ サンリオキャラクター大賞2026 マック マクド ハッピーセット 新作ガチャ サンリオボンドロ ミニチュアチャーム しまむら シール配布 — シャインマスカット｜シール情報局 (@SM_seal_room) April 26, 2026",
    "url": "https://x.com/SM_seal_room/status/2048210956006863056",
    "postedAt": "2026-04-28T14:28:00.304117+00:00",
    "matchedKeyword": "サンリオ ガチャ 新作"
  },
  {
    "id": "x_2047890193311805934",
    "platform": "X",
    "username": "@shinku_seal",
    "content": "クロミベビー💘うるちゅる ▶ https://t.co/YJgMN468vR 【PR】 シブヤさん今日も うるちゅるポップシール 祭り開催中！ この後も続く可能性大、要チェックです。 ぷっくりシール ボンボンドロップシール サンリオキャラクターズ ミニチュアチャーム 新作ガチャ サンリオキャラクター大賞 シル活 — 神紅｜シール情報局 (@shinku_seal) April 25, 2026",
    "url": "https://x.com/shinku_seal/status/2047890193311805934",
    "postedAt": "2026-04-28T14:28:00.304117+00:00",
    "matchedKeyword": "サンリオ ガチャ 新作"
  },
  {
    "id": "x_2047889697868054963",
    "platform": "X",
    "username": "@SM_seal_room",
    "content": "送料無料破格在庫！急げー！ クロミベビー💘うるちゅる ▶ https://t.co/cOaDD0GB8F 【PR】 うるちゅるポップシール プチドロ きゅるるんシール も サンリオボンドロ ボンボンドロップミニチュアチャーム みたいな 新作ガチャ作ってもらえたら絶対買います！！しまむら イオン 西松屋 バースデイ シル活 — シャインマスカット｜シール情報局 (@SM_seal_room) April 25, 2026",
    "url": "https://x.com/SM_seal_room/status/2047889697868054963",
    "postedAt": "2026-04-28T14:28:00.304117+00:00",
    "matchedKeyword": "サンリオ ガチャ 新作"
  },
  {
    "id": "x_2047874725691683024",
    "platform": "X",
    "username": "@shinku_seal",
    "content": "ボンボンドロップシール 4月第3週今週売ってる場所だった店 ⤵ https://t.co/CabvAgEqBQ 実店舗・通販別まとめ 動物園 水族館限定 新作販売も クーリア セブンイレブン ちいかわ ボンドロ サンリオ 新作ガチャ ミニチュアチャーム ディズニー コラボ しまむら イオ ンヨドバシ 西松屋 HANZ シル活 — 神紅｜シール情報局 (@shinku_seal) April 25, 2026",
    "url": "https://x.com/shinku_seal/status/2047874725691683024",
    "postedAt": "2026-04-28T14:28:00.304117+00:00",
    "matchedKeyword": "サンリオ ガチャ 新作"
  },
  {
    "id": "x_2047861754433306776",
    "platform": "X",
    "username": "@SM_seal_room",
    "content": "送料無料破格在庫！ うるちゅるポップシール パワパフ ▶ https://t.co/PtakYh9sBz 【PR】 今日のシブヤさんは サンリオキャラクターズ 以外の日？！ セブンイレブン ちいかわボンドロ 新作ガチャミニチュアチャーム しまむら バースデイ全部行きたい パワーパフガールズ カートゥーンネットワーク — シャインマスカット｜シール情報局 (@SM_seal_room) April 25, 2026",
    "url": "https://x.com/SM_seal_room/status/2047861754433306776",
    "postedAt": "2026-04-28T14:28:00.304117+00:00",
    "matchedKeyword": "サンリオ ガチャ 新作"
  },
  {
    "id": "x_2047856907722109379",
    "platform": "X",
    "username": "@narimi85",
    "content": "サンリオ新作ガチャ、これは争奪戦の予感…。ボンボンドロップミニチュアチャーム、はぴだんぶいも入ってるの熱くない？見つけたら即回すべき！ ハローキティ ポムポムプリン はぴだんぶい — なりみ (@narimi85) April 25, 2026",
    "url": "https://x.com/narimi85/status/2047856907722109379",
    "postedAt": "2026-04-28T14:28:00.304117+00:00",
    "matchedKeyword": "サンリオ ガチャ 新作"
  },
  {
    "id": "x_2047855821338620379",
    "platform": "X",
    "username": "@pindonde",
    "content": "サンリオ ガチャ 新作 に関する投稿",
    "url": "https://x.com/pindonde/status/2047855821338620379",
    "postedAt": "2026-04-28T14:28:00.304117+00:00",
    "matchedKeyword": "サンリオ ガチャ 新作"
  },
  {
    "id": "x_2047851898921975963",
    "platform": "X",
    "username": "@SM_seal_room",
    "content": "サンリオ ガチャ 新作 に関する投稿",
    "url": "https://x.com/SM_seal_room/status/2047851898921975963",
    "postedAt": "2026-04-28T14:28:00.304117+00:00",
    "matchedKeyword": "サンリオ ガチャ 新作"
  },
  {
    "id": "x_2047843823603311042",
    "platform": "X",
    "username": "@piyoko14500",
    "content": "サンリオ ガチャ 新作 に関する投稿",
    "url": "https://x.com/piyoko14500/status/2047843823603311042",
    "postedAt": "2026-04-28T14:28:00.304117+00:00",
    "matchedKeyword": "サンリオ ガチャ 新作"
  },
  {
    "id": "x_2047824523777720497",
    "platform": "X",
    "username": "@SM_seal_room",
    "content": "サンリオ ガチャ 新作 に関する投稿",
    "url": "https://x.com/SM_seal_room/status/2047824523777720497",
    "postedAt": "2026-04-28T14:28:00.304117+00:00",
    "matchedKeyword": "サンリオ ガチャ 新作"
  },
  {
    "id": "x_2047794746186518956",
    "platform": "X",
    "username": "@SM_seal_room",
    "content": "サンリオ ガチャ 新作 に関する投稿",
    "url": "https://x.com/SM_seal_room/status/2047794746186518956",
    "postedAt": "2026-04-28T14:28:00.304117+00:00",
    "matchedKeyword": "サンリオ ガチャ 新作"
  },
  {
    "id": "x_2047651441662411092",
    "platform": "X",
    "username": "@lily_flower10",
    "content": "サンリオ ガチャ 新作 に関する投稿",
    "url": "https://x.com/lily_flower10/status/2047651441662411092",
    "postedAt": "2026-04-28T14:28:00.304117+00:00",
    "matchedKeyword": "サンリオ ガチャ 新作"
  },
  {
    "id": "x_2047640044547215629",
    "platform": "X",
    "username": "@SM_seal_room",
    "content": "サンリオ ガチャ 新作 に関する投稿",
    "url": "https://x.com/SM_seal_room/status/2047640044547215629",
    "postedAt": "2026-04-28T14:28:00.304117+00:00",
    "matchedKeyword": "サンリオ ガチャ 新作"
  },
  {
    "id": "x_2047634339526300058",
    "platform": "X",
    "username": "@SM_seal_room",
    "content": "サンリオ ガチャ 新作 に関する投稿",
    "url": "https://x.com/SM_seal_room/status/2047634339526300058",
    "postedAt": "2026-04-28T14:28:00.304117+00:00",
    "matchedKeyword": "サンリオ ガチャ 新作"
  },
  {
    "id": "x_2047629742233571555",
    "platform": "X",
    "username": "@SM_seal_room",
    "content": "サンリオ ガチャ 新作 に関する投稿",
    "url": "https://x.com/SM_seal_room/status/2047629742233571555",
    "postedAt": "2026-04-28T14:28:00.304117+00:00",
    "matchedKeyword": "サンリオ ガチャ 新作"
  },
  {
    "id": "x_2047611515600359521",
    "platform": "X",
    "username": "@shinku_seal",
    "content": "サンリオ ガチャ 新作 に関する投稿",
    "url": "https://x.com/shinku_seal/status/2047611515600359521",
    "postedAt": "2026-04-28T14:28:00.304117+00:00",
    "matchedKeyword": "サンリオ ガチャ 新作"
  },
  {
    "id": "x_2047599683699396736",
    "platform": "X",
    "username": "@SM_seal_room",
    "content": "サンリオ ガチャ 新作 に関する投稿",
    "url": "https://x.com/SM_seal_room/status/2047599683699396736",
    "postedAt": "2026-04-28T14:28:00.304117+00:00",
    "matchedKeyword": "サンリオ ガチャ 新作"
  },
  {
    "id": "x_2047597976022024276",
    "platform": "X",
    "username": "@SM_seal_room",
    "content": "サンリオ ガチャ 新作 に関する投稿",
    "url": "https://x.com/SM_seal_room/status/2047597976022024276",
    "postedAt": "2026-04-28T14:28:00.304117+00:00",
    "matchedKeyword": "サンリオ ガチャ 新作"
  },
  {
    "id": "x_2047582549971701765",
    "platform": "X",
    "username": "@shinku_seal",
    "content": "サンリオ ガチャ 新作 に関する投稿",
    "url": "https://x.com/shinku_seal/status/2047582549971701765",
    "postedAt": "2026-04-28T14:28:00.304117+00:00",
    "matchedKeyword": "サンリオ ガチャ 新作"
  },
  {
    "id": "x_2047566710845436114",
    "platform": "X",
    "username": "@WJwx1If4C022680",
    "content": "サンリオ ガチャ 新作 に関する投稿",
    "url": "https://x.com/WJwx1If4C022680/status/2047566710845436114",
    "postedAt": "2026-04-28T14:28:00.304117+00:00",
    "matchedKeyword": "サンリオ ガチャ 新作"
  },
  {
    "id": "x_2048970074720260145",
    "platform": "X",
    "username": "@shinkyogoku150",
    "content": "たまごっち ガチャ に関する投稿",
    "url": "https://x.com/shinkyogoku150/status/2048970074720260145",
    "postedAt": "2026-04-28T14:27:57.704523+00:00",
    "matchedKeyword": "たまごっち ガチャ"
  },
  {
    "id": "x_2049133223448543256",
    "platform": "X",
    "username": "@li_0v0_",
    "content": "たまごっち ガチャ に関する投稿",
    "url": "https://x.com/li_0v0_/status/2049133223448543256",
    "postedAt": "2026-04-28T14:27:57.704523+00:00",
    "matchedKeyword": "たまごっち ガチャ"
  },
  {
    "id": "x_2049133162022965737",
    "platform": "X",
    "username": "@y_dona_hsj",
    "content": "たまごっち ガチャ に関する投稿",
    "url": "https://x.com/y_dona_hsj/status/2049133162022965737",
    "postedAt": "2026-04-28T14:27:57.704523+00:00",
    "matchedKeyword": "たまごっち ガチャ"
  },
  {
    "id": "x_2049132893465960757",
    "platform": "X",
    "username": "@milkruban31",
    "content": "たまごっち ガチャ に関する投稿",
    "url": "https://x.com/milkruban31/status/2049132893465960757",
    "postedAt": "2026-04-28T14:27:57.704523+00:00",
    "matchedKeyword": "たまごっち ガチャ"
  },
  {
    "id": "x_2049132741388820833",
    "platform": "X",
    "username": "@nananabananatim",
    "content": "たまごっち ガチャ に関する投稿",
    "url": "https://x.com/nananabananatim/status/2049132741388820833",
    "postedAt": "2026-04-28T14:27:57.704523+00:00",
    "matchedKeyword": "たまごっち ガチャ"
  },
  {
    "id": "x_2049132186612515096",
    "platform": "X",
    "username": "@xA_Kyanxxxx",
    "content": "たまごっち ガチャ に関する投稿",
    "url": "https://x.com/xA_Kyanxxxx/status/2049132186612515096",
    "postedAt": "2026-04-28T14:27:57.704523+00:00",
    "matchedKeyword": "たまごっち ガチャ"
  },
  {
    "id": "x_2049132132279427580",
    "platform": "X",
    "username": "@kisumaitan",
    "content": "たまごっち ガチャ に関する投稿",
    "url": "https://x.com/kisumaitan/status/2049132132279427580",
    "postedAt": "2026-04-28T14:27:57.704523+00:00",
    "matchedKeyword": "たまごっち ガチャ"
  },
  {
    "id": "x_2049131837386330473",
    "platform": "X",
    "username": "@RyoheMomo_ii27",
    "content": "たまごっち ガチャ に関する投稿",
    "url": "https://x.com/RyoheMomo_ii27/status/2049131837386330473",
    "postedAt": "2026-04-28T14:27:57.704523+00:00",
    "matchedKeyword": "たまごっち ガチャ"
  },
  {
    "id": "x_2049131170181571064",
    "platform": "X",
    "username": "@nananabananatim",
    "content": "たまごっち ガチャ に関する投稿",
    "url": "https://x.com/nananabananatim/status/2049131170181571064",
    "postedAt": "2026-04-28T14:27:57.704523+00:00",
    "matchedKeyword": "たまごっち ガチャ"
  },
  {
    "id": "x_2049130979651178661",
    "platform": "X",
    "username": "@hc7gpr",
    "content": "たまごっち ガチャ に関する投稿",
    "url": "https://x.com/hc7gpr/status/2049130979651178661",
    "postedAt": "2026-04-28T14:27:57.704523+00:00",
    "matchedKeyword": "たまごっち ガチャ"
  },
  {
    "id": "x_2049130936827281426",
    "platform": "X",
    "username": "@chii3o__",
    "content": "たまごっち ガチャ に関する投稿",
    "url": "https://x.com/chii3o__/status/2049130936827281426",
    "postedAt": "2026-04-28T14:27:57.704523+00:00",
    "matchedKeyword": "たまごっち ガチャ"
  },
  {
    "id": "x_2049130458093687220",
    "platform": "X",
    "username": "@satan86336209",
    "content": "たまごっち ガチャ に関する投稿",
    "url": "https://x.com/satan86336209/status/2049130458093687220",
    "postedAt": "2026-04-28T14:27:57.704523+00:00",
    "matchedKeyword": "たまごっち ガチャ"
  },
  {
    "id": "x_2049130203813998982",
    "platform": "X",
    "username": "@satan86336209",
    "content": "たまごっち ガチャ に関する投稿",
    "url": "https://x.com/satan86336209/status/2049130203813998982",
    "postedAt": "2026-04-28T14:27:57.704523+00:00",
    "matchedKeyword": "たまごっち ガチャ"
  },
  {
    "id": "x_2049129579105939821",
    "platform": "X",
    "username": "@maro_no_trade",
    "content": "たまごっち ガチャ に関する投稿",
    "url": "https://x.com/maro_no_trade/status/2049129579105939821",
    "postedAt": "2026-04-28T14:27:57.704523+00:00",
    "matchedKeyword": "たまごっち ガチャ"
  },
  {
    "id": "x_2049129573087088730",
    "platform": "X",
    "username": "@li_0v0_",
    "content": "たまごっち ガチャ に関する投稿",
    "url": "https://x.com/li_0v0_/status/2049129573087088730",
    "postedAt": "2026-04-28T14:27:57.704523+00:00",
    "matchedKeyword": "たまごっち ガチャ"
  },
  {
    "id": "x_2049129512739467694",
    "platform": "X",
    "username": "@asaaaaa__3156",
    "content": "たまごっち ガチャ に関する投稿",
    "url": "https://x.com/asaaaaa__3156/status/2049129512739467694",
    "postedAt": "2026-04-28T14:27:57.704523+00:00",
    "matchedKeyword": "たまごっち ガチャ"
  },
  {
    "id": "x_2049129253997027421",
    "platform": "X",
    "username": "@hikachuu4",
    "content": "たまごっち ガチャ に関する投稿",
    "url": "https://x.com/hikachuu4/status/2049129253997027421",
    "postedAt": "2026-04-28T14:27:57.704523+00:00",
    "matchedKeyword": "たまごっち ガチャ"
  },
  {
    "id": "x_2049128410946117921",
    "platform": "X",
    "username": "@li_0v0_",
    "content": "たまごっち ガチャ に関する投稿",
    "url": "https://x.com/li_0v0_/status/2049128410946117921",
    "postedAt": "2026-04-28T14:27:57.704523+00:00",
    "matchedKeyword": "たまごっち ガチャ"
  },
  {
    "id": "x_2049128187054170586",
    "platform": "X",
    "username": "@3o3o_1o12",
    "content": "たまごっち ガチャ に関する投稿",
    "url": "https://x.com/3o3o_1o12/status/2049128187054170586",
    "postedAt": "2026-04-28T14:27:57.704523+00:00",
    "matchedKeyword": "たまごっち ガチャ"
  },
  {
    "id": "x_2049127772019433733",
    "platform": "X",
    "username": "@22kittyz",
    "content": "たまごっち ガチャ に関する投稿",
    "url": "https://x.com/22kittyz/status/2049127772019433733",
    "postedAt": "2026-04-28T14:27:57.704523+00:00",
    "matchedKeyword": "たまごっち ガチャ"
  },
  {
    "id": "x_2049127468901302634",
    "platform": "X",
    "username": "@icghm_",
    "content": "たまごっち ガチャ に関する投稿",
    "url": "https://x.com/icghm_/status/2049127468901302634",
    "postedAt": "2026-04-28T14:27:57.704523+00:00",
    "matchedKeyword": "たまごっち ガチャ"
  },
  {
    "id": "x_2049126541804941513",
    "platform": "X",
    "username": "@3o3_____",
    "content": "たまごっち ガチャ に関する投稿",
    "url": "https://x.com/3o3_____/status/2049126541804941513",
    "postedAt": "2026-04-28T14:27:57.704523+00:00",
    "matchedKeyword": "たまごっち ガチャ"
  },
  {
    "id": "x_2049125599529345509",
    "platform": "X",
    "username": "@KAi22t",
    "content": "たまごっち ガチャ に関する投稿",
    "url": "https://x.com/KAi22t/status/2049125599529345509",
    "postedAt": "2026-04-28T14:27:57.704523+00:00",
    "matchedKeyword": "たまごっち ガチャ"
  },
  {
    "id": "x_2049125332293464303",
    "platform": "X",
    "username": "@hani2c2",
    "content": "たまごっち ガチャ に関する投稿",
    "url": "https://x.com/hani2c2/status/2049125332293464303",
    "postedAt": "2026-04-28T14:27:57.704523+00:00",
    "matchedKeyword": "たまごっち ガチャ"
  },
  {
    "id": "x_2049125321568661997",
    "platform": "X",
    "username": "@Lumpy_0505xxx",
    "content": "たまごっち ガチャ に関する投稿",
    "url": "https://x.com/Lumpy_0505xxx/status/2049125321568661997",
    "postedAt": "2026-04-28T14:27:57.704523+00:00",
    "matchedKeyword": "たまごっち ガチャ"
  },
  {
    "id": "x_2049125284583280785",
    "platform": "X",
    "username": "@REleei",
    "content": "たまごっち ガチャ に関する投稿",
    "url": "https://x.com/REleei/status/2049125284583280785",
    "postedAt": "2026-04-28T14:27:57.704523+00:00",
    "matchedKeyword": "たまごっち ガチャ"
  },
  {
    "id": "x_2049125265444643073",
    "platform": "X",
    "username": "@Kawaii___cha",
    "content": "たまごっち ガチャ に関する投稿",
    "url": "https://x.com/Kawaii___cha/status/2049125265444643073",
    "postedAt": "2026-04-28T14:27:57.704523+00:00",
    "matchedKeyword": "たまごっち ガチャ"
  },
  {
    "id": "x_2049124459504980346",
    "platform": "X",
    "username": "@Qoo_torihikky",
    "content": "たまごっち ガチャ に関する投稿",
    "url": "https://x.com/Qoo_torihikky/status/2049124459504980346",
    "postedAt": "2026-04-28T14:27:57.704523+00:00",
    "matchedKeyword": "たまごっち ガチャ"
  },
  {
    "id": "x_2049123984118354368",
    "platform": "X",
    "username": "@amaama_nana",
    "content": "たまごっち ガチャ に関する投稿",
    "url": "https://x.com/amaama_nana/status/2049123984118354368",
    "postedAt": "2026-04-28T14:27:57.704523+00:00",
    "matchedKeyword": "たまごっち ガチャ"
  },
  {
    "id": "x_2049123912840278173",
    "platform": "X",
    "username": "@blindboxxange",
    "content": "たまごっち ガチャ に関する投稿",
    "url": "https://x.com/blindboxxange/status/2049123912840278173",
    "postedAt": "2026-04-28T14:27:57.704523+00:00",
    "matchedKeyword": "たまごっち ガチャ"
  },
  {
    "id": "x_2049123862483521577",
    "platform": "X",
    "username": "@tw112132",
    "content": "たまごっち ガチャ に関する投稿",
    "url": "https://x.com/tw112132/status/2049123862483521577",
    "postedAt": "2026-04-28T14:27:57.704523+00:00",
    "matchedKeyword": "たまごっち ガチャ"
  },
  {
    "id": "x_2049123668543078705",
    "platform": "X",
    "username": "@ra_sa_rinon",
    "content": "たまごっち ガチャ に関する投稿",
    "url": "https://x.com/ra_sa_rinon/status/2049123668543078705",
    "postedAt": "2026-04-28T14:27:57.704523+00:00",
    "matchedKeyword": "たまごっち ガチャ"
  },
  {
    "id": "x_2049123625140441574",
    "platform": "X",
    "username": "@yuri_1205613",
    "content": "たまごっち ガチャ に関する投稿",
    "url": "https://x.com/yuri_1205613/status/2049123625140441574",
    "postedAt": "2026-04-28T14:27:57.704523+00:00",
    "matchedKeyword": "たまごっち ガチャ"
  },
  {
    "id": "x_2049123212412551418",
    "platform": "X",
    "username": "@riii_tw02",
    "content": "たまごっち ガチャ に関する投稿",
    "url": "https://x.com/riii_tw02/status/2049123212412551418",
    "postedAt": "2026-04-28T14:27:57.704523+00:00",
    "matchedKeyword": "たまごっち ガチャ"
  },
  {
    "id": "x_2049123202547511506",
    "platform": "X",
    "username": "@xihai_guide817",
    "content": "たまごっち ガチャ に関する投稿",
    "url": "https://x.com/xihai_guide817/status/2049123202547511506",
    "postedAt": "2026-04-28T14:27:57.704523+00:00",
    "matchedKeyword": "たまごっち ガチャ"
  },
  {
    "id": "x_2049123058762543521",
    "platform": "X",
    "username": "@yDQBZMzsR432963",
    "content": "たまごっち ガチャ に関する投稿",
    "url": "https://x.com/yDQBZMzsR432963/status/2049123058762543521",
    "postedAt": "2026-04-28T14:27:57.704523+00:00",
    "matchedKeyword": "たまごっち ガチャ"
  },
  {
    "id": "x_2049122996800098326",
    "platform": "X",
    "username": "@__1026_yu",
    "content": "たまごっち ガチャ に関する投稿",
    "url": "https://x.com/__1026_yu/status/2049122996800098326",
    "postedAt": "2026-04-28T14:27:57.704523+00:00",
    "matchedKeyword": "たまごっち ガチャ"
  },
  {
    "id": "x_2049122901224521835",
    "platform": "X",
    "username": "@eof3sk000",
    "content": "たまごっち ガチャ に関する投稿",
    "url": "https://x.com/eof3sk000/status/2049122901224521835",
    "postedAt": "2026-04-28T14:27:57.704523+00:00",
    "matchedKeyword": "たまごっち ガチャ"
  },
  {
    "id": "x_2049122679970742616",
    "platform": "X",
    "username": "@__R__08100902",
    "content": "たまごっち ガチャ に関する投稿",
    "url": "https://x.com/__R__08100902/status/2049122679970742616",
    "postedAt": "2026-04-28T14:27:57.704523+00:00",
    "matchedKeyword": "たまごっち ガチャ"
  },
  {
    "id": "x_2049121256721785308",
    "platform": "X",
    "username": "@otori_tanaka",
    "content": "たまごっち ガチャ に関する投稿",
    "url": "https://x.com/otori_tanaka/status/2049121256721785308",
    "postedAt": "2026-04-28T14:27:57.704523+00:00",
    "matchedKeyword": "たまごっち ガチャ"
  },
  {
    "id": "x_2048598180431069359",
    "platform": "X",
    "username": "@prestagepress",
    "content": "カプセルトイ 新商品 に関する投稿",
    "url": "https://x.com/prestagepress/status/2048598180431069359",
    "postedAt": "2026-04-28T14:27:55.461179+00:00",
    "matchedKeyword": "カプセルトイ 新商品"
  },
  {
    "id": "x_2049111555959406615",
    "platform": "X",
    "username": "@Cpla_chayamachi",
    "content": "カプセルトイ 新商品 に関する投稿",
    "url": "https://x.com/Cpla_chayamachi/status/2049111555959406615",
    "postedAt": "2026-04-28T14:27:55.461179+00:00",
    "matchedKeyword": "カプセルトイ 新商品"
  },
  {
    "id": "x_2049110011583009009",
    "platform": "X",
    "username": "@Cpla51",
    "content": "カプセルトイ 新商品 に関する投稿",
    "url": "https://x.com/Cpla51/status/2049110011583009009",
    "postedAt": "2026-04-28T14:27:55.461179+00:00",
    "matchedKeyword": "カプセルトイ 新商品"
  },
  {
    "id": "x_2049107474943492209",
    "platform": "X",
    "username": "@cplahakataguchi",
    "content": "カプセルトイ 新商品 に関する投稿",
    "url": "https://x.com/cplahakataguchi/status/2049107474943492209",
    "postedAt": "2026-04-28T14:27:55.461179+00:00",
    "matchedKeyword": "カプセルトイ 新商品"
  },
  {
    "id": "x_2049104789951348845",
    "platform": "X",
    "username": "@cplahakataguchi",
    "content": "カプセルトイ 新商品 に関する投稿",
    "url": "https://x.com/cplahakataguchi/status/2049104789951348845",
    "postedAt": "2026-04-28T14:27:55.461179+00:00",
    "matchedKeyword": "カプセルトイ 新商品"
  },
  {
    "id": "x_2049104009592770764",
    "platform": "X",
    "username": "@Cpla51",
    "content": "カプセルトイ 新商品 に関する投稿",
    "url": "https://x.com/Cpla51/status/2049104009592770764",
    "postedAt": "2026-04-28T14:27:55.461179+00:00",
    "matchedKeyword": "カプセルトイ 新商品"
  },
  {
    "id": "x_2049103757074731393",
    "platform": "X",
    "username": "@cplahakataguchi",
    "content": "カプセルトイ 新商品 に関する投稿",
    "url": "https://x.com/cplahakataguchi/status/2049103757074731393",
    "postedAt": "2026-04-28T14:27:55.461179+00:00",
    "matchedKeyword": "カプセルトイ 新商品"
  },
  {
    "id": "x_2049102525387931878",
    "platform": "X",
    "username": "@cplahakataguchi",
    "content": "カプセルトイ 新商品 に関する投稿",
    "url": "https://x.com/cplahakataguchi/status/2049102525387931878",
    "postedAt": "2026-04-28T14:27:55.461179+00:00",
    "matchedKeyword": "カプセルトイ 新商品"
  },
  {
    "id": "x_2049101734870716588",
    "platform": "X",
    "username": "@Cpla51",
    "content": "カプセルトイ 新商品 に関する投稿",
    "url": "https://x.com/Cpla51/status/2049101734870716588",
    "postedAt": "2026-04-28T14:27:55.461179+00:00",
    "matchedKeyword": "カプセルトイ 新商品"
  },
  {
    "id": "x_2049096136426979576",
    "platform": "X",
    "username": "@Cplakamata",
    "content": "カプセルトイ 新商品 に関する投稿",
    "url": "https://x.com/Cplakamata/status/2049096136426979576",
    "postedAt": "2026-04-28T14:27:55.461179+00:00",
    "matchedKeyword": "カプセルトイ 新商品"
  },
  {
    "id": "x_2049095738903457874",
    "platform": "X",
    "username": "@Cplakamata",
    "content": "カプセルトイ 新商品 に関する投稿",
    "url": "https://x.com/Cplakamata/status/2049095738903457874",
    "postedAt": "2026-04-28T14:27:55.461179+00:00",
    "matchedKeyword": "カプセルトイ 新商品"
  },
  {
    "id": "x_2049095147888267755",
    "platform": "X",
    "username": "@Cplakamata",
    "content": "カプセルトイ 新商品 に関する投稿",
    "url": "https://x.com/Cplakamata/status/2049095147888267755",
    "postedAt": "2026-04-28T14:27:55.461179+00:00",
    "matchedKeyword": "カプセルトイ 新商品"
  },
  {
    "id": "x_2049095114942025947",
    "platform": "X",
    "username": "@Cpla51",
    "content": "カプセルトイ 新商品 に関する投稿",
    "url": "https://x.com/Cpla51/status/2049095114942025947",
    "postedAt": "2026-04-28T14:27:55.461179+00:00",
    "matchedKeyword": "カプセルトイ 新商品"
  },
  {
    "id": "x_2049095035044639009",
    "platform": "X",
    "username": "@Cplakamata",
    "content": "カプセルトイ 新商品 に関する投稿",
    "url": "https://x.com/Cplakamata/status/2049095035044639009",
    "postedAt": "2026-04-28T14:27:55.461179+00:00",
    "matchedKeyword": "カプセルトイ 新商品"
  },
  {
    "id": "x_2049094919604805815",
    "platform": "X",
    "username": "@Cplakamata",
    "content": "カプセルトイ 新商品 に関する投稿",
    "url": "https://x.com/Cplakamata/status/2049094919604805815",
    "postedAt": "2026-04-28T14:27:55.461179+00:00",
    "matchedKeyword": "カプセルトイ 新商品"
  },
  {
    "id": "x_2049094830312263888",
    "platform": "X",
    "username": "@Cplakamata",
    "content": "カプセルトイ 新商品 に関する投稿",
    "url": "https://x.com/Cplakamata/status/2049094830312263888",
    "postedAt": "2026-04-28T14:27:55.461179+00:00",
    "matchedKeyword": "カプセルトイ 新商品"
  },
  {
    "id": "x_2049094735969866060",
    "platform": "X",
    "username": "@Cplakamata",
    "content": "カプセルトイ 新商品 に関する投稿",
    "url": "https://x.com/Cplakamata/status/2049094735969866060",
    "postedAt": "2026-04-28T14:27:55.461179+00:00",
    "matchedKeyword": "カプセルトイ 新商品"
  },
  {
    "id": "x_2049094615299760289",
    "platform": "X",
    "username": "@Cplakamata",
    "content": "カプセルトイ 新商品 に関する投稿",
    "url": "https://x.com/Cplakamata/status/2049094615299760289",
    "postedAt": "2026-04-28T14:27:55.461179+00:00",
    "matchedKeyword": "カプセルトイ 新商品"
  },
  {
    "id": "x_2049094423276073020",
    "platform": "X",
    "username": "@Cplakamata",
    "content": "カプセルトイ 新商品 に関する投稿",
    "url": "https://x.com/Cplakamata/status/2049094423276073020",
    "postedAt": "2026-04-28T14:27:55.461179+00:00",
    "matchedKeyword": "カプセルトイ 新商品"
  },
  {
    "id": "x_2049094263024284020",
    "platform": "X",
    "username": "@Cplakamata",
    "content": "カプセルトイ 新商品 に関する投稿",
    "url": "https://x.com/Cplakamata/status/2049094263024284020",
    "postedAt": "2026-04-28T14:27:55.461179+00:00",
    "matchedKeyword": "カプセルトイ 新商品"
  },
  {
    "id": "x_2049093978080084332",
    "platform": "X",
    "username": "@Cpla51",
    "content": "カプセルトイ 新商品 に関する投稿",
    "url": "https://x.com/Cpla51/status/2049093978080084332",
    "postedAt": "2026-04-28T14:27:55.461179+00:00",
    "matchedKeyword": "カプセルトイ 新商品"
  },
  {
    "id": "x_2049093422368317699",
    "platform": "X",
    "username": "@ms_gachagacha",
    "content": "カプセルトイ 新商品 に関する投稿",
    "url": "https://x.com/ms_gachagacha/status/2049093422368317699",
    "postedAt": "2026-04-28T14:27:55.461179+00:00",
    "matchedKeyword": "カプセルトイ 新商品"
  },
  {
    "id": "x_2049093054368567598",
    "platform": "X",
    "username": "@ms_gachagacha",
    "content": "カプセルトイ 新商品 に関する投稿",
    "url": "https://x.com/ms_gachagacha/status/2049093054368567598",
    "postedAt": "2026-04-28T14:27:55.461179+00:00",
    "matchedKeyword": "カプセルトイ 新商品"
  },
  {
    "id": "x_2049092764634378473",
    "platform": "X",
    "username": "@ms_gachagacha",
    "content": "カプセルトイ 新商品 に関する投稿",
    "url": "https://x.com/ms_gachagacha/status/2049092764634378473",
    "postedAt": "2026-04-28T14:27:55.461179+00:00",
    "matchedKeyword": "カプセルトイ 新商品"
  },
  {
    "id": "x_2049092556634644757",
    "platform": "X",
    "username": "@ms_gachagacha",
    "content": "カプセルトイ 新商品 に関する投稿",
    "url": "https://x.com/ms_gachagacha/status/2049092556634644757",
    "postedAt": "2026-04-28T14:27:55.461179+00:00",
    "matchedKeyword": "カプセルトイ 新商品"
  },
  {
    "id": "x_2049092216124219472",
    "platform": "X",
    "username": "@ms_gachagacha",
    "content": "カプセルトイ 新商品 に関する投稿",
    "url": "https://x.com/ms_gachagacha/status/2049092216124219472",
    "postedAt": "2026-04-28T14:27:55.461179+00:00",
    "matchedKeyword": "カプセルトイ 新商品"
  },
  {
    "id": "x_2049092080878919739",
    "platform": "X",
    "username": "@Cplakamata",
    "content": "カプセルトイ 新商品 に関する投稿",
    "url": "https://x.com/Cplakamata/status/2049092080878919739",
    "postedAt": "2026-04-28T14:27:55.461179+00:00",
    "matchedKeyword": "カプセルトイ 新商品"
  },
  {
    "id": "x_2049092008372039808",
    "platform": "X",
    "username": "@ms_gachagacha",
    "content": "カプセルトイ 新商品 に関する投稿",
    "url": "https://x.com/ms_gachagacha/status/2049092008372039808",
    "postedAt": "2026-04-28T14:27:55.461179+00:00",
    "matchedKeyword": "カプセルトイ 新商品"
  },
  {
    "id": "x_2049091992735678964",
    "platform": "X",
    "username": "@Cplakamata",
    "content": "カプセルトイ 新商品 に関する投稿",
    "url": "https://x.com/Cplakamata/status/2049091992735678964",
    "postedAt": "2026-04-28T14:27:55.461179+00:00",
    "matchedKeyword": "カプセルトイ 新商品"
  },
  {
    "id": "x_2049091974557499482",
    "platform": "X",
    "username": "@Cplakamata",
    "content": "カプセルトイ 新商品 に関する投稿",
    "url": "https://x.com/Cplakamata/status/2049091974557499482",
    "postedAt": "2026-04-28T14:27:55.461179+00:00",
    "matchedKeyword": "カプセルトイ 新商品"
  },
  {
    "id": "x_2049091867594355012",
    "platform": "X",
    "username": "@Cplakamata",
    "content": "カプセルトイ 新商品 に関する投稿",
    "url": "https://x.com/Cplakamata/status/2049091867594355012",
    "postedAt": "2026-04-28T14:27:55.461179+00:00",
    "matchedKeyword": "カプセルトイ 新商品"
  },
  {
    "id": "x_2049091795725013448",
    "platform": "X",
    "username": "@Cplakamata",
    "content": "カプセルトイ 新商品 に関する投稿",
    "url": "https://x.com/Cplakamata/status/2049091795725013448",
    "postedAt": "2026-04-28T14:27:55.461179+00:00",
    "matchedKeyword": "カプセルトイ 新商品"
  },
  {
    "id": "x_2049091690166886832",
    "platform": "X",
    "username": "@ms_gachagacha",
    "content": "カプセルトイ 新商品 に関する投稿",
    "url": "https://x.com/ms_gachagacha/status/2049091690166886832",
    "postedAt": "2026-04-28T14:27:55.461179+00:00",
    "matchedKeyword": "カプセルトイ 新商品"
  },
  {
    "id": "x_2049091420905148833",
    "platform": "X",
    "username": "@Cplakamata",
    "content": "カプセルトイ 新商品 に関する投稿",
    "url": "https://x.com/Cplakamata/status/2049091420905148833",
    "postedAt": "2026-04-28T14:27:55.461179+00:00",
    "matchedKeyword": "カプセルトイ 新商品"
  },
  {
    "id": "x_2049091371097895419",
    "platform": "X",
    "username": "@Cplakamata",
    "content": "カプセルトイ 新商品 に関する投稿",
    "url": "https://x.com/Cplakamata/status/2049091371097895419",
    "postedAt": "2026-04-28T14:27:55.461179+00:00",
    "matchedKeyword": "カプセルトイ 新商品"
  },
  {
    "id": "x_2049091347572047886",
    "platform": "X",
    "username": "@Cpla51",
    "content": "カプセルトイ 新商品 に関する投稿",
    "url": "https://x.com/Cpla51/status/2049091347572047886",
    "postedAt": "2026-04-28T14:27:55.461179+00:00",
    "matchedKeyword": "カプセルトイ 新商品"
  },
  {
    "id": "x_2049091338151596057",
    "platform": "X",
    "username": "@Cplakamata",
    "content": "カプセルトイ 新商品 に関する投稿",
    "url": "https://x.com/Cplakamata/status/2049091338151596057",
    "postedAt": "2026-04-28T14:27:55.461179+00:00",
    "matchedKeyword": "カプセルトイ 新商品"
  },
  {
    "id": "x_2049091318295773507",
    "platform": "X",
    "username": "@Cplakamata",
    "content": "カプセルトイ 新商品 に関する投稿",
    "url": "https://x.com/Cplakamata/status/2049091318295773507",
    "postedAt": "2026-04-28T14:27:55.461179+00:00",
    "matchedKeyword": "カプセルトイ 新商品"
  },
  {
    "id": "x_2049091294161678693",
    "platform": "X",
    "username": "@Cplakamata",
    "content": "カプセルトイ 新商品 に関する投稿",
    "url": "https://x.com/Cplakamata/status/2049091294161678693",
    "postedAt": "2026-04-28T14:27:55.461179+00:00",
    "matchedKeyword": "カプセルトイ 新商品"
  },
  {
    "id": "x_2049091272707887500",
    "platform": "X",
    "username": "@Cplakamata",
    "content": "カプセルトイ 新商品 に関する投稿",
    "url": "https://x.com/Cplakamata/status/2049091272707887500",
    "postedAt": "2026-04-28T14:27:55.461179+00:00",
    "matchedKeyword": "カプセルトイ 新商品"
  },
  {
    "id": "x_2048764100403208569",
    "platform": "X",
    "username": "@DOPA_Oripa",
    "content": "ガチャ 新作 に関する投稿",
    "url": "https://x.com/DOPA_Oripa/status/2048764100403208569",
    "postedAt": "2026-04-28T14:27:53.973012+00:00",
    "matchedKeyword": "ガチャ 新作"
  },
  {
    "id": "x_2049126497458491804",
    "platform": "X",
    "username": "@pairium_info",
    "content": "ガチャ 新作 に関する投稿",
    "url": "https://x.com/pairium_info/status/2049126497458491804",
    "postedAt": "2026-04-28T14:27:53.973012+00:00",
    "matchedKeyword": "ガチャ 新作"
  },
  {
    "id": "x_2049121481532289446",
    "platform": "X",
    "username": "@oldgorem",
    "content": "ガチャ 新作 に関する投稿",
    "url": "https://x.com/oldgorem/status/2049121481532289446",
    "postedAt": "2026-04-28T14:27:53.973012+00:00",
    "matchedKeyword": "ガチャ 新作"
  },
  {
    "id": "x_2049117240973504886",
    "platform": "X",
    "username": "@zimomomoo",
    "content": "ガチャ 新作 に関する投稿",
    "url": "https://x.com/zimomomoo/status/2049117240973504886",
    "postedAt": "2026-04-28T14:27:53.973012+00:00",
    "matchedKeyword": "ガチャ 新作"
  },
  {
    "id": "x_2049109061875155429",
    "platform": "X",
    "username": "@teritama_nikke",
    "content": "ガチャ 新作 に関する投稿",
    "url": "https://x.com/teritama_nikke/status/2049109061875155429",
    "postedAt": "2026-04-28T14:27:53.973012+00:00",
    "matchedKeyword": "ガチャ 新作"
  },
  {
    "id": "x_2049105239245238775",
    "platform": "X",
    "username": "@umoruez",
    "content": "ガチャ 新作 に関する投稿",
    "url": "https://x.com/umoruez/status/2049105239245238775",
    "postedAt": "2026-04-28T14:27:53.973012+00:00",
    "matchedKeyword": "ガチャ 新作"
  },
  {
    "id": "x_2049104924089393647",
    "platform": "X",
    "username": "@Saffron9913",
    "content": "ガチャ 新作 に関する投稿",
    "url": "https://x.com/Saffron9913/status/2049104924089393647",
    "postedAt": "2026-04-28T14:27:53.973012+00:00",
    "matchedKeyword": "ガチャ 新作"
  },
  {
    "id": "x_2049103105707696423",
    "platform": "X",
    "username": "@kakkasama082",
    "content": "ガチャ 新作 に関する投稿",
    "url": "https://x.com/kakkasama082/status/2049103105707696423",
    "postedAt": "2026-04-28T14:27:53.973012+00:00",
    "matchedKeyword": "ガチャ 新作"
  },
  {
    "id": "x_2049098722714513861",
    "platform": "X",
    "username": "@kluke_yuu",
    "content": "ガチャ 新作 に関する投稿",
    "url": "https://x.com/kluke_yuu/status/2049098722714513861",
    "postedAt": "2026-04-28T14:27:53.973012+00:00",
    "matchedKeyword": "ガチャ 新作"
  },
  {
    "id": "x_2049093771296735589",
    "platform": "X",
    "username": "@morokoshi1",
    "content": "ガチャ 新作 に関する投稿",
    "url": "https://x.com/morokoshi1/status/2049093771296735589",
    "postedAt": "2026-04-28T14:27:53.973012+00:00",
    "matchedKeyword": "ガチャ 新作"
  },
  {
    "id": "x_2049090775296901430",
    "platform": "X",
    "username": "@saltangler77",
    "content": "ガチャ 新作 に関する投稿",
    "url": "https://x.com/saltangler77/status/2049090775296901430",
    "postedAt": "2026-04-28T14:27:53.973012+00:00",
    "matchedKeyword": "ガチャ 新作"
  },
  {
    "id": "x_2049081207066100054",
    "platform": "X",
    "username": "@pairium_info",
    "content": "ガチャ 新作 に関する投稿",
    "url": "https://x.com/pairium_info/status/2049081207066100054",
    "postedAt": "2026-04-28T14:27:53.973012+00:00",
    "matchedKeyword": "ガチャ 新作"
  },
  {
    "id": "x_2049079472322961544",
    "platform": "X",
    "username": "@GanVarjan",
    "content": "ガチャ 新作 に関する投稿",
    "url": "https://x.com/GanVarjan/status/2049079472322961544",
    "postedAt": "2026-04-28T14:27:53.973012+00:00",
    "matchedKeyword": "ガチャ 新作"
  },
  {
    "id": "x_2049077532365111412",
    "platform": "X",
    "username": "@miena_1014",
    "content": "ガチャ 新作 に関する投稿",
    "url": "https://x.com/miena_1014/status/2049077532365111412",
    "postedAt": "2026-04-28T14:27:53.973012+00:00",
    "matchedKeyword": "ガチャ 新作"
  },
  {
    "id": "x_2049076988451885279",
    "platform": "X",
    "username": "@chiikawa_info",
    "content": "ガチャ 新作 に関する投稿",
    "url": "https://x.com/chiikawa_info/status/2049076988451885279",
    "postedAt": "2026-04-28T14:27:53.973012+00:00",
    "matchedKeyword": "ガチャ 新作"
  },
  {
    "id": "x_2049076353623069048",
    "platform": "X",
    "username": "@kashisu_9625",
    "content": "ガチャ 新作 に関する投稿",
    "url": "https://x.com/kashisu_9625/status/2049076353623069048",
    "postedAt": "2026-04-28T14:27:53.973012+00:00",
    "matchedKeyword": "ガチャ 新作"
  },
  {
    "id": "x_2049075684300206480",
    "platform": "X",
    "username": "@02aki26",
    "content": "ガチャ 新作 に関する投稿",
    "url": "https://x.com/02aki26/status/2049075684300206480",
    "postedAt": "2026-04-28T14:27:53.973012+00:00",
    "matchedKeyword": "ガチャ 新作"
  },
  {
    "id": "x_2049075578196971920",
    "platform": "X",
    "username": "@yy2312yy",
    "content": "ガチャ 新作 に関する投稿",
    "url": "https://x.com/yy2312yy/status/2049075578196971920",
    "postedAt": "2026-04-28T14:27:53.973012+00:00",
    "matchedKeyword": "ガチャ 新作"
  },
  {
    "id": "x_2049070298700685454",
    "platform": "X",
    "username": "@sanrio_oshikatu",
    "content": "ガチャ 新作 に関する投稿",
    "url": "https://x.com/sanrio_oshikatu/status/2049070298700685454",
    "postedAt": "2026-04-28T14:27:53.973012+00:00",
    "matchedKeyword": "ガチャ 新作"
  },
  {
    "id": "x_2049070284624584867",
    "platform": "X",
    "username": "@sakuraba_koharu",
    "content": "ガチャ 新作 に関する投稿",
    "url": "https://x.com/sakuraba_koharu/status/2049070284624584867",
    "postedAt": "2026-04-28T14:27:53.973012+00:00",
    "matchedKeyword": "ガチャ 新作"
  },
  {
    "id": "x_2049069307431391678",
    "platform": "X",
    "username": "@patrol_yo",
    "content": "ガチャ 新作 に関する投稿",
    "url": "https://x.com/patrol_yo/status/2049069307431391678",
    "postedAt": "2026-04-28T14:27:53.973012+00:00",
    "matchedKeyword": "ガチャ 新作"
  },
  {
    "id": "x_2049061367869735180",
    "platform": "X",
    "username": "@regeseia808",
    "content": "ガチャ 新作 に関する投稿",
    "url": "https://x.com/regeseia808/status/2049061367869735180",
    "postedAt": "2026-04-28T14:27:53.973012+00:00",
    "matchedKeyword": "ガチャ 新作"
  },
  {
    "id": "x_2049060350998593869",
    "platform": "X",
    "username": "@pairium_info",
    "content": "ガチャ 新作 に関する投稿",
    "url": "https://x.com/pairium_info/status/2049060350998593869",
    "postedAt": "2026-04-28T14:27:53.973012+00:00",
    "matchedKeyword": "ガチャ 新作"
  },
  {
    "id": "x_2049059220952408475",
    "platform": "X",
    "username": "@Dorima8_info",
    "content": "ガチャ 新作 に関する投稿",
    "url": "https://x.com/Dorima8_info/status/2049059220952408475",
    "postedAt": "2026-04-28T14:27:53.973012+00:00",
    "matchedKeyword": "ガチャ 新作"
  },
  {
    "id": "x_2049058971655516455",
    "platform": "X",
    "username": "@jug__men",
    "content": "ガチャ 新作 に関する投稿",
    "url": "https://x.com/jug__men/status/2049058971655516455",
    "postedAt": "2026-04-28T14:27:53.973012+00:00",
    "matchedKeyword": "ガチャ 新作"
  },
  {
    "id": "x_2049054495804649887",
    "platform": "X",
    "username": "@mushimushioja",
    "content": "ガチャ 新作 に関する投稿",
    "url": "https://x.com/mushimushioja/status/2049054495804649887",
    "postedAt": "2026-04-28T14:27:53.973012+00:00",
    "matchedKeyword": "ガチャ 新作"
  },
  {
    "id": "x_2049051619824972272",
    "platform": "X",
    "username": "@lophophora",
    "content": "ガチャ 新作 に関する投稿",
    "url": "https://x.com/lophophora/status/2049051619824972272",
    "postedAt": "2026-04-28T14:27:53.973012+00:00",
    "matchedKeyword": "ガチャ 新作"
  },
  {
    "id": "x_2049050727134437592",
    "platform": "X",
    "username": "@choko_choko_poi",
    "content": "ガチャ 新作 に関する投稿",
    "url": "https://x.com/choko_choko_poi/status/2049050727134437592",
    "postedAt": "2026-04-28T14:27:53.973012+00:00",
    "matchedKeyword": "ガチャ 新作"
  },
  {
    "id": "x_2049049134221717779",
    "platform": "X",
    "username": "@totototo0507",
    "content": "ガチャ 新作 に関する投稿",
    "url": "https://x.com/totototo0507/status/2049049134221717779",
    "postedAt": "2026-04-28T14:27:53.973012+00:00",
    "matchedKeyword": "ガチャ 新作"
  },
  {
    "id": "x_2049046383601295687",
    "platform": "X",
    "username": "@fiddle8fad22832",
    "content": "ガチャ 新作 に関する投稿",
    "url": "https://x.com/fiddle8fad22832/status/2049046383601295687",
    "postedAt": "2026-04-28T14:27:53.973012+00:00",
    "matchedKeyword": "ガチャ 新作"
  },
  {
    "id": "x_2049044250093080843",
    "platform": "X",
    "username": "@Nii_n4_",
    "content": "ガチャ 新作 に関する投稿",
    "url": "https://x.com/Nii_n4_/status/2049044250093080843",
    "postedAt": "2026-04-28T14:27:53.973012+00:00",
    "matchedKeyword": "ガチャ 新作"
  },
  {
    "id": "x_2049042094841614665",
    "platform": "X",
    "username": "@goha_shining",
    "content": "ガチャ 新作 に関する投稿",
    "url": "https://x.com/goha_shining/status/2049042094841614665",
    "postedAt": "2026-04-28T14:27:53.973012+00:00",
    "matchedKeyword": "ガチャ 新作"
  },
  {
    "id": "x_2049037353105440805",
    "platform": "X",
    "username": "@RG8BDoBdN114156",
    "content": "ガチャ 新作 に関する投稿",
    "url": "https://x.com/RG8BDoBdN114156/status/2049037353105440805",
    "postedAt": "2026-04-28T14:27:53.973012+00:00",
    "matchedKeyword": "ガチャ 新作"
  },
  {
    "id": "x_2049036666418131266",
    "platform": "X",
    "username": "@takeno_tkdb",
    "content": "ガチャ 新作 に関する投稿",
    "url": "https://x.com/takeno_tkdb/status/2049036666418131266",
    "postedAt": "2026-04-28T14:27:53.973012+00:00",
    "matchedKeyword": "ガチャ 新作"
  },
  {
    "id": "x_2049030456373637179",
    "platform": "X",
    "username": "@esola_game",
    "content": "ガチャ 新作 に関する投稿",
    "url": "https://x.com/esola_game/status/2049030456373637179",
    "postedAt": "2026-04-28T14:27:53.973012+00:00",
    "matchedKeyword": "ガチャ 新作"
  },
  {
    "id": "x_2049030170481439122",
    "platform": "X",
    "username": "@TorekaZamurai_i",
    "content": "ガチャ 新作 に関する投稿",
    "url": "https://x.com/TorekaZamurai_i/status/2049030170481439122",
    "postedAt": "2026-04-28T14:27:53.973012+00:00",
    "matchedKeyword": "ガチャ 新作"
  },
  {
    "id": "x_2049028842883571943",
    "platform": "X",
    "username": "@mrc___0",
    "content": "ガチャ 新作 に関する投稿",
    "url": "https://x.com/mrc___0/status/2049028842883571943",
    "postedAt": "2026-04-28T14:27:53.973012+00:00",
    "matchedKeyword": "ガチャ 新作"
  },
  {
    "id": "x_2049020953108332925",
    "platform": "X",
    "username": "@SM_seal_room",
    "content": "ガチャ 新作 に関する投稿",
    "url": "https://x.com/SM_seal_room/status/2049020953108332925",
    "postedAt": "2026-04-28T14:27:53.973012+00:00",
    "matchedKeyword": "ガチャ 新作"
  },
  {
    "id": "x_2049002129545965728",
    "platform": "X",
    "username": "@YS_G_MINT",
    "content": "ガチャ 新作 に関する投稿",
    "url": "https://x.com/YS_G_MINT/status/2049002129545965728",
    "postedAt": "2026-04-28T14:27:53.973012+00:00",
    "matchedKeyword": "ガチャ 新作"
  },
  {
    "id": "x_2048999882527310040",
    "platform": "X",
    "username": "@xo0u8gQpLVZpJ7Y",
    "content": "ガチャ 新作 に関する投稿",
    "url": "https://x.com/xo0u8gQpLVZpJ7Y/status/2048999882527310040",
    "postedAt": "2026-04-28T14:27:53.973012+00:00",
    "matchedKeyword": "ガチャ 新作"
  },
  {
    "id": "x_2049003706079957471",
    "platform": "X",
    "username": "@gachadokoro_hrj",
    "content": "ガシャポン 新商品 に関する投稿",
    "url": "https://x.com/gachadokoro_hrj/status/2049003706079957471",
    "postedAt": "2026-04-28T14:27:52.395353+00:00",
    "matchedKeyword": "ガシャポン 新商品"
  },
  {
    "id": "x_2049080416221720714",
    "platform": "X",
    "username": "@cplaatrekawagoe",
    "content": "ガシャポン 新商品 に関する投稿",
    "url": "https://x.com/cplaatrekawagoe/status/2049080416221720714",
    "postedAt": "2026-04-28T14:27:52.395353+00:00",
    "matchedKeyword": "ガシャポン 新商品"
  },
  {
    "id": "x_2049071204515107169",
    "platform": "X",
    "username": "@CplaEAST",
    "content": "ガシャポン 新商品 に関する投稿",
    "url": "https://x.com/CplaEAST/status/2049071204515107169",
    "postedAt": "2026-04-28T14:27:52.395353+00:00",
    "matchedKeyword": "ガシャポン 新商品"
  },
  {
    "id": "x_2049041410016587878",
    "platform": "X",
    "username": "@SuiseiNewsJP",
    "content": "ガシャポン 新商品 に関する投稿",
    "url": "https://x.com/SuiseiNewsJP/status/2049041410016587878",
    "postedAt": "2026-04-28T14:27:52.395353+00:00",
    "matchedKeyword": "ガシャポン 新商品"
  },
  {
    "id": "x_2049041182832091291",
    "platform": "X",
    "username": "@MikoNewsJP",
    "content": "ガシャポン 新商品 に関する投稿",
    "url": "https://x.com/MikoNewsJP/status/2049041182832091291",
    "postedAt": "2026-04-28T14:27:52.395353+00:00",
    "matchedKeyword": "ガシャポン 新商品"
  },
  {
    "id": "x_2049035551307927613",
    "platform": "X",
    "username": "@Cpla_tamapula",
    "content": "ガシャポン 新商品 に関する投稿",
    "url": "https://x.com/Cpla_tamapula/status/2049035551307927613",
    "postedAt": "2026-04-28T14:27:52.395353+00:00",
    "matchedKeyword": "ガシャポン 新商品"
  },
  {
    "id": "x_2049034067824538028",
    "platform": "X",
    "username": "@Cpla428446Pla",
    "content": "ガシャポン 新商品 に関する投稿",
    "url": "https://x.com/Cpla428446Pla/status/2049034067824538028",
    "postedAt": "2026-04-28T14:27:52.395353+00:00",
    "matchedKeyword": "ガシャポン 新商品"
  },
  {
    "id": "x_2049018425440436255",
    "platform": "X",
    "username": "@cplachoufu",
    "content": "ガシャポン 新商品 に関する投稿",
    "url": "https://x.com/cplachoufu/status/2049018425440436255",
    "postedAt": "2026-04-28T14:27:52.395353+00:00",
    "matchedKeyword": "ガシャポン 新商品"
  },
  {
    "id": "x_2049013146489380924",
    "platform": "X",
    "username": "@Cplalefront",
    "content": "ガシャポン 新商品 に関する投稿",
    "url": "https://x.com/Cplalefront/status/2049013146489380924",
    "postedAt": "2026-04-28T14:27:52.395353+00:00",
    "matchedKeyword": "ガシャポン 新商品"
  },
  {
    "id": "x_2049011968661725347",
    "platform": "X",
    "username": "@gasha_mozo_wc",
    "content": "ガシャポン 新商品 に関する投稿",
    "url": "https://x.com/gasha_mozo_wc/status/2049011968661725347",
    "postedAt": "2026-04-28T14:27:52.395353+00:00",
    "matchedKeyword": "ガシャポン 新商品"
  },
  {
    "id": "x_2049007009266327578",
    "platform": "X",
    "username": "@gachadokoro_hrj",
    "content": "ガシャポン 新商品 に関する投稿",
    "url": "https://x.com/gachadokoro_hrj/status/2049007009266327578",
    "postedAt": "2026-04-28T14:27:52.395353+00:00",
    "matchedKeyword": "ガシャポン 新商品"
  },
  {
    "id": "x_2049006823483834541",
    "platform": "X",
    "username": "@gachadokoro_hrj",
    "content": "ガシャポン 新商品 に関する投稿",
    "url": "https://x.com/gachadokoro_hrj/status/2049006823483834541",
    "postedAt": "2026-04-28T14:27:52.395353+00:00",
    "matchedKeyword": "ガシャポン 新商品"
  },
  {
    "id": "x_2049006044815499592",
    "platform": "X",
    "username": "@gachadokoro_hrj",
    "content": "ガシャポン 新商品 に関する投稿",
    "url": "https://x.com/gachadokoro_hrj/status/2049006044815499592",
    "postedAt": "2026-04-28T14:27:52.395353+00:00",
    "matchedKeyword": "ガシャポン 新商品"
  },
  {
    "id": "x_2049005308601864591",
    "platform": "X",
    "username": "@gachadokoro_hrj",
    "content": "ガシャポン 新商品 に関する投稿",
    "url": "https://x.com/gachadokoro_hrj/status/2049005308601864591",
    "postedAt": "2026-04-28T14:27:52.395353+00:00",
    "matchedKeyword": "ガシャポン 新商品"
  },
  {
    "id": "x_2049004909857812933",
    "platform": "X",
    "username": "@gachadokoro_hrj",
    "content": "ガシャポン 新商品 に関する投稿",
    "url": "https://x.com/gachadokoro_hrj/status/2049004909857812933",
    "postedAt": "2026-04-28T14:27:52.395353+00:00",
    "matchedKeyword": "ガシャポン 新商品"
  },
  {
    "id": "x_2049004176479605156",
    "platform": "X",
    "username": "@gachadokoro_hrj",
    "content": "ガシャポン 新商品 に関する投稿",
    "url": "https://x.com/gachadokoro_hrj/status/2049004176479605156",
    "postedAt": "2026-04-28T14:27:52.395353+00:00",
    "matchedKeyword": "ガシャポン 新商品"
  },
  {
    "id": "x_2049003736882884721",
    "platform": "X",
    "username": "@opa_pla",
    "content": "ガシャポン 新商品 に関する投稿",
    "url": "https://x.com/opa_pla/status/2049003736882884721",
    "postedAt": "2026-04-28T14:27:52.395353+00:00",
    "matchedKeyword": "ガシャポン 新商品"
  },
  {
    "id": "x_2049003676694634925",
    "platform": "X",
    "username": "@Cpla0216",
    "content": "ガシャポン 新商品 に関する投稿",
    "url": "https://x.com/Cpla0216/status/2049003676694634925",
    "postedAt": "2026-04-28T14:27:52.395353+00:00",
    "matchedKeyword": "ガシャポン 新商品"
  },
  {
    "id": "x_2049001309106581899",
    "platform": "X",
    "username": "@gachadokoro_hrj",
    "content": "ガシャポン 新商品 に関する投稿",
    "url": "https://x.com/gachadokoro_hrj/status/2049001309106581899",
    "postedAt": "2026-04-28T14:27:52.395353+00:00",
    "matchedKeyword": "ガシャポン 新商品"
  },
  {
    "id": "x_2048998309113798794",
    "platform": "X",
    "username": "@gachadokoro_hrj",
    "content": "ガシャポン 新商品 に関する投稿",
    "url": "https://x.com/gachadokoro_hrj/status/2048998309113798794",
    "postedAt": "2026-04-28T14:27:52.395353+00:00",
    "matchedKeyword": "ガシャポン 新商品"
  },
  {
    "id": "x_2048997827712516254",
    "platform": "X",
    "username": "@gachadokoro_hrj",
    "content": "ガシャポン 新商品 に関する投稿",
    "url": "https://x.com/gachadokoro_hrj/status/2048997827712516254",
    "postedAt": "2026-04-28T14:27:52.395353+00:00",
    "matchedKeyword": "ガシャポン 新商品"
  },
  {
    "id": "x_2048996798631760049",
    "platform": "X",
    "username": "@gachadokoro_hrj",
    "content": "ガシャポン 新商品 に関する投稿",
    "url": "https://x.com/gachadokoro_hrj/status/2048996798631760049",
    "postedAt": "2026-04-28T14:27:52.395353+00:00",
    "matchedKeyword": "ガシャポン 新商品"
  },
  {
    "id": "x_2048996160619348377",
    "platform": "X",
    "username": "@gachadokoro_hrj",
    "content": "ガシャポン 新商品 に関する投稿",
    "url": "https://x.com/gachadokoro_hrj/status/2048996160619348377",
    "postedAt": "2026-04-28T14:27:52.395353+00:00",
    "matchedKeyword": "ガシャポン 新商品"
  },
  {
    "id": "x_2048996036828680270",
    "platform": "X",
    "username": "@Cpla79968708",
    "content": "ガシャポン 新商品 に関する投稿",
    "url": "https://x.com/Cpla79968708/status/2048996036828680270",
    "postedAt": "2026-04-28T14:27:52.395353+00:00",
    "matchedKeyword": "ガシャポン 新商品"
  },
  {
    "id": "x_2048995247922024655",
    "platform": "X",
    "username": "@gachadokoro_hrj",
    "content": "ガシャポン 新商品 に関する投稿",
    "url": "https://x.com/gachadokoro_hrj/status/2048995247922024655",
    "postedAt": "2026-04-28T14:27:52.395353+00:00",
    "matchedKeyword": "ガシャポン 新商品"
  },
  {
    "id": "x_2048993790472618257",
    "platform": "X",
    "username": "@gachadokoro_hrj",
    "content": "ガシャポン 新商品 に関する投稿",
    "url": "https://x.com/gachadokoro_hrj/status/2048993790472618257",
    "postedAt": "2026-04-28T14:27:52.395353+00:00",
    "matchedKeyword": "ガシャポン 新商品"
  },
  {
    "id": "x_2048993443075260446",
    "platform": "X",
    "username": "@gachadokoro_hrj",
    "content": "ガシャポン 新商品 に関する投稿",
    "url": "https://x.com/gachadokoro_hrj/status/2048993443075260446",
    "postedAt": "2026-04-28T14:27:52.395353+00:00",
    "matchedKeyword": "ガシャポン 新商品"
  },
  {
    "id": "x_2048993067798327376",
    "platform": "X",
    "username": "@gachadokoro_hrj",
    "content": "ガシャポン 新商品 に関する投稿",
    "url": "https://x.com/gachadokoro_hrj/status/2048993067798327376",
    "postedAt": "2026-04-28T14:27:52.395353+00:00",
    "matchedKeyword": "ガシャポン 新商品"
  },
  {
    "id": "x_2048992294205108357",
    "platform": "X",
    "username": "@gachadokoro_hrj",
    "content": "ガシャポン 新商品 に関する投稿",
    "url": "https://x.com/gachadokoro_hrj/status/2048992294205108357",
    "postedAt": "2026-04-28T14:27:52.395353+00:00",
    "matchedKeyword": "ガシャポン 新商品"
  },
  {
    "id": "x_2048991969528168778",
    "platform": "X",
    "username": "@gachadokoro_hrj",
    "content": "ガシャポン 新商品 に関する投稿",
    "url": "https://x.com/gachadokoro_hrj/status/2048991969528168778",
    "postedAt": "2026-04-28T14:27:52.395353+00:00",
    "matchedKeyword": "ガシャポン 新商品"
  },
  {
    "id": "x_2048990399121990060",
    "platform": "X",
    "username": "@gachadokoro_hrj",
    "content": "ガシャポン 新商品 に関する投稿",
    "url": "https://x.com/gachadokoro_hrj/status/2048990399121990060",
    "postedAt": "2026-04-28T14:27:52.395353+00:00",
    "matchedKeyword": "ガシャポン 新商品"
  },
  {
    "id": "x_2048989974209683793",
    "platform": "X",
    "username": "@gachadokoro_hrj",
    "content": "ガシャポン 新商品 に関する投稿",
    "url": "https://x.com/gachadokoro_hrj/status/2048989974209683793",
    "postedAt": "2026-04-28T14:27:52.395353+00:00",
    "matchedKeyword": "ガシャポン 新商品"
  },
  {
    "id": "x_2048989529823174701",
    "platform": "X",
    "username": "@gachadokoro_hrj",
    "content": "ガシャポン 新商品 に関する投稿",
    "url": "https://x.com/gachadokoro_hrj/status/2048989529823174701",
    "postedAt": "2026-04-28T14:27:52.395353+00:00",
    "matchedKeyword": "ガシャポン 新商品"
  },
  {
    "id": "x_2048989171604484573",
    "platform": "X",
    "username": "@gachadokoro_hrj",
    "content": "ガシャポン 新商品 に関する投稿",
    "url": "https://x.com/gachadokoro_hrj/status/2048989171604484573",
    "postedAt": "2026-04-28T14:27:52.395353+00:00",
    "matchedKeyword": "ガシャポン 新商品"
  },
  {
    "id": "x_2048988662864764980",
    "platform": "X",
    "username": "@gachadokoro_hrj",
    "content": "ガシャポン 新商品 に関する投稿",
    "url": "https://x.com/gachadokoro_hrj/status/2048988662864764980",
    "postedAt": "2026-04-28T14:27:52.395353+00:00",
    "matchedKeyword": "ガシャポン 新商品"
  },
  {
    "id": "x_2048987477013328191",
    "platform": "X",
    "username": "@gachadokoro_hrj",
    "content": "ガシャポン 新商品 に関する投稿",
    "url": "https://x.com/gachadokoro_hrj/status/2048987477013328191",
    "postedAt": "2026-04-28T14:27:52.395353+00:00",
    "matchedKeyword": "ガシャポン 新商品"
  },
  {
    "id": "x_2048987041388696056",
    "platform": "X",
    "username": "@gachadokoro_hrj",
    "content": "ガシャポン 新商品 に関する投稿",
    "url": "https://x.com/gachadokoro_hrj/status/2048987041388696056",
    "postedAt": "2026-04-28T14:27:52.395353+00:00",
    "matchedKeyword": "ガシャポン 新商品"
  },
  {
    "id": "x_2048985238878269578",
    "platform": "X",
    "username": "@GBO_pombashi",
    "content": "ガシャポン 新商品 に関する投稿",
    "url": "https://x.com/GBO_pombashi/status/2048985238878269578",
    "postedAt": "2026-04-28T14:27:52.395353+00:00",
    "matchedKeyword": "ガシャポン 新商品"
  },
  {
    "id": "x_2048981848496505056",
    "platform": "X",
    "username": "@Cplaabiko",
    "content": "ガシャポン 新商品 に関する投稿",
    "url": "https://x.com/Cplaabiko/status/2048981848496505056",
    "postedAt": "2026-04-28T14:27:52.395353+00:00",
    "matchedKeyword": "ガシャポン 新商品"
  },
  {
    "id": "x_2048977807678783980",
    "platform": "X",
    "username": "@gacha_oomiya",
    "content": "ガシャポン 新商品 に関する投稿",
    "url": "https://x.com/gacha_oomiya/status/2048977807678783980",
    "postedAt": "2026-04-28T14:27:52.395353+00:00",
    "matchedKeyword": "ガシャポン 新商品"
  }
]