[
  {
    "id": "x_2044613879909826929",
    "platform": "X",
    "username": "@hebinotyuke",
    "content": "私サンリオダイヤモンド会員だし、新作やくじ出るたびに数万使ってるのに、最近のガチャ平日入荷で社会人どう足掻いても無理ゲー過ぎて本当泣ける — のちゅ (@hebinotyuke) April 16, 2026",
    "url": "https://x.com/hebinotyuke/status/2044613879909826929",
    "postedAt": "2026-04-18T07:18:51.079104+00:00",
    "matchedKeyword": "サンリオ ガチャ 新作"
  },
  {
    "id": "x_2044410105668710505",
    "platform": "X",
    "username": "@mizuki19_aoi_21",
    "content": "毎年恒例のコナン映画観てきた🎥 千速さんかっこいい〜‼️バイク姿が似合います🏍✨ あれは男女問わず惚れちゃうよね😍 グッズはコナンぬいだけ買ってきた👓🎀 去年はキッド様を🎩🪄 サンリオガチャしたら第2の推しのポムポムプリンお迎え💓 帰りに31で新作食べてきた🍨 pic.twitter.com/bbm78AmAql — 🐰ともみ(水城)🐹4/17LiSA、24.25ふるっぱー (@mizuki19_aoi_21) April 15, 2026",
    "url": "https://x.com/mizuki19_aoi_21/status/2044410105668710505",
    "postedAt": "2026-04-18T07:18:51.079104+00:00",
    "matchedKeyword": "サンリオ ガチャ 新作"
  },
  {
    "id": "x_2044185614762025230",
    "platform": "X",
    "username": "@ryuhey555",
    "content": "新作ガチャ「サンリオキャラクターズ minimini ファイルキーホルダー 全6種セット」が予約受付スタートしてます！ シール帳としても使えます！ コンプリートで買えるお店少ないので気になってた方はチェックしてみて下さい！ #カプセルトイ https://t.co/EXibKvANTr — りゅうへい (@ryuhey555) April 14, 2026",
    "url": "https://x.com/ryuhey555/status/2044185614762025230",
    "postedAt": "2026-04-18T07:18:51.079104+00:00",
    "matchedKeyword": "サンリオ ガチャ 新作"
  },
  {
    "id": "x_2044075993149952408",
    "platform": "X",
    "username": "@moonbijin88",
    "content": "たぶん めじるしポム買えなかった人続出するので こちらサンリオショップ新作ポム販売中です！こちらも キーホルダーが魅力的ですね 今年はポムポムプリンが30周年なので たくさんグッズがでますよ #ポムポムプリン #めじるしアクセサリー #ガシャポン #ガチャ pic.twitter.com/HDRFI6rBcb — 宇宙最後の蝶🦋遊楽蝶月下美人🌜️🌸 Vtuber 生配信 (@moonbijin88) April 14, 2026",
    "url": "https://x.com/moonbijin88/status/2044075993149952408",
    "postedAt": "2026-04-18T07:18:51.079104+00:00",
    "matchedKeyword": "サンリオ ガチャ 新作"
  },
  {
    "id": "x_2044045417680437254",
    "platform": "X",
    "username": "@so3av",
    "content": "サンリオの新作ガチャ、5分の1でキティ出るはずなのに、全シナモンでその後キティでたんだけど… 普通に重複シナモンのために1500円使ったと思うと萎える — ᕱ⑅︎ᕱ (@so3av) April 14, 2026",
    "url": "https://x.com/so3av/status/2044045417680437254",
    "postedAt": "2026-04-18T07:18:51.079104+00:00",
    "matchedKeyword": "サンリオ ガチャ 新作"
  },
  {
    "id": "x_2043909468547899557",
    "platform": "X",
    "username": "@chima_830",
    "content": "ブログ更新🔔新作ガチャ紹介🌷 ラインナップ神！✨タカラトミーアーツ🎀サンリオキャラクターズ メルヘン工房 おなまえホルダーミニチュアラバーマスコット2 #ガチャガチャ #カプセルトイ #新作ガチャ #サンリオ https://t.co/5xyQCjLQby — ちま (@chima_830) April 14, 2026",
    "url": "https://x.com/chima_830/status/2043909468547899557",
    "postedAt": "2026-04-18T07:18:51.079104+00:00",
    "matchedKeyword": "サンリオ ガチャ 新作"
  },
  {
    "id": "x_2043754867307827506",
    "platform": "X",
    "username": "@jagajaga7575",
    "content": "サンリオ 新作！ サンリオキャラクターズ チョコボックス ボックスフィギュアコレクション ▶ https://t.co/w2kMhHu2NT 【PR】 定価：税込み385円×14個＝5,390円 2025年7月発売・Amazon バンダイ 食玩 付録 交換 ガチャ SNSで話題 ローソン ファミマ コンビニ しまむら ヨドバシ イオン アプリ — じゃが (@jagajaga7575) April 13, 2026",
    "url": "https://x.com/jagajaga7575/status/2043754867307827506",
    "postedAt": "2026-04-18T07:18:51.079104+00:00",
    "matchedKeyword": "サンリオ ガチャ 新作"
  },
  {
    "id": "x_2043588965094277388",
    "platform": "X",
    "username": "@o76DXxobZi99209",
    "content": "今日は帰り道にガチャガチャ巡りしてきた💜春の新作が一気に出ててテンション上がるし、サンリオのシナモロールとちいかわの並びはずるい可愛さすぎる…🥺狙いは出なかったけどダブりも愛せるのが沼ポイント。ガチャ好きさんと繋がりたいしおすすめ台あったら教えてほしい✨ — さや (@o76DXxobZi99209) April 13, 2026",
    "url": "https://x.com/o76DXxobZi99209/status/2043588965094277388",
    "postedAt": "2026-04-18T07:18:51.079104+00:00",
    "matchedKeyword": "サンリオ ガチャ 新作"
  },
  {
    "id": "x_2043568845592641950",
    "platform": "X",
    "username": "@panko66666",
    "content": "[PR] 【8月予約】ニャニィニュニェニョン フロッキーフィギュア 全5種 コンプリートセット ガチャ 送料無料 楽天市場で予約開始💕 🔻 ホビー雑貨のチャチャ https://t.co/eIMMnOUS5g ふわっとした質感までかわいすぎる🐱✨ サンリオ ガチャガチャ ガチャ ガシャポン カプセルトイ 入荷 新作 — ぱにーに🥖 (@panko66666) April 13, 2026",
    "url": "https://x.com/panko66666/status/2043568845592641950",
    "postedAt": "2026-04-18T07:18:51.079104+00:00",
    "matchedKeyword": "サンリオ ガチャ 新作"
  },
  {
    "id": "x_2043540242335224319",
    "platform": "X",
    "username": "@mmmred2xxx",
    "content": "なんか気づいたらサンリオの新作ガチャ毎回バズって店頭で見つけても売り切れになってること増えた… — 塔 (@mmmred2xxx) April 13, 2026",
    "url": "https://x.com/mmmred2xxx/status/2043540242335224319",
    "postedAt": "2026-04-18T07:18:51.079104+00:00",
    "matchedKeyword": "サンリオ ガチャ 新作"
  },
  {
    "id": "x_2043479983893745995",
    "platform": "X",
    "username": "@ryuhey555",
    "content": "新作ガチャ【サンリオ マイメロディ ぬいぐるみチャーム 全4種セット】が予約受付スタートしました！ コンプリートセットで購入できます！ マイメロお好きな方はチェックしてみて下さい！ #カプセルトイ https://t.co/yVaiP8XgvA — りゅうへい (@ryuhey555) April 13, 2026",
    "url": "https://x.com/ryuhey555/status/2043479983893745995",
    "postedAt": "2026-04-18T07:18:51.079104+00:00",
    "matchedKeyword": "サンリオ ガチャ 新作"
  },
  {
    "id": "x_2043127696948089257",
    "platform": "X",
    "username": "@hiyoko00145",
    "content": "[PR] サンリオキャラクターズ ワントーンマスコット 桜 全5種セット コンプリートセット 楽天で買えた✨ 🔻 アミュームショップ 楽天市場店 https://t.co/aFN0epyHP9 シナモロール、ハローキティ、クロミ、ポムポムプリン、ポチャッコ 春っぽくて可愛い🌸 ガチャガチャ ガチャ ガシャポン 入荷 新作 — ひよ子🌼 (@hiyoko00145) April 12, 2026",
    "url": "https://x.com/hiyoko00145/status/2043127696948089257",
    "postedAt": "2026-04-18T07:18:51.079104+00:00",
    "matchedKeyword": "サンリオ ガチャ 新作"
  },
  {
    "id": "x_2043086156146082190",
    "platform": "X",
    "username": "@BAK1DAZE",
    "content": "サンリオ友にサンリオ新作のガチャシナモン当たったからいる？って聞いたらいるー！って来たからあげようとしたら他のサンリオガチャくれるってw交換っこ♡今度あったら交換しよう❣️ — 薔姫ﾊﾞｷ (@BAK1DAZE) April 11, 2026",
    "url": "https://x.com/BAK1DAZE/status/2043086156146082190",
    "postedAt": "2026-04-18T07:18:51.079104+00:00",
    "matchedKeyword": "サンリオ ガチャ 新作"
  },
  {
    "id": "x_2043014112998052213",
    "platform": "X",
    "username": "@isesakigacha2",
    "content": "#万代書店伊勢崎店 #ガチャ #ガシャポン ╲4/12新作・再販入荷情報／ サンリオ桜・モンチッチめじるしアクセは大通り沿い入口コーナーに設置しています。12日開店時から販売予定です。各40個(２回回しで20名様)で在庫は終了になります。 pic.twitter.com/u5YgQIjXZw — シン•万代書店伊勢崎店ガチャガチャコーナー (@isesakigacha2) April 11, 2026",
    "url": "https://x.com/isesakigacha2/status/2043014112998052213",
    "postedAt": "2026-04-18T07:18:51.079104+00:00",
    "matchedKeyword": "サンリオ ガチャ 新作"
  },
  {
    "id": "x_2042934108700184593",
    "platform": "X",
    "username": "@krnk_299",
    "content": "サンリオのおなまえホルダーガチャ再入荷と新作あって渡したら投票カードもらえたの良かった。お店によってやってたりやってなかったりしてるんだね — 黒ねこ (@krnk_299) April 11, 2026",
    "url": "https://x.com/krnk_299/status/2042934108700184593",
    "postedAt": "2026-04-18T07:18:51.079104+00:00",
    "matchedKeyword": "サンリオ ガチャ 新作"
  },
  {
    "id": "x_2042927472413642909",
    "platform": "X",
    "username": "@hiyori14300",
    "content": "[PR] 【7月予約】サンリオキャラクターズ スクバデコ風 ミニバッグ 全5種 コンプリートセット ガチャ 楽天市場で予約開始💕 🔻 ホビー雑貨のチャチャ https://t.co/3VdEZVUlB6 こういう平成っぽい空気のあるサンリオアイテム好きすぎる🎀✨ ガチャガチャ ガチャ ガシャポン カプセルトイ 入荷 新作 — ひより🤍🤍 (@hiyori14300) April 11, 2026",
    "url": "https://x.com/hiyori14300/status/2042927472413642909",
    "postedAt": "2026-04-18T07:18:51.079104+00:00",
    "matchedKeyword": "サンリオ ガチャ 新作"
  },
  {
    "id": "x_2042913271809011915",
    "platform": "X",
    "username": "@rererurububu",
    "content": "[PR] 【5月再販予定】 サンリオキャラクターズ バレエリボンフィギュア 【全4種セット】 楽天で買えるよ💕 🔻 A-TOYS 楽天市場店 https://t.co/J12XEwE92j マイメロもクロミもシナモロールもマロンクリームもいるの強い🩰✨ ガチャガチャ ガチャ ガシャポン カプセルトイ 入荷 新作 — わっふる🧇 (@rererurububu) April 11, 2026",
    "url": "https://x.com/rererurububu/status/2042913271809011915",
    "postedAt": "2026-04-18T07:18:51.079104+00:00",
    "matchedKeyword": "サンリオ ガチャ 新作"
  },
  {
    "id": "x_2042887916301750435",
    "platform": "X",
    "username": "@kamenaki0428",
    "content": "おちもりの漫才で2部ともゲラゲラ笑ってサンリオショップ行ってガチャ屋行ったら欲しかった新作あってうなぎまで食べちゃって、ただのいい休日じゃないか！！！！ — 🍯 (@kamenaki0428) April 11, 2026",
    "url": "https://x.com/kamenaki0428/status/2042887916301750435",
    "postedAt": "2026-04-18T07:18:51.079104+00:00",
    "matchedKeyword": "サンリオ ガチャ 新作"
  },
  {
    "id": "x_2042859134689968231",
    "platform": "X",
    "username": "@panko66666",
    "content": "[PR] 【7月予約】サンリオキャラクターズ minimini ファイルキーホルダー 全6種 コンプリート 楽天で予約受付中🌼 🔻 ノリーズコレクション https://t.co/Fb2nxcv2dr ハローキティ、マイメロディ、ポムポムプリン、クロミ、シナモロール、ポチャッコ💖 ガチャガチャ ガチャ ガシャポン 入荷 新作 — ぱにーに🥖 (@panko66666) April 11, 2026",
    "url": "https://x.com/panko66666/status/2042859134689968231",
    "postedAt": "2026-04-18T07:18:51.079104+00:00",
    "matchedKeyword": "サンリオ ガチャ 新作"
  },
  {
    "id": "x_2042832107379261448",
    "platform": "X",
    "username": "@hiyoko00145",
    "content": "[PR] 【7月予約】サンリオキャラクターズ リンリン鈴ぬいぐるみ 日焼けデザイン 全4種 コンプリートセット ガチャ 送料無料 楽天市場で予約受付中💕 🔻 ホビー雑貨のチャチャ https://t.co/mgeSJqmxZ0 日焼けキティちゃん！夏っぽくて最高🌺 ガチャガチャ ガチャ ガシャポン カプセルトイ 入荷 新作 — ひよ子🌼 (@hiyoko00145) April 11, 2026",
    "url": "https://x.com/hiyoko00145/status/2042832107379261448",
    "postedAt": "2026-04-18T07:18:51.079104+00:00",
    "matchedKeyword": "サンリオ ガチャ 新作"
  },
  {
    "id": "x_2042545172144361844",
    "platform": "X",
    "username": "@BAK1DAZE",
    "content": "今日の取寄せとガチャ♡ レイヤード風トップス ラインストーン付きパンツ サンリオ新作ガチャはなんと被りなし5連チャン❣️モンチッチは回数制限2回で旦那と回しました❣️あっかわちぃ♡ #ハニーズ #サンリオ #モンチッチ pic.twitter.com/ruG9snsNNV — 薔姫ﾊﾞｷ (@BAK1DAZE) April 10, 2026",
    "url": "https://x.com/BAK1DAZE/status/2042545172144361844",
    "postedAt": "2026-04-18T07:18:51.079104+00:00",
    "matchedKeyword": "サンリオ ガチャ 新作"
  },
  {
    "id": "x_2042402776689541225",
    "platform": "X",
    "username": "@jagajaga7575",
    "content": "サンリオ 新作！ サンリオキャラクターズ チョコボックス ボックスフィギュアコレクション ▶ https://t.co/w2kMhHu2NT 【PR】 定価：税込み385円×14個＝5,390円 2025年7月発売・Amazon バンダイ 食玩 付録 交換 ガチャ SNSで話題 ローソン ファミマ コンビニ しまむら ヨドバシ イオン アプリ — じゃが (@jagajaga7575) April 10, 2026",
    "url": "https://x.com/jagajaga7575/status/2042402776689541225",
    "postedAt": "2026-04-18T07:18:51.079104+00:00",
    "matchedKeyword": "サンリオ ガチャ 新作"
  },
  {
    "id": "x_2042229121720385612",
    "platform": "X",
    "username": "@rererurububu",
    "content": "[PR]【7月予約】【送料無料】サンリオキャラクターズ ぴょこのる マスコット3 全5種 コンプリート 楽天市場で予約開始💞 🔻ノリーズコレクション https://t.co/DAisHa0kOV ウサハナ、シュガーバニーズ、チャーミーキティ、コロコロクリリン🥰 ガチャガチャ ガチャ ガシャポン 入荷 新作 — わっふる🧇 (@rererurububu) April 9, 2026",
    "url": "https://x.com/rererurububu/status/2042229121720385612",
    "postedAt": "2026-04-18T07:18:51.079104+00:00",
    "matchedKeyword": "サンリオ ガチャ 新作"
  },
  {
    "id": "x_2042113648907448647",
    "platform": "X",
    "username": "@panko66666",
    "content": "[PR]【7月再販予約】【送料無料】サンリオキャラクターズ なかよしドロップチャーム 全4種 コンプリート 楽天市場で予約開始🌼 🔻ノリーズコレクション https://t.co/RBr7beznUZ ハローキティ＆ハローミミィとリトルツインスターズが好みすぎる💖 ガチャガチャ ガチャ ガシャポン 入荷 新作 — ぱにーに🥖 (@panko66666) April 9, 2026",
    "url": "https://x.com/panko66666/status/2042113648907448647",
    "postedAt": "2026-04-18T07:18:51.079104+00:00",
    "matchedKeyword": "サンリオ ガチャ 新作"
  },
  {
    "id": "x_2042098090589720973",
    "platform": "X",
    "username": "@Mandai_Aomori",
    "content": "💁🏻‍♀️今週のガチャコーナーNEWS📺🌸 【絶対あたるガチャ】 ラブブ好きな🐰💕常連様に届け～✉️ ＼THE MONSTERS×Sanrio Characters／ が絶対あたるガチャに登場😆💖 【カードコーナー】 新作オリパのご紹介✨️ ＼🌸ブイズの❕新生活応援オリパ🌸／ 1口3000円 全72口👄 【カプセルトイコーナー】… pic.twitter.com/QtM9TnVDxh — 万代新青森店 (@Mandai_Aomori) April 9, 2026",
    "url": "https://x.com/Mandai_Aomori/status/2042098090589720973",
    "postedAt": "2026-04-18T07:18:51.079104+00:00",
    "matchedKeyword": "サンリオ ガチャ 新作"
  },
  {
    "id": "x_2041729878035480922",
    "platform": "X",
    "username": "@festalandutadu",
    "content": "サンリオ ガチャ 新作 に関する投稿",
    "url": "https://x.com/festalandutadu/status/2041729878035480922",
    "postedAt": "2026-04-18T07:18:51.079104+00:00",
    "matchedKeyword": "サンリオ ガチャ 新作"
  },
  {
    "id": "x_2041452132948398337",
    "platform": "X",
    "username": "@o76DXxobZi99209",
    "content": "サンリオ ガチャ 新作 に関する投稿",
    "url": "https://x.com/o76DXxobZi99209/status/2041452132948398337",
    "postedAt": "2026-04-18T07:18:51.079104+00:00",
    "matchedKeyword": "サンリオ ガチャ 新作"
  },
  {
    "id": "x_2041376605420110166",
    "platform": "X",
    "username": "@drecap_kusatsu",
    "content": "サンリオ ガチャ 新作 に関する投稿",
    "url": "https://x.com/drecap_kusatsu/status/2041376605420110166",
    "postedAt": "2026-04-18T07:18:51.079104+00:00",
    "matchedKeyword": "サンリオ ガチャ 新作"
  },
  {
    "id": "x_2041078460601569633",
    "platform": "X",
    "username": "@Play_Gacha",
    "content": "サンリオ ガチャ 新作 に関する投稿",
    "url": "https://x.com/Play_Gacha/status/2041078460601569633",
    "postedAt": "2026-04-18T07:18:51.079104+00:00",
    "matchedKeyword": "サンリオ ガチャ 新作"
  },
  {
    "id": "x_2041041763746697290",
    "platform": "X",
    "username": "@jagajaga7575",
    "content": "サンリオ ガチャ 新作 に関する投稿",
    "url": "https://x.com/jagajaga7575/status/2041041763746697290",
    "postedAt": "2026-04-18T07:18:51.079104+00:00",
    "matchedKeyword": "サンリオ ガチャ 新作"
  },
  {
    "id": "x_2040991907753623845",
    "platform": "X",
    "username": "@w9KwleZR6CjEOGV",
    "content": "サンリオ ガチャ 新作 に関する投稿",
    "url": "https://x.com/w9KwleZR6CjEOGV/status/2040991907753623845",
    "postedAt": "2026-04-18T07:18:51.079104+00:00",
    "matchedKeyword": "サンリオ ガチャ 新作"
  },
  {
    "id": "x_2039911332003348649",
    "platform": "X",
    "username": "@suugar1357",
    "content": "サンリオ ガチャ 新作 に関する投稿",
    "url": "https://x.com/suugar1357/status/2039911332003348649",
    "postedAt": "2026-04-18T07:18:51.079104+00:00",
    "matchedKeyword": "サンリオ ガチャ 新作"
  },
  {
    "id": "x_2039768951090217208",
    "platform": "X",
    "username": "@jagajaga7575",
    "content": "サンリオ ガチャ 新作 に関する投稿",
    "url": "https://x.com/jagajaga7575/status/2039768951090217208",
    "postedAt": "2026-04-18T07:18:51.079104+00:00",
    "matchedKeyword": "サンリオ ガチャ 新作"
  },
  {
    "id": "x_2039717980662317126",
    "platform": "X",
    "username": "@xiying_niziu",
    "content": "サンリオ ガチャ 新作 に関する投稿",
    "url": "https://x.com/xiying_niziu/status/2039717980662317126",
    "postedAt": "2026-04-18T07:18:51.079104+00:00",
    "matchedKeyword": "サンリオ ガチャ 新作"
  },
  {
    "id": "x_2039228769974858116",
    "platform": "X",
    "username": "@app_pia",
    "content": "サンリオ ガチャ 新作 に関する投稿",
    "url": "https://x.com/app_pia/status/2039228769974858116",
    "postedAt": "2026-04-18T07:18:51.079104+00:00",
    "matchedKeyword": "サンリオ ガチャ 新作"
  },
  {
    "id": "x_2039213672417972298",
    "platform": "X",
    "username": "@grok",
    "content": "サンリオ ガチャ 新作 に関する投稿",
    "url": "https://x.com/grok/status/2039213672417972298",
    "postedAt": "2026-04-18T07:18:51.079104+00:00",
    "matchedKeyword": "サンリオ ガチャ 新作"
  },
  {
    "id": "x_2039211039938736510",
    "platform": "X",
    "username": "@9_tpe",
    "content": "サンリオ ガチャ 新作 に関する投稿",
    "url": "https://x.com/9_tpe/status/2039211039938736510",
    "postedAt": "2026-04-18T07:18:51.079104+00:00",
    "matchedKeyword": "サンリオ ガチャ 新作"
  },
  {
    "id": "x_2039152159602917570",
    "platform": "X",
    "username": "@Koppvho",
    "content": "サンリオ ガチャ 新作 に関する投稿",
    "url": "https://x.com/Koppvho/status/2039152159602917570",
    "postedAt": "2026-04-18T07:18:51.079104+00:00",
    "matchedKeyword": "サンリオ ガチャ 新作"
  },
  {
    "id": "x_2038525866641363206",
    "platform": "X",
    "username": "@w9KwleZR6CjEOGV",
    "content": "サンリオ ガチャ 新作 に関する投稿",
    "url": "https://x.com/w9KwleZR6CjEOGV/status/2038525866641363206",
    "postedAt": "2026-04-18T07:18:51.079104+00:00",
    "matchedKeyword": "サンリオ ガチャ 新作"
  },
  {
    "id": "x_2045376328011288927",
    "platform": "X",
    "username": "@umeshu_idol",
    "content": "たまごっち ガチャ に関する投稿",
    "url": "https://x.com/umeshu_idol/status/2045376328011288927",
    "postedAt": "2026-04-18T07:18:49.391514+00:00",
    "matchedKeyword": "たまごっち ガチャ"
  },
  {
    "id": "x_2045398888321094024",
    "platform": "X",
    "username": "@hs____615",
    "content": "たまごっち ガチャ に関する投稿",
    "url": "https://x.com/hs____615/status/2045398888321094024",
    "postedAt": "2026-04-18T07:18:49.391514+00:00",
    "matchedKeyword": "たまごっち ガチャ"
  },
  {
    "id": "x_2045398639720481195",
    "platform": "X",
    "username": "@ha_machaki_ru",
    "content": "たまごっち ガチャ に関する投稿",
    "url": "https://x.com/ha_machaki_ru/status/2045398639720481195",
    "postedAt": "2026-04-18T07:18:49.391514+00:00",
    "matchedKeyword": "たまごっち ガチャ"
  },
  {
    "id": "x_2045397512232784354",
    "platform": "X",
    "username": "@potama_chi",
    "content": "たまごっち ガチャ に関する投稿",
    "url": "https://x.com/potama_chi/status/2045397512232784354",
    "postedAt": "2026-04-18T07:18:49.391514+00:00",
    "matchedKeyword": "たまごっち ガチャ"
  },
  {
    "id": "x_2045393829604512005",
    "platform": "X",
    "username": "@tkt_gds",
    "content": "たまごっち ガチャ に関する投稿",
    "url": "https://x.com/tkt_gds/status/2045393829604512005",
    "postedAt": "2026-04-18T07:18:49.391514+00:00",
    "matchedKeyword": "たまごっち ガチャ"
  },
  {
    "id": "x_2045389371571052844",
    "platform": "X",
    "username": "@mykj_514",
    "content": "たまごっち ガチャ に関する投稿",
    "url": "https://x.com/mykj_514/status/2045389371571052844",
    "postedAt": "2026-04-18T07:18:49.391514+00:00",
    "matchedKeyword": "たまごっち ガチャ"
  },
  {
    "id": "x_2045387888708534299",
    "platform": "X",
    "username": "@hpmchan",
    "content": "たまごっち ガチャ に関する投稿",
    "url": "https://x.com/hpmchan/status/2045387888708534299",
    "postedAt": "2026-04-18T07:18:49.391514+00:00",
    "matchedKeyword": "たまごっち ガチャ"
  },
  {
    "id": "x_2045383488891994372",
    "platform": "X",
    "username": "@XbOh0n",
    "content": "たまごっち ガチャ に関する投稿",
    "url": "https://x.com/XbOh0n/status/2045383488891994372",
    "postedAt": "2026-04-18T07:18:49.391514+00:00",
    "matchedKeyword": "たまごっち ガチャ"
  },
  {
    "id": "x_2045381847409103284",
    "platform": "X",
    "username": "@I8b2Rnf26y90505",
    "content": "たまごっち ガチャ に関する投稿",
    "url": "https://x.com/I8b2Rnf26y90505/status/2045381847409103284",
    "postedAt": "2026-04-18T07:18:49.391514+00:00",
    "matchedKeyword": "たまごっち ガチャ"
  },
  {
    "id": "x_2045379852099023101",
    "platform": "X",
    "username": "@aaeerrooo",
    "content": "たまごっち ガチャ に関する投稿",
    "url": "https://x.com/aaeerrooo/status/2045379852099023101",
    "postedAt": "2026-04-18T07:18:49.391514+00:00",
    "matchedKeyword": "たまごっち ガチャ"
  },
  {
    "id": "x_2045377634490826861",
    "platform": "X",
    "username": "@cocoaa7878",
    "content": "たまごっち ガチャ に関する投稿",
    "url": "https://x.com/cocoaa7878/status/2045377634490826861",
    "postedAt": "2026-04-18T07:18:49.391514+00:00",
    "matchedKeyword": "たまごっち ガチャ"
  },
  {
    "id": "x_2045376394931405159",
    "platform": "X",
    "username": "@88drgn88",
    "content": "たまごっち ガチャ に関する投稿",
    "url": "https://x.com/88drgn88/status/2045376394931405159",
    "postedAt": "2026-04-18T07:18:49.391514+00:00",
    "matchedKeyword": "たまごっち ガチャ"
  },
  {
    "id": "x_2045375563477745827",
    "platform": "X",
    "username": "@Ryon37_",
    "content": "たまごっち ガチャ に関する投稿",
    "url": "https://x.com/Ryon37_/status/2045375563477745827",
    "postedAt": "2026-04-18T07:18:49.391514+00:00",
    "matchedKeyword": "たまごっち ガチャ"
  },
  {
    "id": "x_2045373395169403110",
    "platform": "X",
    "username": "@56569rix2n",
    "content": "たまごっち ガチャ に関する投稿",
    "url": "https://x.com/56569rix2n/status/2045373395169403110",
    "postedAt": "2026-04-18T07:18:49.391514+00:00",
    "matchedKeyword": "たまごっち ガチャ"
  },
  {
    "id": "x_2045371755481726981",
    "platform": "X",
    "username": "@keipon_n",
    "content": "たまごっち ガチャ に関する投稿",
    "url": "https://x.com/keipon_n/status/2045371755481726981",
    "postedAt": "2026-04-18T07:18:49.391514+00:00",
    "matchedKeyword": "たまごっち ガチャ"
  },
  {
    "id": "x_2045370627205513668",
    "platform": "X",
    "username": "@qrsise",
    "content": "たまごっち ガチャ に関する投稿",
    "url": "https://x.com/qrsise/status/2045370627205513668",
    "postedAt": "2026-04-18T07:18:49.391514+00:00",
    "matchedKeyword": "たまごっち ガチャ"
  },
  {
    "id": "x_2045367636574491041",
    "platform": "X",
    "username": "@s2_Mitchellsan",
    "content": "たまごっち ガチャ に関する投稿",
    "url": "https://x.com/s2_Mitchellsan/status/2045367636574491041",
    "postedAt": "2026-04-18T07:18:49.391514+00:00",
    "matchedKeyword": "たまごっち ガチャ"
  },
  {
    "id": "x_2045367513899524121",
    "platform": "X",
    "username": "@45rabbitj",
    "content": "たまごっち ガチャ に関する投稿",
    "url": "https://x.com/45rabbitj/status/2045367513899524121",
    "postedAt": "2026-04-18T07:18:49.391514+00:00",
    "matchedKeyword": "たまごっち ガチャ"
  },
  {
    "id": "x_2045363996841418876",
    "platform": "X",
    "username": "@MDR_HKS_P",
    "content": "たまごっち ガチャ に関する投稿",
    "url": "https://x.com/MDR_HKS_P/status/2045363996841418876",
    "postedAt": "2026-04-18T07:18:49.391514+00:00",
    "matchedKeyword": "たまごっち ガチャ"
  },
  {
    "id": "x_2045361441243644365",
    "platform": "X",
    "username": "@_43cc",
    "content": "たまごっち ガチャ に関する投稿",
    "url": "https://x.com/_43cc/status/2045361441243644365",
    "postedAt": "2026-04-18T07:18:49.391514+00:00",
    "matchedKeyword": "たまごっち ガチャ"
  },
  {
    "id": "x_2045358961227162017",
    "platform": "X",
    "username": "@a____m43",
    "content": "たまごっち ガチャ に関する投稿",
    "url": "https://x.com/a____m43/status/2045358961227162017",
    "postedAt": "2026-04-18T07:18:49.391514+00:00",
    "matchedKeyword": "たまごっち ガチャ"
  },
  {
    "id": "x_2045358216348078206",
    "platform": "X",
    "username": "@oyoimo9",
    "content": "たまごっち ガチャ に関する投稿",
    "url": "https://x.com/oyoimo9/status/2045358216348078206",
    "postedAt": "2026-04-18T07:18:49.391514+00:00",
    "matchedKeyword": "たまごっち ガチャ"
  },
  {
    "id": "x_2045357404662190395",
    "platform": "X",
    "username": "@yomotsuhegui11",
    "content": "たまごっち ガチャ に関する投稿",
    "url": "https://x.com/yomotsuhegui11/status/2045357404662190395",
    "postedAt": "2026-04-18T07:18:49.391514+00:00",
    "matchedKeyword": "たまごっち ガチャ"
  },
  {
    "id": "x_2045354506763010440",
    "platform": "X",
    "username": "@a_ny2312",
    "content": "たまごっち ガチャ に関する投稿",
    "url": "https://x.com/a_ny2312/status/2045354506763010440",
    "postedAt": "2026-04-18T07:18:49.391514+00:00",
    "matchedKeyword": "たまごっち ガチャ"
  },
  {
    "id": "x_2045353887583060188",
    "platform": "X",
    "username": "@peterpanisexo",
    "content": "たまごっち ガチャ に関する投稿",
    "url": "https://x.com/peterpanisexo/status/2045353887583060188",
    "postedAt": "2026-04-18T07:18:49.391514+00:00",
    "matchedKeyword": "たまごっち ガチャ"
  },
  {
    "id": "x_2045353839151501560",
    "platform": "X",
    "username": "@B9pt03",
    "content": "たまごっち ガチャ に関する投稿",
    "url": "https://x.com/B9pt03/status/2045353839151501560",
    "postedAt": "2026-04-18T07:18:49.391514+00:00",
    "matchedKeyword": "たまごっち ガチャ"
  },
  {
    "id": "x_2045352277033226405",
    "platform": "X",
    "username": "@otori_tanaka",
    "content": "たまごっち ガチャ に関する投稿",
    "url": "https://x.com/otori_tanaka/status/2045352277033226405",
    "postedAt": "2026-04-18T07:18:49.391514+00:00",
    "matchedKeyword": "たまごっち ガチャ"
  },
  {
    "id": "x_2045351723192209521",
    "platform": "X",
    "username": "@soramame__beans",
    "content": "たまごっち ガチャ に関する投稿",
    "url": "https://x.com/soramame__beans/status/2045351723192209521",
    "postedAt": "2026-04-18T07:18:49.391514+00:00",
    "matchedKeyword": "たまごっち ガチャ"
  },
  {
    "id": "x_2045351668712456629",
    "platform": "X",
    "username": "@mendokusai2021",
    "content": "たまごっち ガチャ に関する投稿",
    "url": "https://x.com/mendokusai2021/status/2045351668712456629",
    "postedAt": "2026-04-18T07:18:49.391514+00:00",
    "matchedKeyword": "たまごっち ガチャ"
  },
  {
    "id": "x_2045351420799717449",
    "platform": "X",
    "username": "@yeonrinnn1313",
    "content": "たまごっち ガチャ に関する投稿",
    "url": "https://x.com/yeonrinnn1313/status/2045351420799717449",
    "postedAt": "2026-04-18T07:18:49.391514+00:00",
    "matchedKeyword": "たまごっち ガチャ"
  },
  {
    "id": "x_2045350503178219588",
    "platform": "X",
    "username": "@ochamaru1212",
    "content": "たまごっち ガチャ に関する投稿",
    "url": "https://x.com/ochamaru1212/status/2045350503178219588",
    "postedAt": "2026-04-18T07:18:49.391514+00:00",
    "matchedKeyword": "たまごっち ガチャ"
  },
  {
    "id": "x_2045347641123643871",
    "platform": "X",
    "username": "@Qoo_torihikky",
    "content": "たまごっち ガチャ に関する投稿",
    "url": "https://x.com/Qoo_torihikky/status/2045347641123643871",
    "postedAt": "2026-04-18T07:18:49.391514+00:00",
    "matchedKeyword": "たまごっち ガチャ"
  },
  {
    "id": "x_2045346097665871930",
    "platform": "X",
    "username": "@yyyyyu_ac",
    "content": "たまごっち ガチャ に関する投稿",
    "url": "https://x.com/yyyyyu_ac/status/2045346097665871930",
    "postedAt": "2026-04-18T07:18:49.391514+00:00",
    "matchedKeyword": "たまごっち ガチャ"
  },
  {
    "id": "x_2045340666369392750",
    "platform": "X",
    "username": "@mihani0914",
    "content": "たまごっち ガチャ に関する投稿",
    "url": "https://x.com/mihani0914/status/2045340666369392750",
    "postedAt": "2026-04-18T07:18:49.391514+00:00",
    "matchedKeyword": "たまごっち ガチャ"
  },
  {
    "id": "x_2045340160326607285",
    "platform": "X",
    "username": "@9_nsi5",
    "content": "たまごっち ガチャ に関する投稿",
    "url": "https://x.com/9_nsi5/status/2045340160326607285",
    "postedAt": "2026-04-18T07:18:49.391514+00:00",
    "matchedKeyword": "たまごっち ガチャ"
  },
  {
    "id": "x_2045336931777864030",
    "platform": "X",
    "username": "@mog2mugi8",
    "content": "たまごっち ガチャ に関する投稿",
    "url": "https://x.com/mog2mugi8/status/2045336931777864030",
    "postedAt": "2026-04-18T07:18:49.391514+00:00",
    "matchedKeyword": "たまごっち ガチャ"
  },
  {
    "id": "x_2045330522289897631",
    "platform": "X",
    "username": "@Umesuke_18",
    "content": "たまごっち ガチャ に関する投稿",
    "url": "https://x.com/Umesuke_18/status/2045330522289897631",
    "postedAt": "2026-04-18T07:18:49.391514+00:00",
    "matchedKeyword": "たまごっち ガチャ"
  },
  {
    "id": "x_2045328708001734904",
    "platform": "X",
    "username": "@youtube_0509",
    "content": "たまごっち ガチャ に関する投稿",
    "url": "https://x.com/youtube_0509/status/2045328708001734904",
    "postedAt": "2026-04-18T07:18:49.391514+00:00",
    "matchedKeyword": "たまごっち ガチャ"
  },
  {
    "id": "x_2045327611258376487",
    "platform": "X",
    "username": "@na_bas2",
    "content": "たまごっち ガチャ に関する投稿",
    "url": "https://x.com/na_bas2/status/2045327611258376487",
    "postedAt": "2026-04-18T07:18:49.391514+00:00",
    "matchedKeyword": "たまごっち ガチャ"
  },
  {
    "id": "x_2045326075434328111",
    "platform": "X",
    "username": "@xo_xx59",
    "content": "たまごっち ガチャ に関する投稿",
    "url": "https://x.com/xo_xx59/status/2045326075434328111",
    "postedAt": "2026-04-18T07:18:49.391514+00:00",
    "matchedKeyword": "たまごっち ガチャ"
  },
  {
    "id": "x_2044650412989653096",
    "platform": "X",
    "username": "@asahi_eigyo_2",
    "content": "カプセルトイ 新商品 に関する投稿",
    "url": "https://x.com/asahi_eigyo_2/status/2044650412989653096",
    "postedAt": "2026-04-18T07:18:47.574645+00:00",
    "matchedKeyword": "カプセルトイ 新商品"
  },
  {
    "id": "x_2045401482330251592",
    "platform": "X",
    "username": "@Capcomharajuku",
    "content": "カプセルトイ 新商品 に関する投稿",
    "url": "https://x.com/Capcomharajuku/status/2045401482330251592",
    "postedAt": "2026-04-18T07:18:47.574645+00:00",
    "matchedKeyword": "カプセルトイ 新商品"
  },
  {
    "id": "x_2045401450633924666",
    "platform": "X",
    "username": "@Capcomharajuku",
    "content": "カプセルトイ 新商品 に関する投稿",
    "url": "https://x.com/Capcomharajuku/status/2045401450633924666",
    "postedAt": "2026-04-18T07:18:47.574645+00:00",
    "matchedKeyword": "カプセルトイ 新商品"
  },
  {
    "id": "x_2045401425652638102",
    "platform": "X",
    "username": "@Capcomharajuku",
    "content": "カプセルトイ 新商品 に関する投稿",
    "url": "https://x.com/Capcomharajuku/status/2045401425652638102",
    "postedAt": "2026-04-18T07:18:47.574645+00:00",
    "matchedKeyword": "カプセルトイ 新商品"
  },
  {
    "id": "x_2045396634247553282",
    "platform": "X",
    "username": "@Cpla0425",
    "content": "カプセルトイ 新商品 に関する投稿",
    "url": "https://x.com/Cpla0425/status/2045396634247553282",
    "postedAt": "2026-04-18T07:18:47.574645+00:00",
    "matchedKeyword": "カプセルトイ 新商品"
  },
  {
    "id": "x_2045396595584504127",
    "platform": "X",
    "username": "@Cpla0425",
    "content": "カプセルトイ 新商品 に関する投稿",
    "url": "https://x.com/Cpla0425/status/2045396595584504127",
    "postedAt": "2026-04-18T07:18:47.574645+00:00",
    "matchedKeyword": "カプセルトイ 新商品"
  },
  {
    "id": "x_2045396525698986058",
    "platform": "X",
    "username": "@Cpla0425",
    "content": "カプセルトイ 新商品 に関する投稿",
    "url": "https://x.com/Cpla0425/status/2045396525698986058",
    "postedAt": "2026-04-18T07:18:47.574645+00:00",
    "matchedKeyword": "カプセルトイ 新商品"
  },
  {
    "id": "x_2045396487384031689",
    "platform": "X",
    "username": "@Cpla0425",
    "content": "カプセルトイ 新商品 に関する投稿",
    "url": "https://x.com/Cpla0425/status/2045396487384031689",
    "postedAt": "2026-04-18T07:18:47.574645+00:00",
    "matchedKeyword": "カプセルトイ 新商品"
  },
  {
    "id": "x_2045396416961585609",
    "platform": "X",
    "username": "@drecap_MainLabo",
    "content": "カプセルトイ 新商品 に関する投稿",
    "url": "https://x.com/drecap_MainLabo/status/2045396416961585609",
    "postedAt": "2026-04-18T07:18:47.574645+00:00",
    "matchedKeyword": "カプセルトイ 新商品"
  },
  {
    "id": "x_2045396246337298498",
    "platform": "X",
    "username": "@Cpla470164",
    "content": "カプセルトイ 新商品 に関する投稿",
    "url": "https://x.com/Cpla470164/status/2045396246337298498",
    "postedAt": "2026-04-18T07:18:47.574645+00:00",
    "matchedKeyword": "カプセルトイ 新商品"
  },
  {
    "id": "x_2045396235088257127",
    "platform": "X",
    "username": "@Cpla470164",
    "content": "カプセルトイ 新商品 に関する投稿",
    "url": "https://x.com/Cpla470164/status/2045396235088257127",
    "postedAt": "2026-04-18T07:18:47.574645+00:00",
    "matchedKeyword": "カプセルトイ 新商品"
  },
  {
    "id": "x_2045396222350110787",
    "platform": "X",
    "username": "@Cpla470164",
    "content": "カプセルトイ 新商品 に関する投稿",
    "url": "https://x.com/Cpla470164/status/2045396222350110787",
    "postedAt": "2026-04-18T07:18:47.574645+00:00",
    "matchedKeyword": "カプセルトイ 新商品"
  },
  {
    "id": "x_2045393964245909905",
    "platform": "X",
    "username": "@drecap_MainLabo",
    "content": "カプセルトイ 新商品 に関する投稿",
    "url": "https://x.com/drecap_MainLabo/status/2045393964245909905",
    "postedAt": "2026-04-18T07:18:47.574645+00:00",
    "matchedKeyword": "カプセルトイ 新商品"
  },
  {
    "id": "x_2045391993413787854",
    "platform": "X",
    "username": "@drecap_MainLabo",
    "content": "カプセルトイ 新商品 に関する投稿",
    "url": "https://x.com/drecap_MainLabo/status/2045391993413787854",
    "postedAt": "2026-04-18T07:18:47.574645+00:00",
    "matchedKeyword": "カプセルトイ 新商品"
  },
  {
    "id": "x_2045390699856842835",
    "platform": "X",
    "username": "@gachafoleo",
    "content": "カプセルトイ 新商品 に関する投稿",
    "url": "https://x.com/gachafoleo/status/2045390699856842835",
    "postedAt": "2026-04-18T07:18:47.574645+00:00",
    "matchedKeyword": "カプセルトイ 新商品"
  },
  {
    "id": "x_2045389543847899166",
    "platform": "X",
    "username": "@Cplayakiudon",
    "content": "カプセルトイ 新商品 に関する投稿",
    "url": "https://x.com/Cplayakiudon/status/2045389543847899166",
    "postedAt": "2026-04-18T07:18:47.574645+00:00",
    "matchedKeyword": "カプセルトイ 新商品"
  },
  {
    "id": "x_2045387038523060393",
    "platform": "X",
    "username": "@cplahakataguchi",
    "content": "カプセルトイ 新商品 に関する投稿",
    "url": "https://x.com/cplahakataguchi/status/2045387038523060393",
    "postedAt": "2026-04-18T07:18:47.574645+00:00",
    "matchedKeyword": "カプセルトイ 新商品"
  },
  {
    "id": "x_2045385380137156673",
    "platform": "X",
    "username": "@Cpla79968708",
    "content": "カプセルトイ 新商品 に関する投稿",
    "url": "https://x.com/Cpla79968708/status/2045385380137156673",
    "postedAt": "2026-04-18T07:18:47.574645+00:00",
    "matchedKeyword": "カプセルトイ 新商品"
  },
  {
    "id": "x_2045384825650258109",
    "platform": "X",
    "username": "@Cplakamiiso",
    "content": "カプセルトイ 新商品 に関する投稿",
    "url": "https://x.com/Cplakamiiso/status/2045384825650258109",
    "postedAt": "2026-04-18T07:18:47.574645+00:00",
    "matchedKeyword": "カプセルトイ 新商品"
  },
  {
    "id": "x_2045383491723079800",
    "platform": "X",
    "username": "@Cplakamiiso",
    "content": "カプセルトイ 新商品 に関する投稿",
    "url": "https://x.com/Cplakamiiso/status/2045383491723079800",
    "postedAt": "2026-04-18T07:18:47.574645+00:00",
    "matchedKeyword": "カプセルトイ 新商品"
  },
  {
    "id": "x_2045382205917294872",
    "platform": "X",
    "username": "@CEkimo48326",
    "content": "カプセルトイ 新商品 に関する投稿",
    "url": "https://x.com/CEkimo48326/status/2045382205917294872",
    "postedAt": "2026-04-18T07:18:47.574645+00:00",
    "matchedKeyword": "カプセルトイ 新商品"
  },
  {
    "id": "x_2045381669289697723",
    "platform": "X",
    "username": "@Cplashinjuku",
    "content": "カプセルトイ 新商品 に関する投稿",
    "url": "https://x.com/Cplashinjuku/status/2045381669289697723",
    "postedAt": "2026-04-18T07:18:47.574645+00:00",
    "matchedKeyword": "カプセルトイ 新商品"
  },
  {
    "id": "x_2045381661060370541",
    "platform": "X",
    "username": "@Cplashinjuku",
    "content": "カプセルトイ 新商品 に関する投稿",
    "url": "https://x.com/Cplashinjuku/status/2045381661060370541",
    "postedAt": "2026-04-18T07:18:47.574645+00:00",
    "matchedKeyword": "カプセルトイ 新商品"
  },
  {
    "id": "x_2045381115939332288",
    "platform": "X",
    "username": "@drecap_MainLabo",
    "content": "カプセルトイ 新商品 に関する投稿",
    "url": "https://x.com/drecap_MainLabo/status/2045381115939332288",
    "postedAt": "2026-04-18T07:18:47.574645+00:00",
    "matchedKeyword": "カプセルトイ 新商品"
  },
  {
    "id": "x_2045381055193174080",
    "platform": "X",
    "username": "@Cplakamiiso",
    "content": "カプセルトイ 新商品 に関する投稿",
    "url": "https://x.com/Cplakamiiso/status/2045381055193174080",
    "postedAt": "2026-04-18T07:18:47.574645+00:00",
    "matchedKeyword": "カプセルトイ 新商品"
  },
  {
    "id": "x_2045379907178660075",
    "platform": "X",
    "username": "@Capcomnanba",
    "content": "カプセルトイ 新商品 に関する投稿",
    "url": "https://x.com/Capcomnanba/status/2045379907178660075",
    "postedAt": "2026-04-18T07:18:47.574645+00:00",
    "matchedKeyword": "カプセルトイ 新商品"
  },
  {
    "id": "x_2045379011866689714",
    "platform": "X",
    "username": "@cpla_amukokura",
    "content": "カプセルトイ 新商品 に関する投稿",
    "url": "https://x.com/cpla_amukokura/status/2045379011866689714",
    "postedAt": "2026-04-18T07:18:47.574645+00:00",
    "matchedKeyword": "カプセルトイ 新商品"
  },
  {
    "id": "x_2045378362521362673",
    "platform": "X",
    "username": "@drecap_MainLabo",
    "content": "カプセルトイ 新商品 に関する投稿",
    "url": "https://x.com/drecap_MainLabo/status/2045378362521362673",
    "postedAt": "2026-04-18T07:18:47.574645+00:00",
    "matchedKeyword": "カプセルトイ 新商品"
  },
  {
    "id": "x_2045376652503654864",
    "platform": "X",
    "username": "@Cplakamiiso",
    "content": "カプセルトイ 新商品 に関する投稿",
    "url": "https://x.com/Cplakamiiso/status/2045376652503654864",
    "postedAt": "2026-04-18T07:18:47.574645+00:00",
    "matchedKeyword": "カプセルトイ 新商品"
  },
  {
    "id": "x_2045376156535496968",
    "platform": "X",
    "username": "@Cpla428446Pla",
    "content": "カプセルトイ 新商品 に関する投稿",
    "url": "https://x.com/Cpla428446Pla/status/2045376156535496968",
    "postedAt": "2026-04-18T07:18:47.574645+00:00",
    "matchedKeyword": "カプセルトイ 新商品"
  },
  {
    "id": "x_2045376126202319229",
    "platform": "X",
    "username": "@GiGO_shinokubo",
    "content": "カプセルトイ 新商品 に関する投稿",
    "url": "https://x.com/GiGO_shinokubo/status/2045376126202319229",
    "postedAt": "2026-04-18T07:18:47.574645+00:00",
    "matchedKeyword": "カプセルトイ 新商品"
  },
  {
    "id": "x_2045375937806770630",
    "platform": "X",
    "username": "@Cpla51",
    "content": "カプセルトイ 新商品 に関する投稿",
    "url": "https://x.com/Cpla51/status/2045375937806770630",
    "postedAt": "2026-04-18T07:18:47.574645+00:00",
    "matchedKeyword": "カプセルトイ 新商品"
  },
  {
    "id": "x_2045375874586079537",
    "platform": "X",
    "username": "@Cplakamiiso",
    "content": "カプセルトイ 新商品 に関する投稿",
    "url": "https://x.com/Cplakamiiso/status/2045375874586079537",
    "postedAt": "2026-04-18T07:18:47.574645+00:00",
    "matchedKeyword": "カプセルトイ 新商品"
  },
  {
    "id": "x_2045375691085250827",
    "platform": "X",
    "username": "@Cplakamiiso",
    "content": "カプセルトイ 新商品 に関する投稿",
    "url": "https://x.com/Cplakamiiso/status/2045375691085250827",
    "postedAt": "2026-04-18T07:18:47.574645+00:00",
    "matchedKeyword": "カプセルトイ 新商品"
  },
  {
    "id": "x_2045375577360838845",
    "platform": "X",
    "username": "@Cplakamiiso",
    "content": "カプセルトイ 新商品 に関する投稿",
    "url": "https://x.com/Cplakamiiso/status/2045375577360838845",
    "postedAt": "2026-04-18T07:18:47.574645+00:00",
    "matchedKeyword": "カプセルトイ 新商品"
  },
  {
    "id": "x_2045374616517177813",
    "platform": "X",
    "username": "@Cpla428446Pla",
    "content": "カプセルトイ 新商品 に関する投稿",
    "url": "https://x.com/Cpla428446Pla/status/2045374616517177813",
    "postedAt": "2026-04-18T07:18:47.574645+00:00",
    "matchedKeyword": "カプセルトイ 新商品"
  },
  {
    "id": "x_2045373589927637174",
    "platform": "X",
    "username": "@cpla_omokado",
    "content": "カプセルトイ 新商品 に関する投稿",
    "url": "https://x.com/cpla_omokado/status/2045373589927637174",
    "postedAt": "2026-04-18T07:18:47.574645+00:00",
    "matchedKeyword": "カプセルトイ 新商品"
  },
  {
    "id": "x_2045373183700983981",
    "platform": "X",
    "username": "@cpla_omokado",
    "content": "カプセルトイ 新商品 に関する投稿",
    "url": "https://x.com/cpla_omokado/status/2045373183700983981",
    "postedAt": "2026-04-18T07:18:47.574645+00:00",
    "matchedKeyword": "カプセルトイ 新商品"
  },
  {
    "id": "x_2045373138901619078",
    "platform": "X",
    "username": "@Cpla79968708",
    "content": "カプセルトイ 新商品 に関する投稿",
    "url": "https://x.com/Cpla79968708/status/2045373138901619078",
    "postedAt": "2026-04-18T07:18:47.574645+00:00",
    "matchedKeyword": "カプセルトイ 新商品"
  },
  {
    "id": "x_2045140229972222219",
    "platform": "X",
    "username": "@DOPA_Oripa",
    "content": "ガチャ 新作 に関する投稿",
    "url": "https://x.com/DOPA_Oripa/status/2045140229972222219",
    "postedAt": "2026-04-18T07:18:46.007493+00:00",
    "matchedKeyword": "ガチャ 新作"
  },
  {
    "id": "x_2045397228639134181",
    "platform": "X",
    "username": "@nctiritiru_taka",
    "content": "ガチャ 新作 に関する投稿",
    "url": "https://x.com/nctiritiru_taka/status/2045397228639134181",
    "postedAt": "2026-04-18T07:18:46.007493+00:00",
    "matchedKeyword": "ガチャ 新作"
  },
  {
    "id": "x_2045396768716955684",
    "platform": "X",
    "username": "@mai_nahanaha",
    "content": "ガチャ 新作 に関する投稿",
    "url": "https://x.com/mai_nahanaha/status/2045396768716955684",
    "postedAt": "2026-04-18T07:18:46.007493+00:00",
    "matchedKeyword": "ガチャ 新作"
  },
  {
    "id": "x_2045389512277414318",
    "platform": "X",
    "username": "@ano_2520_chan",
    "content": "ガチャ 新作 に関する投稿",
    "url": "https://x.com/ano_2520_chan/status/2045389512277414318",
    "postedAt": "2026-04-18T07:18:46.007493+00:00",
    "matchedKeyword": "ガチャ 新作"
  },
  {
    "id": "x_2045374619398660444",
    "platform": "X",
    "username": "@u_pura_kitakata",
    "content": "ガチャ 新作 に関する投稿",
    "url": "https://x.com/u_pura_kitakata/status/2045374619398660444",
    "postedAt": "2026-04-18T07:18:46.007493+00:00",
    "matchedKeyword": "ガチャ 新作"
  },
  {
    "id": "x_2045368673268064422",
    "platform": "X",
    "username": "@jagajaga7575",
    "content": "ガチャ 新作 に関する投稿",
    "url": "https://x.com/jagajaga7575/status/2045368673268064422",
    "postedAt": "2026-04-18T07:18:46.007493+00:00",
    "matchedKeyword": "ガチャ 新作"
  },
  {
    "id": "x_2045355299515887886",
    "platform": "X",
    "username": "@CardDaitokuji",
    "content": "ガチャ 新作 に関する投稿",
    "url": "https://x.com/CardDaitokuji/status/2045355299515887886",
    "postedAt": "2026-04-18T07:18:46.007493+00:00",
    "matchedKeyword": "ガチャ 新作"
  },
  {
    "id": "x_2045347110770659714",
    "platform": "X",
    "username": "@suzukiSachi_a",
    "content": "ガチャ 新作 に関する投稿",
    "url": "https://x.com/suzukiSachi_a/status/2045347110770659714",
    "postedAt": "2026-04-18T07:18:46.007493+00:00",
    "matchedKeyword": "ガチャ 新作"
  },
  {
    "id": "x_2045341657605025811",
    "platform": "X",
    "username": "@AniManDigest",
    "content": "ガチャ 新作 に関する投稿",
    "url": "https://x.com/AniManDigest/status/2045341657605025811",
    "postedAt": "2026-04-18T07:18:46.007493+00:00",
    "matchedKeyword": "ガチャ 新作"
  },
  {
    "id": "x_2045337922422055013",
    "platform": "X",
    "username": "@_shibamegu_",
    "content": "ガチャ 新作 に関する投稿",
    "url": "https://x.com/_shibamegu_/status/2045337922422055013",
    "postedAt": "2026-04-18T07:18:46.007493+00:00",
    "matchedKeyword": "ガチャ 新作"
  },
  {
    "id": "x_2045321425486315529",
    "platform": "X",
    "username": "@pairium_info",
    "content": "ガチャ 新作 に関する投稿",
    "url": "https://x.com/pairium_info/status/2045321425486315529",
    "postedAt": "2026-04-18T07:18:46.007493+00:00",
    "matchedKeyword": "ガチャ 新作"
  },
  {
    "id": "x_2045319611537895817",
    "platform": "X",
    "username": "@kiku300_bowling",
    "content": "ガチャ 新作 に関する投稿",
    "url": "https://x.com/kiku300_bowling/status/2045319611537895817",
    "postedAt": "2026-04-18T07:18:46.007493+00:00",
    "matchedKeyword": "ガチャ 新作"
  },
  {
    "id": "x_2045314452082528429",
    "platform": "X",
    "username": "@u_pura_kitakata",
    "content": "ガチャ 新作 に関する投稿",
    "url": "https://x.com/u_pura_kitakata/status/2045314452082528429",
    "postedAt": "2026-04-18T07:18:46.007493+00:00",
    "matchedKeyword": "ガチャ 新作"
  },
  {
    "id": "x_2045306332128182706",
    "platform": "X",
    "username": "@pairium_info",
    "content": "ガチャ 新作 に関する投稿",
    "url": "https://x.com/pairium_info/status/2045306332128182706",
    "postedAt": "2026-04-18T07:18:46.007493+00:00",
    "matchedKeyword": "ガチャ 新作"
  },
  {
    "id": "x_2045306330358099973",
    "platform": "X",
    "username": "@pairium_info",
    "content": "ガチャ 新作 に関する投稿",
    "url": "https://x.com/pairium_info/status/2045306330358099973",
    "postedAt": "2026-04-18T07:18:46.007493+00:00",
    "matchedKeyword": "ガチャ 新作"
  },
  {
    "id": "x_2045289393196576954",
    "platform": "X",
    "username": "@mitsu5",
    "content": "ガチャ 新作 に関する投稿",
    "url": "https://x.com/mitsu5/status/2045289393196576954",
    "postedAt": "2026-04-18T07:18:46.007493+00:00",
    "matchedKeyword": "ガチャ 新作"
  },
  {
    "id": "x_2045278077459329211",
    "platform": "X",
    "username": "@jagajaga7575",
    "content": "ガチャ 新作 に関する投稿",
    "url": "https://x.com/jagajaga7575/status/2045278077459329211",
    "postedAt": "2026-04-18T07:18:46.007493+00:00",
    "matchedKeyword": "ガチャ 新作"
  },
  {
    "id": "x_2045276129158889558",
    "platform": "X",
    "username": "@pairium_info",
    "content": "ガチャ 新作 に関する投稿",
    "url": "https://x.com/pairium_info/status/2045276129158889558",
    "postedAt": "2026-04-18T07:18:46.007493+00:00",
    "matchedKeyword": "ガチャ 新作"
  },
  {
    "id": "x_2045276127363735715",
    "platform": "X",
    "username": "@pairium_info",
    "content": "ガチャ 新作 に関する投稿",
    "url": "https://x.com/pairium_info/status/2045276127363735715",
    "postedAt": "2026-04-18T07:18:46.007493+00:00",
    "matchedKeyword": "ガチャ 新作"
  },
  {
    "id": "x_2045195911463411935",
    "platform": "X",
    "username": "@masahiko3pure",
    "content": "ガチャ 新作 に関する投稿",
    "url": "https://x.com/masahiko3pure/status/2045195911463411935",
    "postedAt": "2026-04-18T07:18:46.007493+00:00",
    "matchedKeyword": "ガチャ 新作"
  },
  {
    "id": "x_2045171572844175826",
    "platform": "X",
    "username": "@nico_chee_anne",
    "content": "ガチャ 新作 に関する投稿",
    "url": "https://x.com/nico_chee_anne/status/2045171572844175826",
    "postedAt": "2026-04-18T07:18:46.007493+00:00",
    "matchedKeyword": "ガチャ 新作"
  },
  {
    "id": "x_2045159440811491565",
    "platform": "X",
    "username": "@Mazarashi07A",
    "content": "ガチャ 新作 に関する投稿",
    "url": "https://x.com/Mazarashi07A/status/2045159440811491565",
    "postedAt": "2026-04-18T07:18:46.007493+00:00",
    "matchedKeyword": "ガチャ 新作"
  },
  {
    "id": "x_2045155330980773973",
    "platform": "X",
    "username": "@PiggPARTY",
    "content": "ガチャ 新作 に関する投稿",
    "url": "https://x.com/PiggPARTY/status/2045155330980773973",
    "postedAt": "2026-04-18T07:18:46.007493+00:00",
    "matchedKeyword": "ガチャ 新作"
  },
  {
    "id": "x_2045150574589727151",
    "platform": "X",
    "username": "@masahiko3pure",
    "content": "ガチャ 新作 に関する投稿",
    "url": "https://x.com/masahiko3pure/status/2045150574589727151",
    "postedAt": "2026-04-18T07:18:46.007493+00:00",
    "matchedKeyword": "ガチャ 新作"
  },
  {
    "id": "x_2045142432048931210",
    "platform": "X",
    "username": "@muumade_muu",
    "content": "ガチャ 新作 に関する投稿",
    "url": "https://x.com/muumade_muu/status/2045142432048931210",
    "postedAt": "2026-04-18T07:18:46.007493+00:00",
    "matchedKeyword": "ガチャ 新作"
  },
  {
    "id": "x_2045140231767421349",
    "platform": "X",
    "username": "@pairium_info",
    "content": "ガチャ 新作 に関する投稿",
    "url": "https://x.com/pairium_info/status/2045140231767421349",
    "postedAt": "2026-04-18T07:18:46.007493+00:00",
    "matchedKeyword": "ガチャ 新作"
  },
  {
    "id": "x_2045132741495386352",
    "platform": "X",
    "username": "@nyaanemui",
    "content": "ガチャ 新作 に関する投稿",
    "url": "https://x.com/nyaanemui/status/2045132741495386352",
    "postedAt": "2026-04-18T07:18:46.007493+00:00",
    "matchedKeyword": "ガチャ 新作"
  },
  {
    "id": "x_2045127938056831021",
    "platform": "X",
    "username": "@hakusama_mauve",
    "content": "ガチャ 新作 に関する投稿",
    "url": "https://x.com/hakusama_mauve/status/2045127938056831021",
    "postedAt": "2026-04-18T07:18:46.007493+00:00",
    "matchedKeyword": "ガチャ 新作"
  },
  {
    "id": "x_2045127343782642112",
    "platform": "X",
    "username": "@rukarinnnozumu",
    "content": "ガチャ 新作 に関する投稿",
    "url": "https://x.com/rukarinnnozumu/status/2045127343782642112",
    "postedAt": "2026-04-18T07:18:46.007493+00:00",
    "matchedKeyword": "ガチャ 新作"
  },
  {
    "id": "x_2045125135573954767",
    "platform": "X",
    "username": "@pairium_info",
    "content": "ガチャ 新作 に関する投稿",
    "url": "https://x.com/pairium_info/status/2045125135573954767",
    "postedAt": "2026-04-18T07:18:46.007493+00:00",
    "matchedKeyword": "ガチャ 新作"
  },
  {
    "id": "x_2045125132839174199",
    "platform": "X",
    "username": "@pairium_info",
    "content": "ガチャ 新作 に関する投稿",
    "url": "https://x.com/pairium_info/status/2045125132839174199",
    "postedAt": "2026-04-18T07:18:46.007493+00:00",
    "matchedKeyword": "ガチャ 新作"
  },
  {
    "id": "x_2045117935904292919",
    "platform": "X",
    "username": "@ao57275064",
    "content": "ガチャ 新作 に関する投稿",
    "url": "https://x.com/ao57275064/status/2045117935904292919",
    "postedAt": "2026-04-18T07:18:46.007493+00:00",
    "matchedKeyword": "ガチャ 新作"
  },
  {
    "id": "x_2045115178589859848",
    "platform": "X",
    "username": "@kusiro_yui",
    "content": "ガチャ 新作 に関する投稿",
    "url": "https://x.com/kusiro_yui/status/2045115178589859848",
    "postedAt": "2026-04-18T07:18:46.007493+00:00",
    "matchedKeyword": "ガチャ 新作"
  },
  {
    "id": "x_2045107400701817139",
    "platform": "X",
    "username": "@mumunyaaaaa",
    "content": "ガチャ 新作 に関する投稿",
    "url": "https://x.com/mumunyaaaaa/status/2045107400701817139",
    "postedAt": "2026-04-18T07:18:46.007493+00:00",
    "matchedKeyword": "ガチャ 新作"
  },
  {
    "id": "x_2045106823699558858",
    "platform": "X",
    "username": "@allgamelabo",
    "content": "ガチャ 新作 に関する投稿",
    "url": "https://x.com/allgamelabo/status/2045106823699558858",
    "postedAt": "2026-04-18T07:18:46.007493+00:00",
    "matchedKeyword": "ガチャ 新作"
  },
  {
    "id": "x_2045104960799719611",
    "platform": "X",
    "username": "@Dorima8_info",
    "content": "ガチャ 新作 に関する投稿",
    "url": "https://x.com/Dorima8_info/status/2045104960799719611",
    "postedAt": "2026-04-18T07:18:46.007493+00:00",
    "matchedKeyword": "ガチャ 新作"
  },
  {
    "id": "x_2045102375388725712",
    "platform": "X",
    "username": "@poprouss",
    "content": "ガチャ 新作 に関する投稿",
    "url": "https://x.com/poprouss/status/2045102375388725712",
    "postedAt": "2026-04-18T07:18:46.007493+00:00",
    "matchedKeyword": "ガチャ 新作"
  },
  {
    "id": "x_2045094940284485939",
    "platform": "X",
    "username": "@pairium_info",
    "content": "ガチャ 新作 に関する投稿",
    "url": "https://x.com/pairium_info/status/2045094940284485939",
    "postedAt": "2026-04-18T07:18:46.007493+00:00",
    "matchedKeyword": "ガチャ 新作"
  },
  {
    "id": "x_2045094938564800681",
    "platform": "X",
    "username": "@pairium_info",
    "content": "ガチャ 新作 に関する投稿",
    "url": "https://x.com/pairium_info/status/2045094938564800681",
    "postedAt": "2026-04-18T07:18:46.007493+00:00",
    "matchedKeyword": "ガチャ 新作"
  },
  {
    "id": "x_2045088461259153664",
    "platform": "X",
    "username": "@Misaki_IRIAM",
    "content": "ガチャ 新作 に関する投稿",
    "url": "https://x.com/Misaki_IRIAM/status/2045088461259153664",
    "postedAt": "2026-04-18T07:18:46.007493+00:00",
    "matchedKeyword": "ガチャ 新作"
  },
  {
    "id": "x_2045346582925828326",
    "platform": "X",
    "username": "@GBO_pombashi",
    "content": "ガシャポン 新商品 に関する投稿",
    "url": "https://x.com/GBO_pombashi/status/2045346582925828326",
    "postedAt": "2026-04-18T07:18:44.401206+00:00",
    "matchedKeyword": "ガシャポン 新商品"
  },
  {
    "id": "x_2045400999125553448",
    "platform": "X",
    "username": "@GBO_kurashiki",
    "content": "ガシャポン 新商品 に関する投稿",
    "url": "https://x.com/GBO_kurashiki/status/2045400999125553448",
    "postedAt": "2026-04-18T07:18:44.401206+00:00",
    "matchedKeyword": "ガシャポン 新商品"
  },
  {
    "id": "x_2045397934972580208",
    "platform": "X",
    "username": "@GBO_m_sakata",
    "content": "ガシャポン 新商品 に関する投稿",
    "url": "https://x.com/GBO_m_sakata/status/2045397934972580208",
    "postedAt": "2026-04-18T07:18:44.401206+00:00",
    "matchedKeyword": "ガシャポン 新商品"
  },
  {
    "id": "x_2045396676668797020",
    "platform": "X",
    "username": "@GBO_tkitara",
    "content": "ガシャポン 新商品 に関する投稿",
    "url": "https://x.com/GBO_tkitara/status/2045396676668797020",
    "postedAt": "2026-04-18T07:18:44.401206+00:00",
    "matchedKeyword": "ガシャポン 新商品"
  },
  {
    "id": "x_2045396169380229278",
    "platform": "X",
    "username": "@GBO_tkitara",
    "content": "ガシャポン 新商品 に関する投稿",
    "url": "https://x.com/GBO_tkitara/status/2045396169380229278",
    "postedAt": "2026-04-18T07:18:44.401206+00:00",
    "matchedKeyword": "ガシャポン 新商品"
  },
  {
    "id": "x_2045395446600987070",
    "platform": "X",
    "username": "@GBO_f_hgsn",
    "content": "ガシャポン 新商品 に関する投稿",
    "url": "https://x.com/GBO_f_hgsn/status/2045395446600987070",
    "postedAt": "2026-04-18T07:18:44.401206+00:00",
    "matchedKeyword": "ガシャポン 新商品"
  },
  {
    "id": "x_2045394182525915282",
    "platform": "X",
    "username": "@GBO_sasaoka",
    "content": "ガシャポン 新商品 に関する投稿",
    "url": "https://x.com/GBO_sasaoka/status/2045394182525915282",
    "postedAt": "2026-04-18T07:18:44.401206+00:00",
    "matchedKeyword": "ガシャポン 新商品"
  },
  {
    "id": "x_2045394044378071275",
    "platform": "X",
    "username": "@GBO_bt_kuroiso",
    "content": "ガシャポン 新商品 に関する投稿",
    "url": "https://x.com/GBO_bt_kuroiso/status/2045394044378071275",
    "postedAt": "2026-04-18T07:18:44.401206+00:00",
    "matchedKeyword": "ガシャポン 新商品"
  },
  {
    "id": "x_2045393841281499627",
    "platform": "X",
    "username": "@gasha_sapporofa",
    "content": "ガシャポン 新商品 に関する投稿",
    "url": "https://x.com/gasha_sapporofa/status/2045393841281499627",
    "postedAt": "2026-04-18T07:18:44.401206+00:00",
    "matchedKeyword": "ガシャポン 新商品"
  },
  {
    "id": "x_2045393492118270090",
    "platform": "X",
    "username": "@GBO_f_hgsn",
    "content": "ガシャポン 新商品 に関する投稿",
    "url": "https://x.com/GBO_f_hgsn/status/2045393492118270090",
    "postedAt": "2026-04-18T07:18:44.401206+00:00",
    "matchedKeyword": "ガシャポン 新商品"
  },
  {
    "id": "x_2045393294189019186",
    "platform": "X",
    "username": "@GBO_p_izumo",
    "content": "ガシャポン 新商品 に関する投稿",
    "url": "https://x.com/GBO_p_izumo/status/2045393294189019186",
    "postedAt": "2026-04-18T07:18:44.401206+00:00",
    "matchedKeyword": "ガシャポン 新商品"
  },
  {
    "id": "x_2045392716004212930",
    "platform": "X",
    "username": "@gasha_ikbkr",
    "content": "ガシャポン 新商品 に関する投稿",
    "url": "https://x.com/gasha_ikbkr/status/2045392716004212930",
    "postedAt": "2026-04-18T07:18:44.401206+00:00",
    "matchedKeyword": "ガシャポン 新商品"
  },
  {
    "id": "x_2045392494998044844",
    "platform": "X",
    "username": "@GBO_m_sanda",
    "content": "ガシャポン 新商品 に関する投稿",
    "url": "https://x.com/GBO_m_sanda/status/2045392494998044844",
    "postedAt": "2026-04-18T07:18:44.401206+00:00",
    "matchedKeyword": "ガシャポン 新商品"
  },
  {
    "id": "x_2045392057003569378",
    "platform": "X",
    "username": "@GBO_m_sanda",
    "content": "ガシャポン 新商品 に関する投稿",
    "url": "https://x.com/GBO_m_sanda/status/2045392057003569378",
    "postedAt": "2026-04-18T07:18:44.401206+00:00",
    "matchedKeyword": "ガシャポン 新商品"
  },
  {
    "id": "x_2045391920185413710",
    "platform": "X",
    "username": "@GBO_m_sanda",
    "content": "ガシャポン 新商品 に関する投稿",
    "url": "https://x.com/GBO_m_sanda/status/2045391920185413710",
    "postedAt": "2026-04-18T07:18:44.401206+00:00",
    "matchedKeyword": "ガシャポン 新商品"
  },
  {
    "id": "x_2045391625359413277",
    "platform": "X",
    "username": "@GBO_m_sanda",
    "content": "ガシャポン 新商品 に関する投稿",
    "url": "https://x.com/GBO_m_sanda/status/2045391625359413277",
    "postedAt": "2026-04-18T07:18:44.401206+00:00",
    "matchedKeyword": "ガシャポン 新商品"
  },
  {
    "id": "x_2045391439182561774",
    "platform": "X",
    "username": "@GBO_m_sanda",
    "content": "ガシャポン 新商品 に関する投稿",
    "url": "https://x.com/GBO_m_sanda/status/2045391439182561774",
    "postedAt": "2026-04-18T07:18:44.401206+00:00",
    "matchedKeyword": "ガシャポン 新商品"
  },
  {
    "id": "x_2045390670375027006",
    "platform": "X",
    "username": "@GBO_m_sanda",
    "content": "ガシャポン 新商品 に関する投稿",
    "url": "https://x.com/GBO_m_sanda/status/2045390670375027006",
    "postedAt": "2026-04-18T07:18:44.401206+00:00",
    "matchedKeyword": "ガシャポン 新商品"
  },
  {
    "id": "x_2045390484546454008",
    "platform": "X",
    "username": "@GBO_m_sanda",
    "content": "ガシャポン 新商品 に関する投稿",
    "url": "https://x.com/GBO_m_sanda/status/2045390484546454008",
    "postedAt": "2026-04-18T07:18:44.401206+00:00",
    "matchedKeyword": "ガシャポン 新商品"
  },
  {
    "id": "x_2045390243998978219",
    "platform": "X",
    "username": "@GBO_urasoe",
    "content": "ガシャポン 新商品 に関する投稿",
    "url": "https://x.com/GBO_urasoe/status/2045390243998978219",
    "postedAt": "2026-04-18T07:18:44.401206+00:00",
    "matchedKeyword": "ガシャポン 新商品"
  },
  {
    "id": "x_2045390153242591431",
    "platform": "X",
    "username": "@GBO_m_sanda",
    "content": "ガシャポン 新商品 に関する投稿",
    "url": "https://x.com/GBO_m_sanda/status/2045390153242591431",
    "postedAt": "2026-04-18T07:18:44.401206+00:00",
    "matchedKeyword": "ガシャポン 新商品"
  },
  {
    "id": "x_2045389929140904105",
    "platform": "X",
    "username": "@GBO_okuwa",
    "content": "ガシャポン 新商品 に関する投稿",
    "url": "https://x.com/GBO_okuwa/status/2045389929140904105",
    "postedAt": "2026-04-18T07:18:44.401206+00:00",
    "matchedKeyword": "ガシャポン 新商品"
  },
  {
    "id": "x_2045389922450989317",
    "platform": "X",
    "username": "@GBO_m_sanda",
    "content": "ガシャポン 新商品 に関する投稿",
    "url": "https://x.com/GBO_m_sanda/status/2045389922450989317",
    "postedAt": "2026-04-18T07:18:44.401206+00:00",
    "matchedKeyword": "ガシャポン 新商品"
  },
  {
    "id": "x_2045389528748441758",
    "platform": "X",
    "username": "@GBO_m_sanda",
    "content": "ガシャポン 新商品 に関する投稿",
    "url": "https://x.com/GBO_m_sanda/status/2045389528748441758",
    "postedAt": "2026-04-18T07:18:44.401206+00:00",
    "matchedKeyword": "ガシャポン 新商品"
  },
  {
    "id": "x_2045389345880965347",
    "platform": "X",
    "username": "@GBO_tkitara",
    "content": "ガシャポン 新商品 に関する投稿",
    "url": "https://x.com/GBO_tkitara/status/2045389345880965347",
    "postedAt": "2026-04-18T07:18:44.401206+00:00",
    "matchedKeyword": "ガシャポン 新商品"
  },
  {
    "id": "x_2045388960588001456",
    "platform": "X",
    "username": "@GBO_fukuyamaSA",
    "content": "ガシャポン 新商品 に関する投稿",
    "url": "https://x.com/GBO_fukuyamaSA/status/2045388960588001456",
    "postedAt": "2026-04-18T07:18:44.401206+00:00",
    "matchedKeyword": "ガシャポン 新商品"
  },
  {
    "id": "x_2045388922520531331",
    "platform": "X",
    "username": "@GBO_tkitara",
    "content": "ガシャポン 新商品 に関する投稿",
    "url": "https://x.com/GBO_tkitara/status/2045388922520531331",
    "postedAt": "2026-04-18T07:18:44.401206+00:00",
    "matchedKeyword": "ガシャポン 新商品"
  },
  {
    "id": "x_2045388691313680434",
    "platform": "X",
    "username": "@GBO_sasaoka",
    "content": "ガシャポン 新商品 に関する投稿",
    "url": "https://x.com/GBO_sasaoka/status/2045388691313680434",
    "postedAt": "2026-04-18T07:18:44.401206+00:00",
    "matchedKeyword": "ガシャポン 新商品"
  },
  {
    "id": "x_2045388559595733330",
    "platform": "X",
    "username": "@GBO_tkitara",
    "content": "ガシャポン 新商品 に関する投稿",
    "url": "https://x.com/GBO_tkitara/status/2045388559595733330",
    "postedAt": "2026-04-18T07:18:44.401206+00:00",
    "matchedKeyword": "ガシャポン 新商品"
  },
  {
    "id": "x_2045388503824093582",
    "platform": "X",
    "username": "@GBO_m_sanda",
    "content": "ガシャポン 新商品 に関する投稿",
    "url": "https://x.com/GBO_m_sanda/status/2045388503824093582",
    "postedAt": "2026-04-18T07:18:44.401206+00:00",
    "matchedKeyword": "ガシャポン 新商品"
  },
  {
    "id": "x_2045387495295332676",
    "platform": "X",
    "username": "@GBO_m_sanda",
    "content": "ガシャポン 新商品 に関する投稿",
    "url": "https://x.com/GBO_m_sanda/status/2045387495295332676",
    "postedAt": "2026-04-18T07:18:44.401206+00:00",
    "matchedKeyword": "ガシャポン 新商品"
  },
  {
    "id": "x_2045387316123017708",
    "platform": "X",
    "username": "@GBO_okuwa",
    "content": "ガシャポン 新商品 に関する投稿",
    "url": "https://x.com/GBO_okuwa/status/2045387316123017708",
    "postedAt": "2026-04-18T07:18:44.401206+00:00",
    "matchedKeyword": "ガシャポン 新商品"
  },
  {
    "id": "x_2045386028840808946",
    "platform": "X",
    "username": "@GBO_minamifur",
    "content": "ガシャポン 新商品 に関する投稿",
    "url": "https://x.com/GBO_minamifur/status/2045386028840808946",
    "postedAt": "2026-04-18T07:18:44.401206+00:00",
    "matchedKeyword": "ガシャポン 新商品"
  },
  {
    "id": "x_2045385324759781592",
    "platform": "X",
    "username": "@Cplakamiiso",
    "content": "ガシャポン 新商品 に関する投稿",
    "url": "https://x.com/Cplakamiiso/status/2045385324759781592",
    "postedAt": "2026-04-18T07:18:44.401206+00:00",
    "matchedKeyword": "ガシャポン 新商品"
  },
  {
    "id": "x_2045384176069976134",
    "platform": "X",
    "username": "@GBO_okuwa",
    "content": "ガシャポン 新商品 に関する投稿",
    "url": "https://x.com/GBO_okuwa/status/2045384176069976134",
    "postedAt": "2026-04-18T07:18:44.401206+00:00",
    "matchedKeyword": "ガシャポン 新商品"
  },
  {
    "id": "x_2045382615629508832",
    "platform": "X",
    "username": "@GBO_sasaoka",
    "content": "ガシャポン 新商品 に関する投稿",
    "url": "https://x.com/GBO_sasaoka/status/2045382615629508832",
    "postedAt": "2026-04-18T07:18:44.401206+00:00",
    "matchedKeyword": "ガシャポン 新商品"
  },
  {
    "id": "x_2045382143854211412",
    "platform": "X",
    "username": "@GBO_kofukugawa",
    "content": "ガシャポン 新商品 に関する投稿",
    "url": "https://x.com/GBO_kofukugawa/status/2045382143854211412",
    "postedAt": "2026-04-18T07:18:44.401206+00:00",
    "matchedKeyword": "ガシャポン 新商品"
  },
  {
    "id": "x_2045381550343434635",
    "platform": "X",
    "username": "@GBO_j_tkmt",
    "content": "ガシャポン 新商品 に関する投稿",
    "url": "https://x.com/GBO_j_tkmt/status/2045381550343434635",
    "postedAt": "2026-04-18T07:18:44.401206+00:00",
    "matchedKeyword": "ガシャポン 新商品"
  },
  {
    "id": "x_2045381200471359548",
    "platform": "X",
    "username": "@GBO_seya_m",
    "content": "ガシャポン 新商品 に関する投稿",
    "url": "https://x.com/GBO_seya_m/status/2045381200471359548",
    "postedAt": "2026-04-18T07:18:44.401206+00:00",
    "matchedKeyword": "ガシャポン 新商品"
  },
  {
    "id": "x_2045380806135435480",
    "platform": "X",
    "username": "@GBO_j_tkmt",
    "content": "ガシャポン 新商品 に関する投稿",
    "url": "https://x.com/GBO_j_tkmt/status/2045380806135435480",
    "postedAt": "2026-04-18T07:18:44.401206+00:00",
    "matchedKeyword": "ガシャポン 新商品"
  }
]