[
  {
    "id": "x_2061932837130178720",
    "platform": "X",
    "username": "@DailyPicks12065",
    "content": "PR サンリオ新作ガチャ情報🍬 つながるキャンディチャーム 9月発売予定だよ✨ クロミ、マイメロディ、ハローキティ好きは見逃せない可愛さ🥹💕 推し活にもぴったり！ リプ欄見てね❤️ #サンリオ #マイメロディ #ガチャガチャ — さくら | Daily Picks (@DailyPicks12065) June 2, 2026",
    "url": "https://x.com/DailyPicks12065/status/2061932837130178720",
    "postedAt": "2026-06-03T17:00:47.977578+00:00",
    "matchedKeyword": "サンリオ ガチャ 新作"
  },
  {
    "id": "x_2062034392697225483",
    "platform": "X",
    "username": "@mikan35350",
    "content": "[PR] サンリオキャラクターズ クリスタルめじるしアクセサリー 全5種 セット コンプリート 楽天市場で買えた💕 🔻GEEX COLLECTION https://t.co/eUxHmnwUsT ハローキティ、マイメロディ、クロミ、シナモロール、ポムポムプリンの全5種😍💖 ガチャガチャ ガチャ ガシャポン カプセルトイ 入荷 新作 — みみたぶ (@mikan35350) June 3, 2026",
    "url": "https://x.com/mikan35350/status/2062034392697225483",
    "postedAt": "2026-06-03T17:00:47.977578+00:00",
    "matchedKeyword": "サンリオ ガチャ 新作"
  },
  {
    "id": "x_2061973992819581084",
    "platform": "X",
    "username": "@mikan35350",
    "content": "[PR]【予約受付中】サンリオキャラクターズ クリスタルめじるしアクセサリー 全5種 ここで買えた💕 🔻SMLトレーディング 楽天市場店 https://t.co/RRbHHvs8nv キティちゃんにマイメロディ、クロミ、シナモロール、ポムポムプリン可愛い🥹✨ ガチャガチャ ガチャ ガシャポン カプセルトイ 入荷 新作 — みみたぶ (@mikan35350) June 3, 2026",
    "url": "https://x.com/mikan35350/status/2061973992819581084",
    "postedAt": "2026-06-03T17:00:47.977578+00:00",
    "matchedKeyword": "サンリオ ガチャ 新作"
  },
  {
    "id": "x_2061800211698364615",
    "platform": "X",
    "username": "@08Hisa22",
    "content": "\"争奪戦必至！新作カプセルトイ「サンリオキャラクターズ アロハスイングコレクション」\" - Gacha Paradise（ガチャパラ） #SmartNews https://t.co/0nGYIzXnfv — HiSA-now ☮️NO WAR🕊️ (@08Hisa22) June 2, 2026",
    "url": "https://x.com/08Hisa22/status/2061800211698364615",
    "postedAt": "2026-06-03T17:00:47.977578+00:00",
    "matchedKeyword": "サンリオ ガチャ 新作"
  },
  {
    "id": "x_2061779932515328189",
    "platform": "X",
    "username": "@trend_diar67661",
    "content": "PR 9月発売のサンリオ新作ガチャ🍬✨ サンリオキャラクターズ つながるキャンディチャーム これは可愛すぎて即チェック案件💕 マイメロディ、ポムポムプリン、ポチャッコ好きにも刺さるやつ🥹 リプ欄見てね❤️ #サンリオ #マイメロディ #ポムポムプリン — あやの | Trend Diary (@trend_diar67661) June 2, 2026",
    "url": "https://x.com/trend_diar67661/status/2061779932515328189",
    "postedAt": "2026-06-03T17:00:47.977578+00:00",
    "matchedKeyword": "サンリオ ガチャ 新作"
  },
  {
    "id": "x_2061748200105791805",
    "platform": "X",
    "username": "@otokusanevor",
    "content": "ガチャ行列に並ぶのやめた！新作を定価や安く予約ゲット✨🎀 トムとジェリー、トップハム・ハット卿、仕事猫、めじるし、ハムスター、ポムポムプリン、サンリオ、ペルソナ、ディズニー、たまごっち、リラックマなどなど ここに纏めました👇🏻 https://t.co/wMKE5otwE4 pic.twitter.com/DGOC05T81W — ガチャ予約さん🐱安く予約出来るサイトや流行りの情報やSALEなど✨️ (@otokusanevor) June 2, 2026",
    "url": "https://x.com/otokusanevor/status/2061748200105791805",
    "postedAt": "2026-06-03T17:00:47.977578+00:00",
    "matchedKeyword": "サンリオ ガチャ 新作"
  },
  {
    "id": "x_2061741820556832771",
    "platform": "X",
    "username": "@hDh4jXfZ4i8189",
    "content": "🎉6月発売予定の新作ガチャまとめ！ 🟦はしもとみおのウルトラ怪獣彫ってみた。0３ 🟥シマエナガ雑貨 ぴよ手帖 ふわもこポーチコレクション（再販） 🟨なめこ栽培キット めじるしアクセサリー2（再販） 🟩サンリオキャラクターズ～なりきりメンダコ～ めじるしアクセサリー #ガチャガチャ … pic.twitter.com/pmMQLk58zT — ガチャ速🚨最新カプセルトイ・ガシャポン情報 (@hDh4jXfZ4i8189) June 2, 2026",
    "url": "https://x.com/hDh4jXfZ4i8189/status/2061741820556832771",
    "postedAt": "2026-06-03T17:00:47.977578+00:00",
    "matchedKeyword": "サンリオ ガチャ 新作"
  },
  {
    "id": "x_2061737566731436373",
    "platform": "X",
    "username": "@B1P9xWik48Ese6O",
    "content": "PR 【ガチャガチャ新作】 発売日: 2026年6月第4週 サンリオキャラクターズ キーリングハンガー 楽天で探す🔎 ▶︎ https://t.co/HtYjXUNqhv キーリングにガチャでGETしたマスコット付けられるのアツすぎ🔥🔥 #ガチャガチャ #サンリオ pic.twitter.com/GRq3KICauE — ポチるん@お得情報 (@B1P9xWik48Ese6O) June 2, 2026",
    "url": "https://x.com/B1P9xWik48Ese6O/status/2061737566731436373",
    "postedAt": "2026-06-03T17:00:47.977578+00:00",
    "matchedKeyword": "サンリオ ガチャ 新作"
  },
  {
    "id": "x_2061730793257636153",
    "platform": "X",
    "username": "@sumire5151",
    "content": "【9月予約】サンリオ新作ガチャが激かわ🥹 サンリオキャラクターズ つながるキャンディチャーム 👈コンプリートセットで確実に揃う！ 👉 https://t.co/Fn8kKsURRx キャンディみたいな透け感たまらん🍬 マイメロ、ポチャッコ、プリン推しは絶対チェックして！ ハローキティ クロミ シナモロール #PR — かおり＠フォロバ100 (@sumire5151) June 2, 2026",
    "url": "https://x.com/sumire5151/status/2061730793257636153",
    "postedAt": "2026-06-03T17:00:47.977578+00:00",
    "matchedKeyword": "サンリオ ガチャ 新作"
  },
  {
    "id": "x_2061713389446176974",
    "platform": "X",
    "username": "@momooshi33",
    "content": "待って、ポムポムプリンがヒーローとか全人類癒やされるでしょ…😭💛 サンリオ新作ガチャの「ポムポムヒーロー」が天才すぎる。 マント羽織って「ぷ」って書いてあるの愛おしすぎない？ビームやびゅーんのポーズ全部集めたいレベル。 ​みんなはどのポーズのプリンが好き？ 📌予約情報はリプへ pic.twitter.com/OecxX7JJ3n — たま｜女性向けグッズ・たまごっち速報 (@momooshi33) June 2, 2026",
    "url": "https://x.com/momooshi33/status/2061713389446176974",
    "postedAt": "2026-06-03T17:00:47.977578+00:00",
    "matchedKeyword": "サンリオ ガチャ 新作"
  },
  {
    "id": "x_2061681458058805496",
    "platform": "X",
    "username": "@DailyPicks12065",
    "content": "PR サンリオ新作ガチャきた🍬✨ サンリオキャラクターズ つながるキャンディチャーム 9月発売のガチャガチャだよ💕 ハローキティ、マイメロディ、クロミ系集めてる人は売り切れ前にチェック🥹 リプ欄見てね❤️ #サンリオ #ガチャ #マイメロディ — さくら | Daily Picks (@DailyPicks12065) June 2, 2026",
    "url": "https://x.com/DailyPicks12065/status/2061681458058805496",
    "postedAt": "2026-06-03T17:00:47.977578+00:00",
    "matchedKeyword": "サンリオ ガチャ 新作"
  },
  {
    "id": "x_2061677769885667600",
    "platform": "X",
    "username": "@ofuro_oshigoto",
    "content": "うーん、あした台風だし夜勤だけどサンリオは新作発売日だしガチャはなんかしら入荷しそうな雰囲気あるし困ったなぁ — 🛁おふろばのまほうつかい👼🧙 (@ofuro_oshigoto) June 2, 2026",
    "url": "https://x.com/ofuro_oshigoto/status/2061677769885667600",
    "postedAt": "2026-06-03T17:00:47.977578+00:00",
    "matchedKeyword": "サンリオ ガチャ 新作"
  },
  {
    "id": "x_2061566884852720051",
    "platform": "X",
    "username": "@pomupomup_fan",
    "content": "サンリオ新作ガチャ 送料無料 販売価格 定価品再入荷 ⤵⤵ https://t.co/o1H8LvZLnA ［PR］ サンリオキャラクターズ つながるキャンディチャーム 全5種フルコンプセット ポムポムプリン ヨッシーめじるしアクセサリー も今日こそ！フェイラー ファミリア コラボ 再販 シナモロール × スタバ もほしい pic.twitter.com/vaTdL8naTS — ぷりん (@pomupomup_fan) June 1, 2026",
    "url": "https://x.com/pomupomup_fan/status/2061566884852720051",
    "postedAt": "2026-06-03T17:00:47.977578+00:00",
    "matchedKeyword": "サンリオ ガチャ 新作"
  },
  {
    "id": "x_2061561307535700382",
    "platform": "X",
    "username": "@xV6dOf8qSQ4099",
    "content": "サンリオ新作ガチャ！ 送料無料 販売価格 定価在庫再入荷 ⤵⤵ https://t.co/BiBkr2LzTT ［PR］ サンリオキャラクターズ つながるキャンディチャーム 全5種 サンリオクリスタル あしながキティ― ヨッシーめじるしアクセサリー も今日こそ！フェイラー FEILER ファミリア コラボ再販もそろそろ？！ pic.twitter.com/S1VaFG1YVC — まどれーぬ｜ガチャガチャ情報局 (@xV6dOf8qSQ4099) June 1, 2026",
    "url": "https://x.com/xV6dOf8qSQ4099/status/2061561307535700382",
    "postedAt": "2026-06-03T17:00:47.977578+00:00",
    "matchedKeyword": "サンリオ ガチャ 新作"
  },
  {
    "id": "x_2061295383486353462",
    "platform": "X",
    "username": "@Trang13404",
    "content": "6月の新作、ラインナップが神すぎて財布の紐がゆるゆるになりますよね…🤦🏻🍀 カービィのドット絵とか、サンリオの新作とか、可愛さの暴力がすごい。 「見るだけ」と思ってガチャコーナーに行っても、気付いたら両手にカプセル持ってる未来しか見えないですw — Trang Florence 🥰 (@Trang13404) June 1, 2026",
    "url": "https://x.com/Trang13404/status/2061295383486353462",
    "postedAt": "2026-06-03T17:00:47.977578+00:00",
    "matchedKeyword": "サンリオ ガチャ 新作"
  },
  {
    "id": "x_2061288561941582003",
    "platform": "X",
    "username": "@TiCK_TACK_world",
    "content": "【ガチャ新作入荷のお知らせ】 🤍サンリオ マイメロディ・クロミ バッグ風ポーチ 🤍Betty Boopフラットコインチャーム 入荷しました✨ その他多数展開中❤️‍🔥 #推し活 pic.twitter.com/BRMy43p4Gb — ティックタックワールド (TiCK TACK ワールド鴨川店) (@TiCK_TACK_world) June 1, 2026",
    "url": "https://x.com/TiCK_TACK_world/status/2061288561941582003",
    "postedAt": "2026-06-03T17:00:47.977578+00:00",
    "matchedKeyword": "サンリオ ガチャ 新作"
  },
  {
    "id": "x_2061283563820245171",
    "platform": "X",
    "username": "@hDh4jXfZ4i8189",
    "content": "🎉6月発売予定の新作ガチャまとめ！ 🟦サンリオキャラクターズ かおりつきマスコットぬいぐるみ ホイップクリームデザイン vol.2 🟥シナモロール ふわふわ巾着 🟨サンリオキャラクターズ カタカタお知らせルームプレート風チャーム 🟩サンリオキャラクターズ おこさまパズル風チャーム… pic.twitter.com/cYJwWKwlyX — ガチャ速🚨最新カプセルトイ・ガシャポン情報 (@hDh4jXfZ4i8189) June 1, 2026",
    "url": "https://x.com/hDh4jXfZ4i8189/status/2061283563820245171",
    "postedAt": "2026-06-03T17:00:47.977578+00:00",
    "matchedKeyword": "サンリオ ガチャ 新作"
  },
  {
    "id": "x_2061278976484741311",
    "platform": "X",
    "username": "@peach_freelife_",
    "content": "6月のサンリオ新作ガチャも可愛すぎる🥹 コンプリートさせたい🤍 pic.twitter.com/Z2MTNArA0X — 𝒎 🍑🧸 (@peach_freelife_) June 1, 2026",
    "url": "https://x.com/peach_freelife_/status/2061278976484741311",
    "postedAt": "2026-06-03T17:00:47.977578+00:00",
    "matchedKeyword": "サンリオ ガチャ 新作"
  },
  {
    "id": "x_2061268783013278087",
    "platform": "X",
    "username": "@5_sugar_5",
    "content": "サンリオ ガチャ 新作 に関する投稿",
    "url": "https://x.com/5_sugar_5/status/2061268783013278087",
    "postedAt": "2026-06-03T17:00:47.977578+00:00",
    "matchedKeyword": "サンリオ ガチャ 新作"
  },
  {
    "id": "x_2061253445374669049",
    "platform": "X",
    "username": "@panko66666",
    "content": "[PR] 【全5種コンプリートセット】サンリオキャラクターズ クリスタルめじるしアクセサリー 楽天で買えるよ✨ 🔻 JUGEM 楽天市場店 https://t.co/vCNK1XcfaQ ハローキティ、マイメロディ、クロミ、シナモロール、ポムポムプリン可愛い🥹✨ ガチャ ガチャガチャ カプセルトイ ガシャポン 入荷 新作 — ぱにーに🥖 (@panko66666) June 1, 2026",
    "url": "https://x.com/panko66666/status/2061253445374669049",
    "postedAt": "2026-06-03T17:00:47.977578+00:00",
    "matchedKeyword": "サンリオ ガチャ 新作"
  },
  {
    "id": "x_2061089538970403304",
    "platform": "X",
    "username": "@BTsHHDEhLj36007",
    "content": "ガチャ活勢のみなさん朗報です サンリオ新作『クリスタルめじるしアクセサリー』争奪戦＆沼から大人の力で脱出する方法あります👇 🛒 https://t.co/7aLx82g3d2 何店舗もハシゴして「お目当てが出ない…」って泣くくらいなら、ここで確実に全種コンプが大正解 シナモロール ポムポムプリン #PR 23:16 — あおに (@BTsHHDEhLj36007) May 31, 2026",
    "url": "https://x.com/BTsHHDEhLj36007/status/2061089538970403304",
    "postedAt": "2026-06-03T17:00:47.977578+00:00",
    "matchedKeyword": "サンリオ ガチャ 新作"
  },
  {
    "id": "x_2061036701620007090",
    "platform": "X",
    "username": "@hDh4jXfZ4i8189",
    "content": "🎉5月発売予定の新作ガチャまとめ！ 🟦おぱんちゅうさぎ ダイカットステッカーセット 🟥おジャ魔女どれみ ダイキャストチャーム＆パッケージ 🟨サンリオキャラクターズ よつばのクローバーマスコット 🟩とっとこハム太郎 まちぼうけ（再販） #ガチャガチャ #カプセルトイ #新商品 #5月発売 … pic.twitter.com/d8TXGbRNzn — ガチャ速🚨最新カプセルトイ・ガシャポン情報 (@hDh4jXfZ4i8189) May 31, 2026",
    "url": "https://x.com/hDh4jXfZ4i8189/status/2061036701620007090",
    "postedAt": "2026-06-03T17:00:47.977578+00:00",
    "matchedKeyword": "サンリオ ガチャ 新作"
  },
  {
    "id": "x_2060687644116570495",
    "platform": "X",
    "username": "@huuu416",
    "content": "ポケモン30周年！新作ガチャ メタルチャームマスコット設置場所まとめ ⤵ https://t.co/TUZD3I5iwV ＼13店舗／ で第1弾・第2弾 両方ゲットチャンス◎ ポケピース サンリオクリスタル あしながキティ― 夏目友人帳 ちいかわめじるしアクセサリー3 も ポケカ ポケモンカード は イオン セブンイレブン？ — ふ～ (@huuu416) May 30, 2026",
    "url": "https://x.com/huuu416/status/2060687644116570495",
    "postedAt": "2026-06-03T17:00:47.977578+00:00",
    "matchedKeyword": "サンリオ ガチャ 新作"
  },
  {
    "id": "x_2060655649693069489",
    "platform": "X",
    "username": "@mikan35350",
    "content": "[PR] 【全5種コンプリートセット】サンリオキャラクターズ ボンボンドロップミニチュアチャーム 楽天で買えた💕 🔻 JUGEM 楽天市場店 https://t.co/R0uKFAGkLH キティちゃん、ポムポムプリン、はぴだんぶい大好き😘 ボンボンドロップシール ボンドロ ガチャガチャ ガチャ ガシャポン 入荷 新作 — みみたぶ (@mikan35350) May 30, 2026",
    "url": "https://x.com/mikan35350/status/2060655649693069489",
    "postedAt": "2026-06-03T17:00:47.977578+00:00",
    "matchedKeyword": "サンリオ ガチャ 新作"
  },
  {
    "id": "x_2060642575607107714",
    "platform": "X",
    "username": "@golden_lip",
    "content": "サンリオのご当地ピンズ、今年中にあと1つや2つ新作が出ると予想しているけど、サクッとガチャを回せる地域であってくれ！！！ — 愛武士 (@golden_lip) May 30, 2026",
    "url": "https://x.com/golden_lip/status/2060642575607107714",
    "postedAt": "2026-06-03T17:00:47.977578+00:00",
    "matchedKeyword": "サンリオ ガチャ 新作"
  },
  {
    "id": "x_2060640016083431765",
    "platform": "X",
    "username": "@TiCK_TACK_world",
    "content": "サンリオ ガチャ 新作 に関する投稿",
    "url": "https://x.com/TiCK_TACK_world/status/2060640016083431765",
    "postedAt": "2026-06-03T17:00:47.977578+00:00",
    "matchedKeyword": "サンリオ ガチャ 新作"
  },
  {
    "id": "x_2060612363553054828",
    "platform": "X",
    "username": "@xV6dOf8qSQ4099",
    "content": "サンリオ ガチャ 新作 に関する投稿",
    "url": "https://x.com/xV6dOf8qSQ4099/status/2060612363553054828",
    "postedAt": "2026-06-03T17:00:47.977578+00:00",
    "matchedKeyword": "サンリオ ガチャ 新作"
  },
  {
    "id": "x_2060567151426351368",
    "platform": "X",
    "username": "@hDh4jXfZ4i8189",
    "content": "サンリオ ガチャ 新作 に関する投稿",
    "url": "https://x.com/hDh4jXfZ4i8189/status/2060567151426351368",
    "postedAt": "2026-06-03T17:00:47.977578+00:00",
    "matchedKeyword": "サンリオ ガチャ 新作"
  },
  {
    "id": "x_2060567117280522679",
    "platform": "X",
    "username": "@hDh4jXfZ4i8189",
    "content": "サンリオ ガチャ 新作 に関する投稿",
    "url": "https://x.com/hDh4jXfZ4i8189/status/2060567117280522679",
    "postedAt": "2026-06-03T17:00:47.977578+00:00",
    "matchedKeyword": "サンリオ ガチャ 新作"
  },
  {
    "id": "x_2060354489086042361",
    "platform": "X",
    "username": "@Monchhichi_rk",
    "content": "サンリオ ガチャ 新作 に関する投稿",
    "url": "https://x.com/Monchhichi_rk/status/2060354489086042361",
    "postedAt": "2026-06-03T17:00:47.977578+00:00",
    "matchedKeyword": "サンリオ ガチャ 新作"
  },
  {
    "id": "x_2060334846204100679",
    "platform": "X",
    "username": "@hDh4jXfZ4i8189",
    "content": "サンリオ ガチャ 新作 に関する投稿",
    "url": "https://x.com/hDh4jXfZ4i8189/status/2060334846204100679",
    "postedAt": "2026-06-03T17:00:47.977578+00:00",
    "matchedKeyword": "サンリオ ガチャ 新作"
  },
  {
    "id": "x_2060327219361468425",
    "platform": "X",
    "username": "@xV6dOf8qSQ4099",
    "content": "サンリオ ガチャ 新作 に関する投稿",
    "url": "https://x.com/xV6dOf8qSQ4099/status/2060327219361468425",
    "postedAt": "2026-06-03T17:00:47.977578+00:00",
    "matchedKeyword": "サンリオ ガチャ 新作"
  },
  {
    "id": "x_2060321743143842130",
    "platform": "X",
    "username": "@mis_ym",
    "content": "サンリオ ガチャ 新作 に関する投稿",
    "url": "https://x.com/mis_ym/status/2060321743143842130",
    "postedAt": "2026-06-03T17:00:47.977578+00:00",
    "matchedKeyword": "サンリオ ガチャ 新作"
  },
  {
    "id": "x_2060294273581597103",
    "platform": "X",
    "username": "@otokusanevor",
    "content": "サンリオ ガチャ 新作 に関する投稿",
    "url": "https://x.com/otokusanevor/status/2060294273581597103",
    "postedAt": "2026-06-03T17:00:47.977578+00:00",
    "matchedKeyword": "サンリオ ガチャ 新作"
  },
  {
    "id": "x_2060220952328515863",
    "platform": "X",
    "username": "@shinku_seal",
    "content": "サンリオ ガチャ 新作 に関する投稿",
    "url": "https://x.com/shinku_seal/status/2060220952328515863",
    "postedAt": "2026-06-03T17:00:47.977578+00:00",
    "matchedKeyword": "サンリオ ガチャ 新作"
  },
  {
    "id": "x_2060176381422776802",
    "platform": "X",
    "username": "@xV6dOf8qSQ4099",
    "content": "サンリオ ガチャ 新作 に関する投稿",
    "url": "https://x.com/xV6dOf8qSQ4099/status/2060176381422776802",
    "postedAt": "2026-06-03T17:00:47.977578+00:00",
    "matchedKeyword": "サンリオ ガチャ 新作"
  },
  {
    "id": "x_2060121265202143268",
    "platform": "X",
    "username": "@xV6dOf8qSQ4099",
    "content": "サンリオ ガチャ 新作 に関する投稿",
    "url": "https://x.com/xV6dOf8qSQ4099/status/2060121265202143268",
    "postedAt": "2026-06-03T17:00:47.977578+00:00",
    "matchedKeyword": "サンリオ ガチャ 新作"
  },
  {
    "id": "x_2062142837861581225",
    "platform": "X",
    "username": "@lweuyMow2rUBnrl",
    "content": "たまごっち ガチャ に関する投稿",
    "url": "https://x.com/lweuyMow2rUBnrl/status/2062142837861581225",
    "postedAt": "2026-06-03T17:00:46.534105+00:00",
    "matchedKeyword": "たまごっち ガチャ"
  },
  {
    "id": "x_2062209661416431760",
    "platform": "X",
    "username": "@HaNa_324_17",
    "content": "たまごっち ガチャ に関する投稿",
    "url": "https://x.com/HaNa_324_17/status/2062209661416431760",
    "postedAt": "2026-06-03T17:00:46.534105+00:00",
    "matchedKeyword": "たまごっち ガチャ"
  },
  {
    "id": "x_2062209109550858383",
    "platform": "X",
    "username": "@skznotorihiki",
    "content": "たまごっち ガチャ に関する投稿",
    "url": "https://x.com/skznotorihiki/status/2062209109550858383",
    "postedAt": "2026-06-03T17:00:46.534105+00:00",
    "matchedKeyword": "たまごっち ガチャ"
  },
  {
    "id": "x_2062207942657781806",
    "platform": "X",
    "username": "@mugi__0312",
    "content": "たまごっち ガチャ に関する投稿",
    "url": "https://x.com/mugi__0312/status/2062207942657781806",
    "postedAt": "2026-06-03T17:00:46.534105+00:00",
    "matchedKeyword": "たまごっち ガチャ"
  },
  {
    "id": "x_2062206771100631537",
    "platform": "X",
    "username": "@__mashiro_oO",
    "content": "たまごっち ガチャ に関する投稿",
    "url": "https://x.com/__mashiro_oO/status/2062206771100631537",
    "postedAt": "2026-06-03T17:00:46.534105+00:00",
    "matchedKeyword": "たまごっち ガチャ"
  },
  {
    "id": "x_2062206300973564167",
    "platform": "X",
    "username": "@mmpq44",
    "content": "たまごっち ガチャ に関する投稿",
    "url": "https://x.com/mmpq44/status/2062206300973564167",
    "postedAt": "2026-06-03T17:00:46.534105+00:00",
    "matchedKeyword": "たまごっち ガチャ"
  },
  {
    "id": "x_2062205430143815850",
    "platform": "X",
    "username": "@4ha111",
    "content": "たまごっち ガチャ に関する投稿",
    "url": "https://x.com/4ha111/status/2062205430143815850",
    "postedAt": "2026-06-03T17:00:46.534105+00:00",
    "matchedKeyword": "たまごっち ガチャ"
  },
  {
    "id": "x_2062204338035101761",
    "platform": "X",
    "username": "@w001ff",
    "content": "たまごっち ガチャ に関する投稿",
    "url": "https://x.com/w001ff/status/2062204338035101761",
    "postedAt": "2026-06-03T17:00:46.534105+00:00",
    "matchedKeyword": "たまごっち ガチャ"
  },
  {
    "id": "x_2062204003338051985",
    "platform": "X",
    "username": "@4ha111",
    "content": "たまごっち ガチャ に関する投稿",
    "url": "https://x.com/4ha111/status/2062204003338051985",
    "postedAt": "2026-06-03T17:00:46.534105+00:00",
    "matchedKeyword": "たまごっち ガチャ"
  },
  {
    "id": "x_2062202969182064898",
    "platform": "X",
    "username": "@vsSeI00MY6i9o7C",
    "content": "たまごっち ガチャ に関する投稿",
    "url": "https://x.com/vsSeI00MY6i9o7C/status/2062202969182064898",
    "postedAt": "2026-06-03T17:00:46.534105+00:00",
    "matchedKeyword": "たまごっち ガチャ"
  },
  {
    "id": "x_2062201599615992204",
    "platform": "X",
    "username": "@pecotan_u",
    "content": "たまごっち ガチャ に関する投稿",
    "url": "https://x.com/pecotan_u/status/2062201599615992204",
    "postedAt": "2026-06-03T17:00:46.534105+00:00",
    "matchedKeyword": "たまごっち ガチャ"
  },
  {
    "id": "x_2062201203292086639",
    "platform": "X",
    "username": "@sgsi_002",
    "content": "たまごっち ガチャ に関する投稿",
    "url": "https://x.com/sgsi_002/status/2062201203292086639",
    "postedAt": "2026-06-03T17:00:46.534105+00:00",
    "matchedKeyword": "たまごっち ガチャ"
  },
  {
    "id": "x_2062200849057955973",
    "platform": "X",
    "username": "@mn_k285",
    "content": "たまごっち ガチャ に関する投稿",
    "url": "https://x.com/mn_k285/status/2062200849057955973",
    "postedAt": "2026-06-03T17:00:46.534105+00:00",
    "matchedKeyword": "たまごっち ガチャ"
  },
  {
    "id": "x_2062200726189978014",
    "platform": "X",
    "username": "@s_hixcha",
    "content": "たまごっち ガチャ に関する投稿",
    "url": "https://x.com/s_hixcha/status/2062200726189978014",
    "postedAt": "2026-06-03T17:00:46.534105+00:00",
    "matchedKeyword": "たまごっち ガチャ"
  },
  {
    "id": "x_2062198448267657592",
    "platform": "X",
    "username": "@pineappl33_",
    "content": "たまごっち ガチャ に関する投稿",
    "url": "https://x.com/pineappl33_/status/2062198448267657592",
    "postedAt": "2026-06-03T17:00:46.534105+00:00",
    "matchedKeyword": "たまごっち ガチャ"
  },
  {
    "id": "x_2062197595309814014",
    "platform": "X",
    "username": "@aiueooooooooc",
    "content": "たまごっち ガチャ に関する投稿",
    "url": "https://x.com/aiueooooooooc/status/2062197595309814014",
    "postedAt": "2026-06-03T17:00:46.534105+00:00",
    "matchedKeyword": "たまごっち ガチャ"
  },
  {
    "id": "x_2062196373651669081",
    "platform": "X",
    "username": "@QYpko4f82F4457",
    "content": "たまごっち ガチャ に関する投稿",
    "url": "https://x.com/QYpko4f82F4457/status/2062196373651669081",
    "postedAt": "2026-06-03T17:00:46.534105+00:00",
    "matchedKeyword": "たまごっち ガチャ"
  },
  {
    "id": "x_2062195263989829641",
    "platform": "X",
    "username": "@maririn1111111",
    "content": "たまごっち ガチャ に関する投稿",
    "url": "https://x.com/maririn1111111/status/2062195263989829641",
    "postedAt": "2026-06-03T17:00:46.534105+00:00",
    "matchedKeyword": "たまごっち ガチャ"
  },
  {
    "id": "x_2062195234000531766",
    "platform": "X",
    "username": "@22kittyz",
    "content": "たまごっち ガチャ に関する投稿",
    "url": "https://x.com/22kittyz/status/2062195234000531766",
    "postedAt": "2026-06-03T17:00:46.534105+00:00",
    "matchedKeyword": "たまごっち ガチャ"
  },
  {
    "id": "x_2062193871812194501",
    "platform": "X",
    "username": "@_dsy19",
    "content": "たまごっち ガチャ に関する投稿",
    "url": "https://x.com/_dsy19/status/2062193871812194501",
    "postedAt": "2026-06-03T17:00:46.534105+00:00",
    "matchedKeyword": "たまごっち ガチャ"
  },
  {
    "id": "x_2062193589929783374",
    "platform": "X",
    "username": "@8zx_q2",
    "content": "たまごっち ガチャ に関する投稿",
    "url": "https://x.com/8zx_q2/status/2062193589929783374",
    "postedAt": "2026-06-03T17:00:46.534105+00:00",
    "matchedKeyword": "たまごっち ガチャ"
  },
  {
    "id": "x_2062193126564041031",
    "platform": "X",
    "username": "@Cinderella__c",
    "content": "たまごっち ガチャ に関する投稿",
    "url": "https://x.com/Cinderella__c/status/2062193126564041031",
    "postedAt": "2026-06-03T17:00:46.534105+00:00",
    "matchedKeyword": "たまごっち ガチャ"
  },
  {
    "id": "x_2062193096331592012",
    "platform": "X",
    "username": "@rito074",
    "content": "たまごっち ガチャ に関する投稿",
    "url": "https://x.com/rito074/status/2062193096331592012",
    "postedAt": "2026-06-03T17:00:46.534105+00:00",
    "matchedKeyword": "たまごっち ガチャ"
  },
  {
    "id": "x_2062192831012438170",
    "platform": "X",
    "username": "@ioio_0119",
    "content": "たまごっち ガチャ に関する投稿",
    "url": "https://x.com/ioio_0119/status/2062192831012438170",
    "postedAt": "2026-06-03T17:00:46.534105+00:00",
    "matchedKeyword": "たまごっち ガチャ"
  },
  {
    "id": "x_2062192272876454154",
    "platform": "X",
    "username": "@RFJ__727_",
    "content": "たまごっち ガチャ に関する投稿",
    "url": "https://x.com/RFJ__727_/status/2062192272876454154",
    "postedAt": "2026-06-03T17:00:46.534105+00:00",
    "matchedKeyword": "たまごっち ガチャ"
  },
  {
    "id": "x_2062192126885298508",
    "platform": "X",
    "username": "@uC2Vg8zQot62rx5",
    "content": "たまごっち ガチャ に関する投稿",
    "url": "https://x.com/uC2Vg8zQot62rx5/status/2062192126885298508",
    "postedAt": "2026-06-03T17:00:46.534105+00:00",
    "matchedKeyword": "たまごっち ガチャ"
  },
  {
    "id": "x_2062191770461769849",
    "platform": "X",
    "username": "@amm96781023",
    "content": "たまごっち ガチャ に関する投稿",
    "url": "https://x.com/amm96781023/status/2062191770461769849",
    "postedAt": "2026-06-03T17:00:46.534105+00:00",
    "matchedKeyword": "たまごっち ガチャ"
  },
  {
    "id": "x_2062190811924893779",
    "platform": "X",
    "username": "@77_riin",
    "content": "たまごっち ガチャ に関する投稿",
    "url": "https://x.com/77_riin/status/2062190811924893779",
    "postedAt": "2026-06-03T17:00:46.534105+00:00",
    "matchedKeyword": "たまごっち ガチャ"
  },
  {
    "id": "x_2062190739866714413",
    "platform": "X",
    "username": "@chisamaruu",
    "content": "たまごっち ガチャ に関する投稿",
    "url": "https://x.com/chisamaruu/status/2062190739866714413",
    "postedAt": "2026-06-03T17:00:46.534105+00:00",
    "matchedKeyword": "たまごっち ガチャ"
  },
  {
    "id": "x_2062190538372329609",
    "platform": "X",
    "username": "@miy_torihiki7",
    "content": "たまごっち ガチャ に関する投稿",
    "url": "https://x.com/miy_torihiki7/status/2062190538372329609",
    "postedAt": "2026-06-03T17:00:46.534105+00:00",
    "matchedKeyword": "たまごっち ガチャ"
  },
  {
    "id": "x_2062189220203209194",
    "platform": "X",
    "username": "@ohana_5oj",
    "content": "たまごっち ガチャ に関する投稿",
    "url": "https://x.com/ohana_5oj/status/2062189220203209194",
    "postedAt": "2026-06-03T17:00:46.534105+00:00",
    "matchedKeyword": "たまごっち ガチャ"
  },
  {
    "id": "x_2062188802744242643",
    "platform": "X",
    "username": "@a_kitty08",
    "content": "たまごっち ガチャ に関する投稿",
    "url": "https://x.com/a_kitty08/status/2062188802744242643",
    "postedAt": "2026-06-03T17:00:46.534105+00:00",
    "matchedKeyword": "たまごっち ガチャ"
  },
  {
    "id": "x_2062188765217771905",
    "platform": "X",
    "username": "@TxX1m",
    "content": "たまごっち ガチャ に関する投稿",
    "url": "https://x.com/TxX1m/status/2062188765217771905",
    "postedAt": "2026-06-03T17:00:46.534105+00:00",
    "matchedKeyword": "たまごっち ガチャ"
  },
  {
    "id": "x_2062188632052826586",
    "platform": "X",
    "username": "@Nyaros_05",
    "content": "たまごっち ガチャ に関する投稿",
    "url": "https://x.com/Nyaros_05/status/2062188632052826586",
    "postedAt": "2026-06-03T17:00:46.534105+00:00",
    "matchedKeyword": "たまごっち ガチャ"
  },
  {
    "id": "x_2062188488917983651",
    "platform": "X",
    "username": "@hanappiru",
    "content": "たまごっち ガチャ に関する投稿",
    "url": "https://x.com/hanappiru/status/2062188488917983651",
    "postedAt": "2026-06-03T17:00:46.534105+00:00",
    "matchedKeyword": "たまごっち ガチャ"
  },
  {
    "id": "x_2062188383380930693",
    "platform": "X",
    "username": "@tmgc_mm",
    "content": "たまごっち ガチャ に関する投稿",
    "url": "https://x.com/tmgc_mm/status/2062188383380930693",
    "postedAt": "2026-06-03T17:00:46.534105+00:00",
    "matchedKeyword": "たまごっち ガチャ"
  },
  {
    "id": "x_2062188068908703787",
    "platform": "X",
    "username": "@trhk0711_",
    "content": "たまごっち ガチャ に関する投稿",
    "url": "https://x.com/trhk0711_/status/2062188068908703787",
    "postedAt": "2026-06-03T17:00:46.534105+00:00",
    "matchedKeyword": "たまごっち ガチャ"
  },
  {
    "id": "x_2062188005914517604",
    "platform": "X",
    "username": "@QYpko4f82F4457",
    "content": "たまごっち ガチャ に関する投稿",
    "url": "https://x.com/QYpko4f82F4457/status/2062188005914517604",
    "postedAt": "2026-06-03T17:00:46.534105+00:00",
    "matchedKeyword": "たまごっち ガチャ"
  },
  {
    "id": "x_2062187988940202393",
    "platform": "X",
    "username": "@meme_pi4",
    "content": "たまごっち ガチャ に関する投稿",
    "url": "https://x.com/meme_pi4/status/2062187988940202393",
    "postedAt": "2026-06-03T17:00:46.534105+00:00",
    "matchedKeyword": "たまごっち ガチャ"
  },
  {
    "id": "x_2062187558923346107",
    "platform": "X",
    "username": "@_TOFU0528",
    "content": "たまごっち ガチャ に関する投稿",
    "url": "https://x.com/_TOFU0528/status/2062187558923346107",
    "postedAt": "2026-06-03T17:00:46.534105+00:00",
    "matchedKeyword": "たまごっち ガチャ"
  },
  {
    "id": "x_2061281586255966689",
    "platform": "X",
    "username": "@MOCHINYAMI",
    "content": "カプセルトイ 新商品 に関する投稿",
    "url": "https://x.com/MOCHINYAMI/status/2061281586255966689",
    "postedAt": "2026-06-03T17:00:45.101845+00:00",
    "matchedKeyword": "カプセルトイ 新商品"
  },
  {
    "id": "x_2062132081489305878",
    "platform": "X",
    "username": "@Cplamikage",
    "content": "カプセルトイ 新商品 に関する投稿",
    "url": "https://x.com/Cplamikage/status/2062132081489305878",
    "postedAt": "2026-06-03T17:00:45.101845+00:00",
    "matchedKeyword": "カプセルトイ 新商品"
  },
  {
    "id": "x_2062118305071260138",
    "platform": "X",
    "username": "@drecap_MainLabo",
    "content": "カプセルトイ 新商品 に関する投稿",
    "url": "https://x.com/drecap_MainLabo/status/2062118305071260138",
    "postedAt": "2026-06-03T17:00:45.101845+00:00",
    "matchedKeyword": "カプセルトイ 新商品"
  },
  {
    "id": "x_2062117979245175263",
    "platform": "X",
    "username": "@drecap_MainLabo",
    "content": "カプセルトイ 新商品 に関する投稿",
    "url": "https://x.com/drecap_MainLabo/status/2062117979245175263",
    "postedAt": "2026-06-03T17:00:45.101845+00:00",
    "matchedKeyword": "カプセルトイ 新商品"
  },
  {
    "id": "x_2062117742845772180",
    "platform": "X",
    "username": "@C_plaOdaka",
    "content": "カプセルトイ 新商品 に関する投稿",
    "url": "https://x.com/C_plaOdaka/status/2062117742845772180",
    "postedAt": "2026-06-03T17:00:45.101845+00:00",
    "matchedKeyword": "カプセルトイ 新商品"
  },
  {
    "id": "x_2062117666404630901",
    "platform": "X",
    "username": "@drecap_MainLabo",
    "content": "カプセルトイ 新商品 に関する投稿",
    "url": "https://x.com/drecap_MainLabo/status/2062117666404630901",
    "postedAt": "2026-06-03T17:00:45.101845+00:00",
    "matchedKeyword": "カプセルトイ 新商品"
  },
  {
    "id": "x_2062117418177282219",
    "platform": "X",
    "username": "@drecap_MainLabo",
    "content": "カプセルトイ 新商品 に関する投稿",
    "url": "https://x.com/drecap_MainLabo/status/2062117418177282219",
    "postedAt": "2026-06-03T17:00:45.101845+00:00",
    "matchedKeyword": "カプセルトイ 新商品"
  },
  {
    "id": "x_2062103949780627703",
    "platform": "X",
    "username": "@Cplus20240724",
    "content": "カプセルトイ 新商品 に関する投稿",
    "url": "https://x.com/Cplus20240724/status/2062103949780627703",
    "postedAt": "2026-06-03T17:00:45.101845+00:00",
    "matchedKeyword": "カプセルトイ 新商品"
  },
  {
    "id": "x_2062101783074480143",
    "platform": "X",
    "username": "@drecap_MainLabo",
    "content": "カプセルトイ 新商品 に関する投稿",
    "url": "https://x.com/drecap_MainLabo/status/2062101783074480143",
    "postedAt": "2026-06-03T17:00:45.101845+00:00",
    "matchedKeyword": "カプセルトイ 新商品"
  },
  {
    "id": "x_2062099330396508241",
    "platform": "X",
    "username": "@CplaWEST",
    "content": "カプセルトイ 新商品 に関する投稿",
    "url": "https://x.com/CplaWEST/status/2062099330396508241",
    "postedAt": "2026-06-03T17:00:45.101845+00:00",
    "matchedKeyword": "カプセルトイ 新商品"
  },
  {
    "id": "x_2062099284032688264",
    "platform": "X",
    "username": "@CplaWEST",
    "content": "カプセルトイ 新商品 に関する投稿",
    "url": "https://x.com/CplaWEST/status/2062099284032688264",
    "postedAt": "2026-06-03T17:00:45.101845+00:00",
    "matchedKeyword": "カプセルトイ 新商品"
  },
  {
    "id": "x_2062098396882850078",
    "platform": "X",
    "username": "@drecap_MainLabo",
    "content": "カプセルトイ 新商品 に関する投稿",
    "url": "https://x.com/drecap_MainLabo/status/2062098396882850078",
    "postedAt": "2026-06-03T17:00:45.101845+00:00",
    "matchedKeyword": "カプセルトイ 新商品"
  },
  {
    "id": "x_2062094820781539403",
    "platform": "X",
    "username": "@otakara_kobe",
    "content": "カプセルトイ 新商品 に関する投稿",
    "url": "https://x.com/otakara_kobe/status/2062094820781539403",
    "postedAt": "2026-06-03T17:00:45.101845+00:00",
    "matchedKeyword": "カプセルトイ 新商品"
  },
  {
    "id": "x_2062094081615090154",
    "platform": "X",
    "username": "@Cplus20240724",
    "content": "カプセルトイ 新商品 に関する投稿",
    "url": "https://x.com/Cplus20240724/status/2062094081615090154",
    "postedAt": "2026-06-03T17:00:45.101845+00:00",
    "matchedKeyword": "カプセルトイ 新商品"
  },
  {
    "id": "x_2062092139547500736",
    "platform": "X",
    "username": "@Cpla4106",
    "content": "カプセルトイ 新商品 に関する投稿",
    "url": "https://x.com/Cpla4106/status/2062092139547500736",
    "postedAt": "2026-06-03T17:00:45.101845+00:00",
    "matchedKeyword": "カプセルトイ 新商品"
  },
  {
    "id": "x_2062091196634448083",
    "platform": "X",
    "username": "@drecap_MainLabo",
    "content": "カプセルトイ 新商品 に関する投稿",
    "url": "https://x.com/drecap_MainLabo/status/2062091196634448083",
    "postedAt": "2026-06-03T17:00:45.101845+00:00",
    "matchedKeyword": "カプセルトイ 新商品"
  },
  {
    "id": "x_2062090484940722460",
    "platform": "X",
    "username": "@Cpla4106",
    "content": "カプセルトイ 新商品 に関する投稿",
    "url": "https://x.com/Cpla4106/status/2062090484940722460",
    "postedAt": "2026-06-03T17:00:45.101845+00:00",
    "matchedKeyword": "カプセルトイ 新商品"
  },
  {
    "id": "x_2062089771162493394",
    "platform": "X",
    "username": "@Cpla4106",
    "content": "カプセルトイ 新商品 に関する投稿",
    "url": "https://x.com/Cpla4106/status/2062089771162493394",
    "postedAt": "2026-06-03T17:00:45.101845+00:00",
    "matchedKeyword": "カプセルトイ 新商品"
  },
  {
    "id": "x_2062089415699366154",
    "platform": "X",
    "username": "@cpla_amukokura",
    "content": "カプセルトイ 新商品 に関する投稿",
    "url": "https://x.com/cpla_amukokura/status/2062089415699366154",
    "postedAt": "2026-06-03T17:00:45.101845+00:00",
    "matchedKeyword": "カプセルトイ 新商品"
  },
  {
    "id": "x_2062088212810699229",
    "platform": "X",
    "username": "@Cpla4106",
    "content": "カプセルトイ 新商品 に関する投稿",
    "url": "https://x.com/Cpla4106/status/2062088212810699229",
    "postedAt": "2026-06-03T17:00:45.101845+00:00",
    "matchedKeyword": "カプセルトイ 新商品"
  },
  {
    "id": "x_2062087684693389660",
    "platform": "X",
    "username": "@Cpla4106",
    "content": "カプセルトイ 新商品 に関する投稿",
    "url": "https://x.com/Cpla4106/status/2062087684693389660",
    "postedAt": "2026-06-03T17:00:45.101845+00:00",
    "matchedKeyword": "カプセルトイ 新商品"
  },
  {
    "id": "x_2062086770481930603",
    "platform": "X",
    "username": "@yumeyagotochiho",
    "content": "カプセルトイ 新商品 に関する投稿",
    "url": "https://x.com/yumeyagotochiho/status/2062086770481930603",
    "postedAt": "2026-06-03T17:00:45.101845+00:00",
    "matchedKeyword": "カプセルトイ 新商品"
  },
  {
    "id": "x_2062086072184746287",
    "platform": "X",
    "username": "@hDh4jXfZ4i8189",
    "content": "カプセルトイ 新商品 に関する投稿",
    "url": "https://x.com/hDh4jXfZ4i8189/status/2062086072184746287",
    "postedAt": "2026-06-03T17:00:45.101845+00:00",
    "matchedKeyword": "カプセルトイ 新商品"
  },
  {
    "id": "x_2062085757309976587",
    "platform": "X",
    "username": "@hDh4jXfZ4i8189",
    "content": "カプセルトイ 新商品 に関する投稿",
    "url": "https://x.com/hDh4jXfZ4i8189/status/2062085757309976587",
    "postedAt": "2026-06-03T17:00:45.101845+00:00",
    "matchedKeyword": "カプセルトイ 新商品"
  },
  {
    "id": "x_2062085713617879510",
    "platform": "X",
    "username": "@opa_pla",
    "content": "カプセルトイ 新商品 に関する投稿",
    "url": "https://x.com/opa_pla/status/2062085713617879510",
    "postedAt": "2026-06-03T17:00:45.101845+00:00",
    "matchedKeyword": "カプセルトイ 新商品"
  },
  {
    "id": "x_2062085689286820226",
    "platform": "X",
    "username": "@opa_pla",
    "content": "カプセルトイ 新商品 に関する投稿",
    "url": "https://x.com/opa_pla/status/2062085689286820226",
    "postedAt": "2026-06-03T17:00:45.101845+00:00",
    "matchedKeyword": "カプセルトイ 新商品"
  },
  {
    "id": "x_2062085678717194467",
    "platform": "X",
    "username": "@Cpla51",
    "content": "カプセルトイ 新商品 に関する投稿",
    "url": "https://x.com/Cpla51/status/2062085678717194467",
    "postedAt": "2026-06-03T17:00:45.101845+00:00",
    "matchedKeyword": "カプセルトイ 新商品"
  },
  {
    "id": "x_2062085493345701941",
    "platform": "X",
    "username": "@chiikawa_land",
    "content": "カプセルトイ 新商品 に関する投稿",
    "url": "https://x.com/chiikawa_land/status/2062085493345701941",
    "postedAt": "2026-06-03T17:00:45.101845+00:00",
    "matchedKeyword": "カプセルトイ 新商品"
  },
  {
    "id": "x_2062081113305305457",
    "platform": "X",
    "username": "@Cpla87116616",
    "content": "カプセルトイ 新商品 に関する投稿",
    "url": "https://x.com/Cpla87116616/status/2062081113305305457",
    "postedAt": "2026-06-03T17:00:45.101845+00:00",
    "matchedKeyword": "カプセルトイ 新商品"
  },
  {
    "id": "x_2062081074696773648",
    "platform": "X",
    "username": "@Cpla87116616",
    "content": "カプセルトイ 新商品 に関する投稿",
    "url": "https://x.com/Cpla87116616/status/2062081074696773648",
    "postedAt": "2026-06-03T17:00:45.101845+00:00",
    "matchedKeyword": "カプセルトイ 新商品"
  },
  {
    "id": "x_2062079543939325961",
    "platform": "X",
    "username": "@Cplakamiiso",
    "content": "カプセルトイ 新商品 に関する投稿",
    "url": "https://x.com/Cplakamiiso/status/2062079543939325961",
    "postedAt": "2026-06-03T17:00:45.101845+00:00",
    "matchedKeyword": "カプセルトイ 新商品"
  },
  {
    "id": "x_2062079278108582142",
    "platform": "X",
    "username": "@cpla1007",
    "content": "カプセルトイ 新商品 に関する投稿",
    "url": "https://x.com/cpla1007/status/2062079278108582142",
    "postedAt": "2026-06-03T17:00:45.101845+00:00",
    "matchedKeyword": "カプセルトイ 新商品"
  },
  {
    "id": "x_2062078923115261972",
    "platform": "X",
    "username": "@chiikawa_land",
    "content": "カプセルトイ 新商品 に関する投稿",
    "url": "https://x.com/chiikawa_land/status/2062078923115261972",
    "postedAt": "2026-06-03T17:00:45.101845+00:00",
    "matchedKeyword": "カプセルトイ 新商品"
  },
  {
    "id": "x_2062077819010863282",
    "platform": "X",
    "username": "@cplahakataguchi",
    "content": "カプセルトイ 新商品 に関する投稿",
    "url": "https://x.com/cplahakataguchi/status/2062077819010863282",
    "postedAt": "2026-06-03T17:00:45.101845+00:00",
    "matchedKeyword": "カプセルトイ 新商品"
  },
  {
    "id": "x_2062077200481079659",
    "platform": "X",
    "username": "@drecap_MainLabo",
    "content": "カプセルトイ 新商品 に関する投稿",
    "url": "https://x.com/drecap_MainLabo/status/2062077200481079659",
    "postedAt": "2026-06-03T17:00:45.101845+00:00",
    "matchedKeyword": "カプセルトイ 新商品"
  },
  {
    "id": "x_2062073880668414330",
    "platform": "X",
    "username": "@cpla_rasukahrtk",
    "content": "カプセルトイ 新商品 に関する投稿",
    "url": "https://x.com/cpla_rasukahrtk/status/2062073880668414330",
    "postedAt": "2026-06-03T17:00:45.101845+00:00",
    "matchedKeyword": "カプセルトイ 新商品"
  },
  {
    "id": "x_2062073511754244420",
    "platform": "X",
    "username": "@Cpla_totsuka",
    "content": "カプセルトイ 新商品 に関する投稿",
    "url": "https://x.com/Cpla_totsuka/status/2062073511754244420",
    "postedAt": "2026-06-03T17:00:45.101845+00:00",
    "matchedKeyword": "カプセルトイ 新商品"
  },
  {
    "id": "x_2062073489113358668",
    "platform": "X",
    "username": "@Cpla_totsuka",
    "content": "カプセルトイ 新商品 に関する投稿",
    "url": "https://x.com/Cpla_totsuka/status/2062073489113358668",
    "postedAt": "2026-06-03T17:00:45.101845+00:00",
    "matchedKeyword": "カプセルトイ 新商品"
  },
  {
    "id": "x_2062065816578007299",
    "platform": "X",
    "username": "@drecap_MainLabo",
    "content": "カプセルトイ 新商品 に関する投稿",
    "url": "https://x.com/drecap_MainLabo/status/2062065816578007299",
    "postedAt": "2026-06-03T17:00:45.101845+00:00",
    "matchedKeyword": "カプセルトイ 新商品"
  },
  {
    "id": "x_2062058981858939242",
    "platform": "X",
    "username": "@Cplamayone1223",
    "content": "カプセルトイ 新商品 に関する投稿",
    "url": "https://x.com/Cplamayone1223/status/2062058981858939242",
    "postedAt": "2026-06-03T17:00:45.101845+00:00",
    "matchedKeyword": "カプセルトイ 新商品"
  },
  {
    "id": "x_2062006860207571284",
    "platform": "X",
    "username": "@sugardoll_game",
    "content": "ガチャ 新作 に関する投稿",
    "url": "https://x.com/sugardoll_game/status/2062006860207571284",
    "postedAt": "2026-06-03T17:00:43.770497+00:00",
    "matchedKeyword": "ガチャ 新作"
  },
  {
    "id": "x_2062191954419745185",
    "platform": "X",
    "username": "@CKDUMBWiEH95042",
    "content": "ガチャ 新作 に関する投稿",
    "url": "https://x.com/CKDUMBWiEH95042/status/2062191954419745185",
    "postedAt": "2026-06-03T17:00:43.770497+00:00",
    "matchedKeyword": "ガチャ 新作"
  },
  {
    "id": "x_2062184777600634939",
    "platform": "X",
    "username": "@SeaMo46",
    "content": "ガチャ 新作 に関する投稿",
    "url": "https://x.com/SeaMo46/status/2062184777600634939",
    "postedAt": "2026-06-03T17:00:43.770497+00:00",
    "matchedKeyword": "ガチャ 新作"
  },
  {
    "id": "x_2062182653097570779",
    "platform": "X",
    "username": "@antashena__",
    "content": "ガチャ 新作 に関する投稿",
    "url": "https://x.com/antashena__/status/2062182653097570779",
    "postedAt": "2026-06-03T17:00:43.770497+00:00",
    "matchedKeyword": "ガチャ 新作"
  },
  {
    "id": "x_2062180306879418820",
    "platform": "X",
    "username": "@shachom_js",
    "content": "ガチャ 新作 に関する投稿",
    "url": "https://x.com/shachom_js/status/2062180306879418820",
    "postedAt": "2026-06-03T17:00:43.770497+00:00",
    "matchedKeyword": "ガチャ 新作"
  },
  {
    "id": "x_2062177111503425698",
    "platform": "X",
    "username": "@bukkomi_nika",
    "content": "ガチャ 新作 に関する投稿",
    "url": "https://x.com/bukkomi_nika/status/2062177111503425698",
    "postedAt": "2026-06-03T17:00:43.770497+00:00",
    "matchedKeyword": "ガチャ 新作"
  },
  {
    "id": "x_2062176098939744279",
    "platform": "X",
    "username": "@lala_lalala333",
    "content": "ガチャ 新作 に関する投稿",
    "url": "https://x.com/lala_lalala333/status/2062176098939744279",
    "postedAt": "2026-06-03T17:00:43.770497+00:00",
    "matchedKeyword": "ガチャ 新作"
  },
  {
    "id": "x_2062174147707572279",
    "platform": "X",
    "username": "@hjn_airr",
    "content": "ガチャ 新作 に関する投稿",
    "url": "https://x.com/hjn_airr/status/2062174147707572279",
    "postedAt": "2026-06-03T17:00:43.770497+00:00",
    "matchedKeyword": "ガチャ 新作"
  },
  {
    "id": "x_2062172465284223054",
    "platform": "X",
    "username": "@pairium_info",
    "content": "ガチャ 新作 に関する投稿",
    "url": "https://x.com/pairium_info/status/2062172465284223054",
    "postedAt": "2026-06-03T17:00:43.770497+00:00",
    "matchedKeyword": "ガチャ 新作"
  },
  {
    "id": "x_2062169240740962371",
    "platform": "X",
    "username": "@umariya41",
    "content": "ガチャ 新作 に関する投稿",
    "url": "https://x.com/umariya41/status/2062169240740962371",
    "postedAt": "2026-06-03T17:00:43.770497+00:00",
    "matchedKeyword": "ガチャ 新作"
  },
  {
    "id": "x_2062168569023213632",
    "platform": "X",
    "username": "@natuki4144",
    "content": "ガチャ 新作 に関する投稿",
    "url": "https://x.com/natuki4144/status/2062168569023213632",
    "postedAt": "2026-06-03T17:00:43.770497+00:00",
    "matchedKeyword": "ガチャ 新作"
  },
  {
    "id": "x_2062167292910395655",
    "platform": "X",
    "username": "@sumire3d",
    "content": "ガチャ 新作 に関する投稿",
    "url": "https://x.com/sumire3d/status/2062167292910395655",
    "postedAt": "2026-06-03T17:00:43.770497+00:00",
    "matchedKeyword": "ガチャ 新作"
  },
  {
    "id": "x_2062166094711025961",
    "platform": "X",
    "username": "@hichan_main",
    "content": "ガチャ 新作 に関する投稿",
    "url": "https://x.com/hichan_main/status/2062166094711025961",
    "postedAt": "2026-06-03T17:00:43.770497+00:00",
    "matchedKeyword": "ガチャ 新作"
  },
  {
    "id": "x_2062165972765827248",
    "platform": "X",
    "username": "@higayume705",
    "content": "ガチャ 新作 に関する投稿",
    "url": "https://x.com/higayume705/status/2062165972765827248",
    "postedAt": "2026-06-03T17:00:43.770497+00:00",
    "matchedKeyword": "ガチャ 新作"
  },
  {
    "id": "x_2062165422561222796",
    "platform": "X",
    "username": "@newcalib",
    "content": "ガチャ 新作 に関する投稿",
    "url": "https://x.com/newcalib/status/2062165422561222796",
    "postedAt": "2026-06-03T17:00:43.770497+00:00",
    "matchedKeyword": "ガチャ 新作"
  },
  {
    "id": "x_2062163805845835919",
    "platform": "X",
    "username": "@yumecyandayo",
    "content": "ガチャ 新作 に関する投稿",
    "url": "https://x.com/yumecyandayo/status/2062163805845835919",
    "postedAt": "2026-06-03T17:00:43.770497+00:00",
    "matchedKeyword": "ガチャ 新作"
  },
  {
    "id": "x_2062162924601557238",
    "platform": "X",
    "username": "@Tamayasha460",
    "content": "ガチャ 新作 に関する投稿",
    "url": "https://x.com/Tamayasha460/status/2062162924601557238",
    "postedAt": "2026-06-03T17:00:43.770497+00:00",
    "matchedKeyword": "ガチャ 新作"
  },
  {
    "id": "x_2062160799414595704",
    "platform": "X",
    "username": "@yumegachayrri",
    "content": "ガチャ 新作 に関する投稿",
    "url": "https://x.com/yumegachayrri/status/2062160799414595704",
    "postedAt": "2026-06-03T17:00:43.770497+00:00",
    "matchedKeyword": "ガチャ 新作"
  },
  {
    "id": "x_2062157370193846667",
    "platform": "X",
    "username": "@pairium_info",
    "content": "ガチャ 新作 に関する投稿",
    "url": "https://x.com/pairium_info/status/2062157370193846667",
    "postedAt": "2026-06-03T17:00:43.770497+00:00",
    "matchedKeyword": "ガチャ 新作"
  },
  {
    "id": "x_2062152330049700078",
    "platform": "X",
    "username": "@nami_linpla1003",
    "content": "ガチャ 新作 に関する投稿",
    "url": "https://x.com/nami_linpla1003/status/2062152330049700078",
    "postedAt": "2026-06-03T17:00:43.770497+00:00",
    "matchedKeyword": "ガチャ 新作"
  },
  {
    "id": "x_2062145099073753482",
    "platform": "X",
    "username": "@blueflo3ers",
    "content": "ガチャ 新作 に関する投稿",
    "url": "https://x.com/blueflo3ers/status/2062145099073753482",
    "postedAt": "2026-06-03T17:00:43.770497+00:00",
    "matchedKeyword": "ガチャ 新作"
  },
  {
    "id": "x_2062140379890340270",
    "platform": "X",
    "username": "@Dorima8_info",
    "content": "ガチャ 新作 に関する投稿",
    "url": "https://x.com/Dorima8_info/status/2062140379890340270",
    "postedAt": "2026-06-03T17:00:43.770497+00:00",
    "matchedKeyword": "ガチャ 新作"
  },
  {
    "id": "x_2062128729661505963",
    "platform": "X",
    "username": "@Soya_29krn",
    "content": "ガチャ 新作 に関する投稿",
    "url": "https://x.com/Soya_29krn/status/2062128729661505963",
    "postedAt": "2026-06-03T17:00:43.770497+00:00",
    "matchedKeyword": "ガチャ 新作"
  },
  {
    "id": "x_2062128597285118192",
    "platform": "X",
    "username": "@ms_gachagacha",
    "content": "ガチャ 新作 に関する投稿",
    "url": "https://x.com/ms_gachagacha/status/2062128597285118192",
    "postedAt": "2026-06-03T17:00:43.770497+00:00",
    "matchedKeyword": "ガチャ 新作"
  },
  {
    "id": "x_2062127162036236676",
    "platform": "X",
    "username": "@pairium_info",
    "content": "ガチャ 新作 に関する投稿",
    "url": "https://x.com/pairium_info/status/2062127162036236676",
    "postedAt": "2026-06-03T17:00:43.770497+00:00",
    "matchedKeyword": "ガチャ 新作"
  },
  {
    "id": "x_2062124654614204715",
    "platform": "X",
    "username": "@7a_____n",
    "content": "ガチャ 新作 に関する投稿",
    "url": "https://x.com/7a_____n/status/2062124654614204715",
    "postedAt": "2026-06-03T17:00:43.770497+00:00",
    "matchedKeyword": "ガチャ 新作"
  },
  {
    "id": "x_2062121633851273717",
    "platform": "X",
    "username": "@rUZjIMlglH35542",
    "content": "ガチャ 新作 に関する投稿",
    "url": "https://x.com/rUZjIMlglH35542/status/2062121633851273717",
    "postedAt": "2026-06-03T17:00:43.770497+00:00",
    "matchedKeyword": "ガチャ 新作"
  },
  {
    "id": "x_2062119395057664411",
    "platform": "X",
    "username": "@Barnardradio",
    "content": "ガチャ 新作 に関する投稿",
    "url": "https://x.com/Barnardradio/status/2062119395057664411",
    "postedAt": "2026-06-03T17:00:43.770497+00:00",
    "matchedKeyword": "ガチャ 新作"
  },
  {
    "id": "x_2062118907247480896",
    "platform": "X",
    "username": "@pokemon_omiki",
    "content": "ガチャ 新作 に関する投稿",
    "url": "https://x.com/pokemon_omiki/status/2062118907247480896",
    "postedAt": "2026-06-03T17:00:43.770497+00:00",
    "matchedKeyword": "ガチャ 新作"
  },
  {
    "id": "x_2062116300445700110",
    "platform": "X",
    "username": "@Hot_U27",
    "content": "ガチャ 新作 に関する投稿",
    "url": "https://x.com/Hot_U27/status/2062116300445700110",
    "postedAt": "2026-06-03T17:00:43.770497+00:00",
    "matchedKeyword": "ガチャ 新作"
  },
  {
    "id": "x_2062113843351044348",
    "platform": "X",
    "username": "@umariya41",
    "content": "ガチャ 新作 に関する投稿",
    "url": "https://x.com/umariya41/status/2062113843351044348",
    "postedAt": "2026-06-03T17:00:43.770497+00:00",
    "matchedKeyword": "ガチャ 新作"
  },
  {
    "id": "x_2062112619532833095",
    "platform": "X",
    "username": "@santosdayom",
    "content": "ガチャ 新作 に関する投稿",
    "url": "https://x.com/santosdayom/status/2062112619532833095",
    "postedAt": "2026-06-03T17:00:43.770497+00:00",
    "matchedKeyword": "ガチャ 新作"
  },
  {
    "id": "x_2062112054362972457",
    "platform": "X",
    "username": "@osanairayura",
    "content": "ガチャ 新作 に関する投稿",
    "url": "https://x.com/osanairayura/status/2062112054362972457",
    "postedAt": "2026-06-03T17:00:43.770497+00:00",
    "matchedKeyword": "ガチャ 新作"
  },
  {
    "id": "x_2062108474331607328",
    "platform": "X",
    "username": "@oripacity",
    "content": "ガチャ 新作 に関する投稿",
    "url": "https://x.com/oripacity/status/2062108474331607328",
    "postedAt": "2026-06-03T17:00:43.770497+00:00",
    "matchedKeyword": "ガチャ 新作"
  },
  {
    "id": "x_2062103057509576831",
    "platform": "X",
    "username": "@m_ira_1212",
    "content": "ガチャ 新作 に関する投稿",
    "url": "https://x.com/m_ira_1212/status/2062103057509576831",
    "postedAt": "2026-06-03T17:00:43.770497+00:00",
    "matchedKeyword": "ガチャ 新作"
  },
  {
    "id": "x_2062097568113594488",
    "platform": "X",
    "username": "@Okudayukolem6",
    "content": "ガチャ 新作 に関する投稿",
    "url": "https://x.com/Okudayukolem6/status/2062097568113594488",
    "postedAt": "2026-06-03T17:00:43.770497+00:00",
    "matchedKeyword": "ガチャ 新作"
  },
  {
    "id": "x_2062096249722183917",
    "platform": "X",
    "username": "@wander_in_the",
    "content": "ガチャ 新作 に関する投稿",
    "url": "https://x.com/wander_in_the/status/2062096249722183917",
    "postedAt": "2026-06-03T17:00:43.770497+00:00",
    "matchedKeyword": "ガチャ 新作"
  },
  {
    "id": "x_2062095620698255692",
    "platform": "X",
    "username": "@topazeye_xxx",
    "content": "ガチャ 新作 に関する投稿",
    "url": "https://x.com/topazeye_xxx/status/2062095620698255692",
    "postedAt": "2026-06-03T17:00:43.770497+00:00",
    "matchedKeyword": "ガチャ 新作"
  },
  {
    "id": "x_2062093969803350161",
    "platform": "X",
    "username": "@choko_choko_poi",
    "content": "ガチャ 新作 に関する投稿",
    "url": "https://x.com/choko_choko_poi/status/2062093969803350161",
    "postedAt": "2026-06-03T17:00:43.770497+00:00",
    "matchedKeyword": "ガチャ 新作"
  },
  {
    "id": "x_2062093340301304062",
    "platform": "X",
    "username": "@mary_store_146",
    "content": "ガチャ 新作 に関する投稿",
    "url": "https://x.com/mary_store_146/status/2062093340301304062",
    "postedAt": "2026-06-03T17:00:43.770497+00:00",
    "matchedKeyword": "ガチャ 新作"
  },
  {
    "id": "x_2062022151675548038",
    "platform": "X",
    "username": "@Stray_Kids_JP",
    "content": "ガシャポン 新商品 に関する投稿",
    "url": "https://x.com/Stray_Kids_JP/status/2062022151675548038",
    "postedAt": "2026-06-03T17:00:42.125867+00:00",
    "matchedKeyword": "ガシャポン 新商品"
  },
  {
    "id": "x_2062124118477267420",
    "platform": "X",
    "username": "@koimaru0322",
    "content": "ガシャポン 新商品 に関する投稿",
    "url": "https://x.com/koimaru0322/status/2062124118477267420",
    "postedAt": "2026-06-03T17:00:42.125867+00:00",
    "matchedKeyword": "ガシャポン 新商品"
  },
  {
    "id": "x_2062118428996165904",
    "platform": "X",
    "username": "@gasha_Eykhm",
    "content": "ガシャポン 新商品 に関する投稿",
    "url": "https://x.com/gasha_Eykhm/status/2062118428996165904",
    "postedAt": "2026-06-03T17:00:42.125867+00:00",
    "matchedKeyword": "ガシャポン 新商品"
  },
  {
    "id": "x_2062095448425570706",
    "platform": "X",
    "username": "@gasha_hakatabt",
    "content": "ガシャポン 新商品 に関する投稿",
    "url": "https://x.com/gasha_hakatabt/status/2062095448425570706",
    "postedAt": "2026-06-03T17:00:42.125867+00:00",
    "matchedKeyword": "ガシャポン 新商品"
  },
  {
    "id": "x_2062084254943863096",
    "platform": "X",
    "username": "@gasha_m_asahi",
    "content": "ガシャポン 新商品 に関する投稿",
    "url": "https://x.com/gasha_m_asahi/status/2062084254943863096",
    "postedAt": "2026-06-03T17:00:42.125867+00:00",
    "matchedKeyword": "ガシャポン 新商品"
  },
  {
    "id": "x_2062083375004013038",
    "platform": "X",
    "username": "@gasha_m_asahi",
    "content": "ガシャポン 新商品 に関する投稿",
    "url": "https://x.com/gasha_m_asahi/status/2062083375004013038",
    "postedAt": "2026-06-03T17:00:42.125867+00:00",
    "matchedKeyword": "ガシャポン 新商品"
  },
  {
    "id": "x_2062082534587191331",
    "platform": "X",
    "username": "@gasha_m_asahi",
    "content": "ガシャポン 新商品 に関する投稿",
    "url": "https://x.com/gasha_m_asahi/status/2062082534587191331",
    "postedAt": "2026-06-03T17:00:42.125867+00:00",
    "matchedKeyword": "ガシャポン 新商品"
  },
  {
    "id": "x_2062082316760174781",
    "platform": "X",
    "username": "@gasha_Eykhm",
    "content": "ガシャポン 新商品 に関する投稿",
    "url": "https://x.com/gasha_Eykhm/status/2062082316760174781",
    "postedAt": "2026-06-03T17:00:42.125867+00:00",
    "matchedKeyword": "ガシャポン 新商品"
  },
  {
    "id": "x_2062081400216723481",
    "platform": "X",
    "username": "@gasha_m_asahi",
    "content": "ガシャポン 新商品 に関する投稿",
    "url": "https://x.com/gasha_m_asahi/status/2062081400216723481",
    "postedAt": "2026-06-03T17:00:42.125867+00:00",
    "matchedKeyword": "ガシャポン 新商品"
  },
  {
    "id": "x_2062081380360815055",
    "platform": "X",
    "username": "@gasha_m_asahi",
    "content": "ガシャポン 新商品 に関する投稿",
    "url": "https://x.com/gasha_m_asahi/status/2062081380360815055",
    "postedAt": "2026-06-03T17:00:42.125867+00:00",
    "matchedKeyword": "ガシャポン 新商品"
  },
  {
    "id": "x_2062081358533697781",
    "platform": "X",
    "username": "@gasha_m_asahi",
    "content": "ガシャポン 新商品 に関する投稿",
    "url": "https://x.com/gasha_m_asahi/status/2062081358533697781",
    "postedAt": "2026-06-03T17:00:42.125867+00:00",
    "matchedKeyword": "ガシャポン 新商品"
  },
  {
    "id": "x_2062081219811315936",
    "platform": "X",
    "username": "@gasha_m_asahi",
    "content": "ガシャポン 新商品 に関する投稿",
    "url": "https://x.com/gasha_m_asahi/status/2062081219811315936",
    "postedAt": "2026-06-03T17:00:42.125867+00:00",
    "matchedKeyword": "ガシャポン 新商品"
  },
  {
    "id": "x_2062080442078228535",
    "platform": "X",
    "username": "@gasha_k_snyr",
    "content": "ガシャポン 新商品 に関する投稿",
    "url": "https://x.com/gasha_k_snyr/status/2062080442078228535",
    "postedAt": "2026-06-03T17:00:42.125867+00:00",
    "matchedKeyword": "ガシャポン 新商品"
  },
  {
    "id": "x_2062077275391377761",
    "platform": "X",
    "username": "@gasha_m_asahi",
    "content": "ガシャポン 新商品 に関する投稿",
    "url": "https://x.com/gasha_m_asahi/status/2062077275391377761",
    "postedAt": "2026-06-03T17:00:42.125867+00:00",
    "matchedKeyword": "ガシャポン 新商品"
  },
  {
    "id": "x_2062068867829321910",
    "platform": "X",
    "username": "@qPNXWvIMNP5Lypa",
    "content": "ガシャポン 新商品 に関する投稿",
    "url": "https://x.com/qPNXWvIMNP5Lypa/status/2062068867829321910",
    "postedAt": "2026-06-03T17:00:42.125867+00:00",
    "matchedKeyword": "ガシャポン 新商品"
  },
  {
    "id": "x_2062062831181463861",
    "platform": "X",
    "username": "@GBO_minamifur",
    "content": "ガシャポン 新商品 に関する投稿",
    "url": "https://x.com/GBO_minamifur/status/2062062831181463861",
    "postedAt": "2026-06-03T17:00:42.125867+00:00",
    "matchedKeyword": "ガシャポン 新商品"
  },
  {
    "id": "x_2062062459582878030",
    "platform": "X",
    "username": "@gasha_b_nsn3",
    "content": "ガシャポン 新商品 に関する投稿",
    "url": "https://x.com/gasha_b_nsn3/status/2062062459582878030",
    "postedAt": "2026-06-03T17:00:42.125867+00:00",
    "matchedKeyword": "ガシャポン 新商品"
  },
  {
    "id": "x_2062062419338543437",
    "platform": "X",
    "username": "@GBO_minamifur",
    "content": "ガシャポン 新商品 に関する投稿",
    "url": "https://x.com/GBO_minamifur/status/2062062419338543437",
    "postedAt": "2026-06-03T17:00:42.125867+00:00",
    "matchedKeyword": "ガシャポン 新商品"
  },
  {
    "id": "x_2062057119575322882",
    "platform": "X",
    "username": "@gasha_akeno",
    "content": "ガシャポン 新商品 に関する投稿",
    "url": "https://x.com/gasha_akeno/status/2062057119575322882",
    "postedAt": "2026-06-03T17:00:42.125867+00:00",
    "matchedKeyword": "ガシャポン 新商品"
  },
  {
    "id": "x_2062056254768570669",
    "platform": "X",
    "username": "@GBO_hakata",
    "content": "ガシャポン 新商品 に関する投稿",
    "url": "https://x.com/GBO_hakata/status/2062056254768570669",
    "postedAt": "2026-06-03T17:00:42.125867+00:00",
    "matchedKeyword": "ガシャポン 新商品"
  },
  {
    "id": "x_2062055491405234493",
    "platform": "X",
    "username": "@gasha_bklucy",
    "content": "ガシャポン 新商品 に関する投稿",
    "url": "https://x.com/gasha_bklucy/status/2062055491405234493",
    "postedAt": "2026-06-03T17:00:42.125867+00:00",
    "matchedKeyword": "ガシャポン 新商品"
  },
  {
    "id": "x_2062053518459179051",
    "platform": "X",
    "username": "@gasha_bklucy",
    "content": "ガシャポン 新商品 に関する投稿",
    "url": "https://x.com/gasha_bklucy/status/2062053518459179051",
    "postedAt": "2026-06-03T17:00:42.125867+00:00",
    "matchedKeyword": "ガシャポン 新商品"
  },
  {
    "id": "x_2062051939119202734",
    "platform": "X",
    "username": "@gasha_bklucy",
    "content": "ガシャポン 新商品 に関する投稿",
    "url": "https://x.com/gasha_bklucy/status/2062051939119202734",
    "postedAt": "2026-06-03T17:00:42.125867+00:00",
    "matchedKeyword": "ガシャポン 新商品"
  },
  {
    "id": "x_2062051374796591318",
    "platform": "X",
    "username": "@GBO_hakata",
    "content": "ガシャポン 新商品 に関する投稿",
    "url": "https://x.com/GBO_hakata/status/2062051374796591318",
    "postedAt": "2026-06-03T17:00:42.125867+00:00",
    "matchedKeyword": "ガシャポン 新商品"
  },
  {
    "id": "x_2062046528785822031",
    "platform": "X",
    "username": "@GBO_lala_izm",
    "content": "ガシャポン 新商品 に関する投稿",
    "url": "https://x.com/GBO_lala_izm/status/2062046528785822031",
    "postedAt": "2026-06-03T17:00:42.125867+00:00",
    "matchedKeyword": "ガシャポン 新商品"
  },
  {
    "id": "x_2062040096900325649",
    "platform": "X",
    "username": "@gasha_hakatabt",
    "content": "ガシャポン 新商品 に関する投稿",
    "url": "https://x.com/gasha_hakatabt/status/2062040096900325649",
    "postedAt": "2026-06-03T17:00:42.125867+00:00",
    "matchedKeyword": "ガシャポン 新商品"
  },
  {
    "id": "x_2062036545033621643",
    "platform": "X",
    "username": "@gasha_hakatabt",
    "content": "ガシャポン 新商品 に関する投稿",
    "url": "https://x.com/gasha_hakatabt/status/2062036545033621643",
    "postedAt": "2026-06-03T17:00:42.125867+00:00",
    "matchedKeyword": "ガシャポン 新商品"
  },
  {
    "id": "x_2062033388941562082",
    "platform": "X",
    "username": "@GBO_t_utnmy",
    "content": "ガシャポン 新商品 に関する投稿",
    "url": "https://x.com/GBO_t_utnmy/status/2062033388941562082",
    "postedAt": "2026-06-03T17:00:42.125867+00:00",
    "matchedKeyword": "ガシャポン 新商品"
  },
  {
    "id": "x_2062026307467456869",
    "platform": "X",
    "username": "@GBO_ogaki",
    "content": "ガシャポン 新商品 に関する投稿",
    "url": "https://x.com/GBO_ogaki/status/2062026307467456869",
    "postedAt": "2026-06-03T17:00:42.125867+00:00",
    "matchedKeyword": "ガシャポン 新商品"
  },
  {
    "id": "x_2062025004716540272",
    "platform": "X",
    "username": "@gasha_b_kotoni",
    "content": "ガシャポン 新商品 に関する投稿",
    "url": "https://x.com/gasha_b_kotoni/status/2062025004716540272",
    "postedAt": "2026-06-03T17:00:42.125867+00:00",
    "matchedKeyword": "ガシャポン 新商品"
  },
  {
    "id": "x_2062022354889482497",
    "platform": "X",
    "username": "@GBO_ageo",
    "content": "ガシャポン 新商品 に関する投稿",
    "url": "https://x.com/GBO_ageo/status/2062022354889482497",
    "postedAt": "2026-06-03T17:00:42.125867+00:00",
    "matchedKeyword": "ガシャポン 新商品"
  },
  {
    "id": "x_2062022258424697247",
    "platform": "X",
    "username": "@GBO_ageo",
    "content": "ガシャポン 新商品 に関する投稿",
    "url": "https://x.com/GBO_ageo/status/2062022258424697247",
    "postedAt": "2026-06-03T17:00:42.125867+00:00",
    "matchedKeyword": "ガシャポン 新商品"
  },
  {
    "id": "x_2062022108788744447",
    "platform": "X",
    "username": "@GBO_ageo",
    "content": "ガシャポン 新商品 に関する投稿",
    "url": "https://x.com/GBO_ageo/status/2062022108788744447",
    "postedAt": "2026-06-03T17:00:42.125867+00:00",
    "matchedKeyword": "ガシャポン 新商品"
  },
  {
    "id": "x_2062021729422295206",
    "platform": "X",
    "username": "@Gashapon_Bandai",
    "content": "ガシャポン 新商品 に関する投稿",
    "url": "https://x.com/Gashapon_Bandai/status/2062021729422295206",
    "postedAt": "2026-06-03T17:00:42.125867+00:00",
    "matchedKeyword": "ガシャポン 新商品"
  },
  {
    "id": "x_2062021254337753217",
    "platform": "X",
    "username": "@gasha_b_kotoni",
    "content": "ガシャポン 新商品 に関する投稿",
    "url": "https://x.com/gasha_b_kotoni/status/2062021254337753217",
    "postedAt": "2026-06-03T17:00:42.125867+00:00",
    "matchedKeyword": "ガシャポン 新商品"
  },
  {
    "id": "x_2062021098569642459",
    "platform": "X",
    "username": "@GBO_ageo",
    "content": "ガシャポン 新商品 に関する投稿",
    "url": "https://x.com/GBO_ageo/status/2062021098569642459",
    "postedAt": "2026-06-03T17:00:42.125867+00:00",
    "matchedKeyword": "ガシャポン 新商品"
  },
  {
    "id": "x_2062020989551346062",
    "platform": "X",
    "username": "@GBO_ageo",
    "content": "ガシャポン 新商品 に関する投稿",
    "url": "https://x.com/GBO_ageo/status/2062020989551346062",
    "postedAt": "2026-06-03T17:00:42.125867+00:00",
    "matchedKeyword": "ガシャポン 新商品"
  },
  {
    "id": "x_2062020899818353045",
    "platform": "X",
    "username": "@GBO_ageo",
    "content": "ガシャポン 新商品 に関する投稿",
    "url": "https://x.com/GBO_ageo/status/2062020899818353045",
    "postedAt": "2026-06-03T17:00:42.125867+00:00",
    "matchedKeyword": "ガシャポン 新商品"
  },
  {
    "id": "x_2062020784554741828",
    "platform": "X",
    "username": "@GBO_ageo",
    "content": "ガシャポン 新商品 に関する投稿",
    "url": "https://x.com/GBO_ageo/status/2062020784554741828",
    "postedAt": "2026-06-03T17:00:42.125867+00:00",
    "matchedKeyword": "ガシャポン 新商品"
  },
  {
    "id": "x_2062020673346977875",
    "platform": "X",
    "username": "@GBO_ageo",
    "content": "ガシャポン 新商品 に関する投稿",
    "url": "https://x.com/GBO_ageo/status/2062020673346977875",
    "postedAt": "2026-06-03T17:00:42.125867+00:00",
    "matchedKeyword": "ガシャポン 新商品"
  }
]